Workbook
Name MONTH: 'Base Data'!$B$15
Name IND_YEAR_1: 'Base Data'!$E$8
Name YEAR_4: 'Base Data'!$B$11
Name IND_YEAR_6: 'Base Data'!$E$13
Name IND_YEAR_5: 'Base Data'!$E$12
Name YEAR_1: 'Base Data'!$B$8
Name IND_YEAR_2: 'Base Data'!$E$9
Name SP_EXCEL_LINK_7353616ca9ac4baea658f5be2f83c964: OVERVIEW!$B$8:$BT$82
Name YEAR_3: 'Base Data'!$B$10
Name COMP: 'Base Data'!$B$5
Name YEAR_2: 'Base Data'!$B$9
Name YEAR_6: 'Base Data'!$B$13
Name IND_YEAR_3: 'Base Data'!$E$10
Name SP_EXCEL_LINK_ffb73710684542a98aad81c21bf8ac33: #REF!
Name YEAR_5: 'Base Data'!$B$12
Name YEAR: 'Base Data'!$B$7
Name IND_YEAR_4: 'Base Data'!$E$11

Sheet OVERVIEW
B1: Comp | D1: =+COMP -> ZHY | E1: =+COMP -> ZHY | F1: =+COMP -> ZHY | G1: =+COMP -> ZHY | H1: =+COMP -> ZHY | I1: =+COMP -> ZHY | J1: =+COMP -> ZHY | K1: =+COMP -> ZHY | ... P1: =+COMP -> ZHY | R1: =+COMP -> ZHY | S1: =+COMP -> ZHY | T1: =+COMP -> ZHY | U1: =+COMP -> ZHY | V1: =+COMP -> ZHY | W1: =+COMP -> ZHY | X1: =+COMP -> ZHY | Y1: =+COMP -> ZHY | ... AD1: =+COMP -> ZHY | AF1: =+COMP -> ZHY | AG1: =+COMP -> ZHY | AH1: =+COMP -> ZHY | AI1: =+COMP -> ZHY | AJ1: =+COMP -> ZHY | AK1: =+COMP -> ZHY | AL1: =+COMP -> ZHY | AM1: =+COMP -> ZHY | ... AR1: =+COMP -> ZHY | AT1: =+COMP -> ZHY | AU1: =+COMP -> ZHY | AV1: =+COMP -> ZHY | AW1: =+COMP -> ZHY | AX1: =+COMP -> ZHY | AY1: =+COMP -> ZHY | AZ1: =+COMP -> ZHY | BA1: =+COMP -> ZHY | ... BF1: =+COMP -> ZHY | BH1: =+COMP -> ZHY | BI1: =+COMP -> ZHY | BJ1: =+COMP -> ZHY | BK1: =+COMP -> ZHY | BL1: =+COMP -> ZHY | BM1: =+COMP -> ZHY | BN1: =+COMP -> ZHY | BO1: =+COMP -> ZHY | ... BT1: =+COMP -> ZHY | BV1: =+COMP -> ZHY | BW1: =+COMP -> ZHY | BX1: =+COMP -> ZHY | BY1: =+COMP -> ZHY | BZ1: =+COMP -> ZHY | CA1: =+COMP -> ZHY | CB1: =+COMP -> ZHY | CC1: =+COMP -> ZHY | ... CH1: =+COMP -> ZHY
B2: YEAR | D2: =+YEAR -> 2025 | E2: =+YEAR -> 2025 | F2: =+YEAR -> 2025 | G2: =+YEAR -> 2025 | H2: =+YEAR -> 2025 | I2: =+YEAR -> 2025 | J2: =+YEAR -> 2025 | K2: =+YEAR -> 2025 | ... P2: =+YEAR -> 2025 | R2: =+YEAR_1 -> 2026 | S2: =+YEAR_1 -> 2026 | T2: =+YEAR_1 -> 2026 | U2: =+YEAR_1 -> 2026 | V2: =+YEAR_1 -> 2026 | W2: =+YEAR_1 -> 2026 | X2: =+YEAR_1 -> 2026 | Y2: =+YEAR_1 -> 2026 | ... AD2: =+YEAR_1 -> 2026 | AF2: =+YEAR_2 -> 2027 | AG2: =+YEAR_2 -> 2027 | AH2: =+YEAR_2 -> 2027 | AI2: =+YEAR_2 -> 2027 | AJ2: =+YEAR_2 -> 2027 | AK2: =+YEAR_2 -> 2027 | AL2: =+YEAR_2 -> 2027 | AM2: =+YEAR_2 -> 2027 | ... AR2: =+YEAR_2 -> 2027 | AT2: =+YEAR_3 -> 2028 | AU2: =+YEAR_3 -> 2028 | AV2: =+YEAR_3 -> 2028 | AW2: =+YEAR_3 -> 2028 | AX2: =+YEAR_3 -> 2028 | AY2: =+YEAR_3 -> 2028 | AZ2: =+YEAR_3 -> 2028 | BA2: =+YEAR_3 -> 2028 | ... BF2: =+YEAR_3 -> 2028 | BH2: =+YEAR_4 -> 2029 | BI2: =+YEAR_4 -> 2029 | BJ2: =+YEAR_4 -> 2029 | BK2: =+YEAR_4 -> 2029 | BL2: =+YEAR_4 -> 2029 | BM2: =+YEAR_4 -> 2029 | BN2: =+YEAR_4 -> 2029 | BO2: =+YEAR_4 -> 2029 | ... BT2: =+YEAR_4 -> 2029 | BV2: =+YEAR_5 -> 2030 | BW2: =+YEAR_5 -> 2030 | BX2: =+YEAR_5 -> 2030 | BY2: =+YEAR_5 -> 2030 | BZ2: =+YEAR_5 -> 2030 | CA2: =+YEAR_5 -> 2030 | CB2: =+YEAR_5 -> 2030 | CC2: =+YEAR_5 -> 2030 | ... CH2: =+YEAR_5 -> 2030
B3: Version | D3: P&L | E3: P&L | F3: P&L | G3: P&L | H3: P&L | I3: P&L | J3: P&L | K3: P&L | L3: P&L | M3: P&L | N3: P&L | O3: P&L | P3: P&L | R3: P&L | S3: P&L | T3: P&L | U3: P&L | V3: P&L | W3: P&L | X3: P&L | Y3: P&L | Z3: P&L | AA3: P&L | AB3: P&L | AC3: P&L | AD3: P&L | AF3: P&L | AG3: P&L | AH3: P&L | AI3: P&L | AJ3: P&L | AK3: P&L | AL3: P&L | AM3: P&L | AN3: P&L | AO3: P&L | AP3: P&L | AQ3: P&L | AR3: P&L | AT3: P&L | AU3: P&L | AV3: P&L | AW3: P&L | AX3: P&L | AY3: P&L | AZ3: P&L | BA3: P&L | BB3: P&L | BC3: P&L | BD3: P&L | BE3: P&L | BF3: P&L | BH3: P&L | BI3: P&L | BJ3: P&L | BK3: P&L | BL3: P&L | BM3: P&L | BN3: P&L | BO3: P&L | BP3: P&L | BQ3: P&L | BR3: P&L | BS3: P&L | BT3: P&L | BV3: P&L | BW3: P&L | BX3: P&L | BY3: P&L | BZ3: P&L | CA3: P&L | CB3: P&L | CC3: P&L | CD3: P&L | CE3: P&L | CF3: P&L | CG3: P&L | CH3: P&L
B4: Month | D4: 1 | E4: =+D4+1 -> 2 | F4: =+E4+1 -> 3 | G4: =+F4+1 -> 4 | H4: =+G4+1 -> 5 | I4: =+H4+1 -> 6 | J4: =+I4+1 -> 7 | K4: =+J4+1 -> 8 | L4: =+K4+1 -> 9 | ... O4: =+N4+1 -> 12 | P4: TOTAL | R4: 1 | S4: =+R4+1 -> 2 | T4: =+S4+1 -> 3 | U4: =+T4+1 -> 4 | V4: =+U4+1 -> 5 | W4: =+V4+1 -> 6 | X4: =+W4+1 -> 7 | Y4: =+X4+1 -> 8 | Z4: =+Y4+1 -> 9 | ... AC4: =+AB4+1 -> 12 | AD4: TOTAL | AF4: 1 | AG4: =+AF4+1 -> 2 | AH4: =+AG4+1 -> 3 | AI4: =+AH4+1 -> 4 | AJ4: =+AI4+1 -> 5 | AK4: =+AJ4+1 -> 6 | AL4: =+AK4+1 -> 7 | AM4: =+AL4+1 -> 8 | AN4: =+AM4+1 -> 9 | ... AQ4: =+AP4+1 -> 12 | AR4: TOTAL | AT4: 1 | AU4: =+AT4+1 -> 2 | AV4: =+AU4+1 -> 3 | AW4: =+AV4+1 -> 4 | AX4: =+AW4+1 -> 5 | AY4: =+AX4+1 -> 6 | AZ4: =+AY4+1 -> 7 | BA4: =+AZ4+1 -> 8 | BB4: =+BA4+1 -> 9 | ... BE4: =+BD4+1 -> 12 | BF4: TOTAL | BH4: 1 | BI4: =+BH4+1 -> 2 | BJ4: =+BI4+1 -> 3 | BK4: =+BJ4+1 -> 4 | BL4: =+BK4+1 -> 5 | BM4: =+BL4+1 -> 6 | BN4: =+BM4+1 -> 7 | BO4: =+BN4+1 -> 8 | BP4: =+BO4+1 -> 9 | ... BS4: =+BR4+1 -> 12 | BT4: TOTAL | BV4: 1 | BW4: =+BV4+1 -> 2 | BX4: =+BW4+1 -> 3 | BY4: =+BX4+1 -> 4 | BZ4: =+BY4+1 -> 5 | CA4: =+BZ4+1 -> 6 | CB4: =+CA4+1 -> 7 | CC4: =+CB4+1 -> 8 | CD4: =+CC4+1 -> 9 | ... CG4: =+CF4+1 -> 12 | CH4: TOTAL
B5: Quarter | D5: Q1 | E5: Q1 | F5: Q1 | G5: Q2 | H5: Q2 | I5: Q2 | J5: Q3 | K5: Q3 | L5: Q3 | M5: Q4 | N5: Q4 | O5: Q4 | R5: Q1 | S5: Q1 | T5: Q1 | U5: Q2 | V5: Q2 | W5: Q2 | X5: Q3 | Y5: Q3 | Z5: Q3 | AA5: Q4 | AB5: Q4 | AC5: Q4 | AF5: Q1 | AG5: Q1 | AH5: Q1 | AI5: Q2 | AJ5: Q2 | AK5: Q2 | AL5: Q3 | AM5: Q3 | AN5: Q3 | AO5: Q4 | AP5: Q4 | AQ5: Q4 | AT5: Q1 | AU5: Q1 | AV5: Q1 | AW5: Q2 | AX5: Q2 | AY5: Q2 | AZ5: Q3 | BA5: Q3 | BB5: Q3 | BC5: Q4 | BD5: Q4 | BE5: Q4 | BH5: Q1 | BI5: Q1 | BJ5: Q1 | BK5: Q2 | BL5: Q2 | BM5: Q2 | BN5: Q3 | BO5: Q3 | BP5: Q3 | BQ5: Q4 | BR5: Q4 | BS5: Q4 | BV5: Q1 | BW5: Q1 | BX5: Q1 | BY5: Q2 | BZ5: Q2 | CA5: Q2 | CB5: Q3 | CC5: Q3 | CD5: Q3 | CE5: Q4 | CF5: Q4 | CG5: Q4
B6: Active Months | D6: =+IF(D4<=MONTH,1,0) -> 1 | E6: =+IF(E4<=MONTH,1,0) -> 1 | F6: =+IF(F4<=MONTH,1,0) -> 1 | G6: =+IF(G4<=MONTH,1,0) -> 1 | H6: =+IF(H4<=MONTH,1,0) -> 1 | I6: =+IF(I4<=MONTH,1,0) -> 1 | J6: =+IF(J4<=MONTH,1,0) -> 1 | K6: =+IF(K4<=MONTH,1,0) -> 1 | ... O6: =+IF(O4<=MONTH,1,0) -> 1 | R6: =+IF(R4<=MONTH,1,0) -> 1 | S6: =+IF(S4<=MONTH,1,0) -> 1 | T6: =+IF(T4<=MONTH,1,0) -> 1 | U6: =+IF(U4<=MONTH,1,0) -> 1 | V6: =+IF(V4<=MONTH,1,0) -> 1 | W6: =+IF(W4<=MONTH,1,0) -> 1 | X6: =+IF(X4<=MONTH,1,0) -> 1 | Y6: =+IF(Y4<=MONTH,1,0) -> 1 | ... AC6: =+IF(AC4<=MONTH,1,0) -> 1 | AF6: =+IF(AF4<=MONTH,1,0) -> 1 | AG6: =+IF(AG4<=MONTH,1,0) -> 1 | AH6: =+IF(AH4<=MONTH,1,0) -> 1 | AI6: =+IF(AI4<=MONTH,1,0) -> 1 | AJ6: =+IF(AJ4<=MONTH,1,0) -> 1 | AK6: =+IF(AK4<=MONTH,1,0) -> 1 | AL6: =+IF(AL4<=MONTH,1,0) -> 1 | AM6: =+IF(AM4<=MONTH,1,0) -> 1 | ... AQ6: =+IF(AQ4<=MONTH,1,0) -> 1 | AT6: =+IF(AT4<=MONTH,1,0) -> 1 | AU6: =+IF(AU4<=MONTH,1,0) -> 1 | AV6: =+IF(AV4<=MONTH,1,0) -> 1 | AW6: =+IF(AW4<=MONTH,1,0) -> 1 | AX6: =+IF(AX4<=MONTH,1,0) -> 1 | AY6: =+IF(AY4<=MONTH,1,0) -> 1 | AZ6: =+IF(AZ4<=MONTH,1,0) -> 1 | BA6: =+IF(BA4<=MONTH,1,0) -> 1 | ... BE6: =+IF(BE4<=MONTH,1,0) -> 1 | BH6: =+IF(BH4<=MONTH,1,0) -> 1 | BI6: =+IF(BI4<=MONTH,1,0) -> 1 | BJ6: =+IF(BJ4<=MONTH,1,0) -> 1 | BK6: =+IF(BK4<=MONTH,1,0) -> 1 | BL6: =+IF(BL4<=MONTH,1,0) -> 1 | BM6: =+IF(BM4<=MONTH,1,0) -> 1 | BN6: =+IF(BN4<=MONTH,1,0) -> 1 | BO6: =+IF(BO4<=MONTH,1,0) -> 1 | ... BS6: =+IF(BS4<=MONTH,1,0) -> 1 | BV6: =+IF(BV4<=MONTH,1,0) -> 1 | BW6: =+IF(BW4<=MONTH,1,0) -> 1 | BX6: =+IF(BX4<=MONTH,1,0) -> 1 | BY6: =+IF(BY4<=MONTH,1,0) -> 1 | BZ6: =+IF(BZ4<=MONTH,1,0) -> 1 | CA6: =+IF(CA4<=MONTH,1,0) -> 1 | CB6: =+IF(CB4<=MONTH,1,0) -> 1 | CC6: =+IF(CC4<=MONTH,1,0) -> 1 | ... CG6: =+IF(CG4<=MONTH,1,0) -> 1
B10: in EUR | D10: =+D2 -> 2025 | E10: =+E2 -> 2025 | F10: =+F2 -> 2025 | G10: =+G2 -> 2025 | H10: =+H2 -> 2025 | I10: =+I2 -> 2025 | J10: =+J2 -> 2025 | K10: =+K2 -> 2025 | ... P10: =+P2 -> 2025 | R10: =+R2 -> 2026 | S10: =+S2 -> 2026 | T10: =+T2 -> 2026 | U10: =+U2 -> 2026 | V10: =+V2 -> 2026 | W10: =+W2 -> 2026 | X10: =+X2 -> 2026 | Y10: =+Y2 -> 2026 | ... AD10: =+AD2 -> 2026 | AF10: =+AF2 -> 2027 | AG10: =+AG2 -> 2027 | AH10: =+AH2 -> 2027 | AI10: =+AI2 -> 2027 | AJ10: =+AJ2 -> 2027 | AK10: =+AK2 -> 2027 | AL10: =+AL2 -> 2027 | AM10: =+AM2 -> 2027 | ... AR10: =+AR2 -> 2027 | AT10: =+AT2 -> 2028 | AU10: =+AU2 -> 2028 | AV10: =+AV2 -> 2028 | AW10: =+AW2 -> 2028 | AX10: =+AX2 -> 2028 | AY10: =+AY2 -> 2028 | AZ10: =+AZ2 -> 2028 | BA10: =+BA2 -> 2028 | ... BF10: =+BF2 -> 2028 | BH10: =+BH2 -> 2029 | BI10: =+BI2 -> 2029 | BJ10: =+BJ2 -> 2029 | BK10: =+BK2 -> 2029 | BL10: =+BL2 -> 2029 | BM10: =+BM2 -> 2029 | BN10: =+BN2 -> 2029 | BO10: =+BO2 -> 2029 | ... BT10: =+BT2 -> 2029 | BV10: =+BV2 -> 2030 | BW10: =+BW2 -> 2030 | BX10: =+BX2 -> 2030 | BY10: =+BY2 -> 2030 | BZ10: =+BZ2 -> 2030 | CA10: =+CA2 -> 2030 | CB10: =+CB2 -> 2030 | CC10: =+CC2 -> 2030 | ... CH10: =+CH2 -> 2030
C11: Key | D11: Jan | E11: Feb | F11: March | G11: April | H11: May | I11: June | J11: July | K11: Aug | L11: Sept | M11: Oct | N11: Nov | O11: Dec | P11: =+P4 -> TOTAL | R11: Jan | S11: Feb | T11: March | U11: April | V11: May | W11: June | X11: July | Y11: Aug | Z11: Sept | AA11: Oct | AB11: Nov | AC11: Dec | AD11: =+AD4 -> TOTAL | AF11: Jan | AG11: Feb | AH11: March | AI11: April | AJ11: May | AK11: June | AL11: July | AM11: Aug | AN11: Sept | AO11: Oct | AP11: Nov | AQ11: Dec | AR11: =+AR4 -> TOTAL | AT11: Jan | AU11: Feb | AV11: March | AW11: April | AX11: May | AY11: June | AZ11: July | BA11: Aug | BB11: Sept | BC11: Oct | BD11: Nov | BE11: Dec | BF11: =+BF4 -> TOTAL | BH11: Jan | BI11: Feb | BJ11: March | BK11: April | BL11: May | BM11: June | BN11: July | BO11: Aug | BP11: Sept | BQ11: Oct | BR11: Nov | BS11: Dec | BT11: =+BT4 -> TOTAL | BV11: Jan | BW11: Feb | BX11: March | BY11: April | BZ11: May | CA11: June | CB11: July | CC11: Aug | CD11: Sept | CE11: Oct | CF11: Nov | CG11: Dec | CH11: =+CH4 -> TOTAL
B12: ='Revenue Overview'!B12 -> Product 1 | C12: INC1 | D12: ='Revenue Overview'!D12 -> 0 | E12: ='Revenue Overview'!E12 -> 0 | F12: ='Revenue Overview'!F12 -> 0 | G12: ='Revenue Overview'!G12 -> 0 | H12: ='Revenue Overview'!H12 -> 0 | I12: ='Revenue Overview'!I12 -> 0 | J12: ='Revenue Overview'!J12 -> 0 | K12: ='Revenue Overview'!K12 -> 0 | ... O12: ='Revenue Overview'!O12 -> 1386 | P12: =SUM(D12:O12) -> 3601.5 | R12: ='Revenue Overview'!R12 -> 1680 | S12: ='Revenue Overview'!S12 -> 2100 | T12: ='Revenue Overview'!T12 -> 3150 | U12: ='Revenue Overview'!U12 -> 4200 | V12: ='Revenue Overview'!V12 -> 5250 | W12: ='Revenue Overview'!W12 -> 6993 | X12: ='Revenue Overview'!X12 -> 8925 | Y12: ='Revenue Overview'!Y12 -> 10500 | ... AC12: ='Revenue Overview'!AC12 -> 10500 | AD12: =SUM(R12:AC12) -> 84798 | AF12: ='Revenue Overview'!AF12 -> 11035.5 | AG12: ='Revenue Overview'!AG12 -> 11035.5 | AH12: ='Revenue Overview'!AH12 -> 11035.5 | AI12: ='Revenue Overview'!AI12 -> 11035.5 | AJ12: ='Revenue Overview'!AJ12 -> 11035.5 | AK12: ='Revenue Overview'!AK12 -> 11035.5 | AL12: ='Revenue Overview'!AL12 -> 11035.5 | AM12: ='Revenue Overview'!AM12 -> 11035.5 | ... AQ12: ='Revenue Overview'!AQ12 -> 11035.5 | AR12: =SUM(AF12:AQ12) -> 132426 | AT12: ='Revenue Overview'!AT12 -> 11432.778 | AU12: ='Revenue Overview'!AU12 -> 11432.778 | AV12: ='Revenue Overview'!AV12 -> 11432.778 | AW12: ='Revenue Overview'!AW12 -> 11432.778 | AX12: ='Revenue Overview'!AX12 -> 11432.778 | AY12: ='Revenue Overview'!AY12 -> 11432.778 | AZ12: ='Revenue Overview'!AZ12 -> 11432.778 | BA12: ='Revenue Overview'!BA12 -> 11432.778 | ... BE12: ='Revenue Overview'!BE12 -> 11432.778 | BF12: =SUM(AT12:BE12) -> 137193.34 | BH12: ='Revenue Overview'!BH12 -> 11832.925 | BI12: ='Revenue Overview'!BI12 -> 11832.925 | BJ12: ='Revenue Overview'!BJ12 -> 11832.925 | BK12: ='Revenue Overview'!BK12 -> 11832.925 | BL12: ='Revenue Overview'!BL12 -> 11832.925 | BM12: ='Revenue Overview'!BM12 -> 11832.925 | BN12: ='Revenue Overview'!BN12 -> 11832.925 | BO12: ='Revenue Overview'!BO12 -> 11832.925 | ... BS12: ='Revenue Overview'!BS12 -> 11832.925 | BT12: =SUM(BH12:BS12) -> 141995.1 | BV12: ='Revenue Overview'!BV12 -> 12247.078 | BW12: ='Revenue Overview'!BW12 -> 12247.078 | BX12: ='Revenue Overview'!BX12 -> 12247.078 | BY12: ='Revenue Overview'!BY12 -> 12247.078 | BZ12: ='Revenue Overview'!BZ12 -> 12247.078 | CA12: ='Revenue Overview'!CA12 -> 12247.078 | CB12: ='Revenue Overview'!CB12 -> 12247.078 | CC12: ='Revenue Overview'!CC12 -> 12247.078 | ... CG12: ='Revenue Overview'!CG12 -> 12247.078 | CH12: =SUM(BV12:CG12) -> 146964.93
B13: ='Revenue Overview'!B13 -> Product 2 | C13: INC2 | D13: ='Revenue Overview'!D13 -> 0 | E13: ='Revenue Overview'!E13 -> 0 | F13: ='Revenue Overview'!F13 -> 0 | G13: ='Revenue Overview'!G13 -> 0 | H13: ='Revenue Overview'!H13 -> 0 | I13: ='Revenue Overview'!I13 -> 0 | J13: ='Revenue Overview'!J13 -> 0 | K13: ='Revenue Overview'!K13 -> 0 | ... O13: ='Revenue Overview'!O13 -> 1386 | P13: =SUM(D13:O13) -> 3601.5 | R13: ='Revenue Overview'!R13 -> 1680 | S13: ='Revenue Overview'!S13 -> 2100 | T13: ='Revenue Overview'!T13 -> 3150 | U13: ='Revenue Overview'!U13 -> 4200 | V13: ='Revenue Overview'!V13 -> 5250 | W13: ='Revenue Overview'!W13 -> 6993 | X13: ='Revenue Overview'!X13 -> 8925 | Y13: ='Revenue Overview'!Y13 -> 10500 | ... AC13: ='Revenue Overview'!AC13 -> 10500 | AD13: =SUM(R13:AC13) -> 84798 | AF13: ='Revenue Overview'!AF13 -> 11035.5 | AG13: ='Revenue Overview'!AG13 -> 11035.5 | AH13: ='Revenue Overview'!AH13 -> 11035.5 | AI13: ='Revenue Overview'!AI13 -> 11035.5 | AJ13: ='Revenue Overview'!AJ13 -> 11035.5 | AK13: ='Revenue Overview'!AK13 -> 11035.5 | AL13: ='Revenue Overview'!AL13 -> 11035.5 | AM13: ='Revenue Overview'!AM13 -> 11035.5 | ... AQ13: ='Revenue Overview'!AQ13 -> 11035.5 | AR13: =SUM(AF13:AQ13) -> 132426 | AT13: ='Revenue Overview'!AT13 -> 11432.778 | AU13: ='Revenue Overview'!AU13 -> 11432.778 | AV13: ='Revenue Overview'!AV13 -> 11432.778 | AW13: ='Revenue Overview'!AW13 -> 11432.778 | AX13: ='Revenue Overview'!AX13 -> 11432.778 | AY13: ='Revenue Overview'!AY13 -> 11432.778 | AZ13: ='Revenue Overview'!AZ13 -> 11432.778 | BA13: ='Revenue Overview'!BA13 -> 11432.778 | ... BE13: ='Revenue Overview'!BE13 -> 11432.778 | BF13: =SUM(AT13:BE13) -> 137193.34 | BH13: ='Revenue Overview'!BH13 -> 11832.925 | BI13: ='Revenue Overview'!BI13 -> 11832.925 | BJ13: ='Revenue Overview'!BJ13 -> 11832.925 | BK13: ='Revenue Overview'!BK13 -> 11832.925 | BL13: ='Revenue Overview'!BL13 -> 11832.925 | BM13: ='Revenue Overview'!BM13 -> 11832.925 | BN13: ='Revenue Overview'!BN13 -> 11832.925 | BO13: ='Revenue Overview'!BO13 -> 11832.925 | ... BS13: ='Revenue Overview'!BS13 -> 11832.925 | BT13: =SUM(BH13:BS13) -> 141995.1 | BV13: ='Revenue Overview'!BV13 -> 12247.078 | BW13: ='Revenue Overview'!BW13 -> 12247.078 | BX13: ='Revenue Overview'!BX13 -> 12247.078 | BY13: ='Revenue Overview'!BY13 -> 12247.078 | BZ13: ='Revenue Overview'!BZ13 -> 12247.078 | CA13: ='Revenue Overview'!CA13 -> 12247.078 | CB13: ='Revenue Overview'!CB13 -> 12247.078 | CC13: ='Revenue Overview'!CC13 -> 12247.078 | ... CG13: ='Revenue Overview'!CG13 -> 12247.078 | CH13: =SUM(BV13:CG13) -> 146964.93
B14: ='Revenue Overview'!B14 -> Product 3 | C14: INC3 | D14: ='Revenue Overview'!D14 -> 0 | E14: ='Revenue Overview'!E14 -> 0 | F14: ='Revenue Overview'!F14 -> 0 | G14: ='Revenue Overview'!G14 -> 0 | H14: ='Revenue Overview'!H14 -> 0 | I14: ='Revenue Overview'!I14 -> 0 | J14: ='Revenue Overview'!J14 -> 0 | K14: ='Revenue Overview'!K14 -> 0 | ... O14: ='Revenue Overview'!O14 -> 1386 | P14: =SUM(D14:O14) -> 3601.5 | R14: ='Revenue Overview'!R14 -> 1680 | S14: ='Revenue Overview'!S14 -> 2100 | T14: ='Revenue Overview'!T14 -> 3150 | U14: ='Revenue Overview'!U14 -> 4200 | V14: ='Revenue Overview'!V14 -> 5250 | W14: ='Revenue Overview'!W14 -> 6993 | X14: ='Revenue Overview'!X14 -> 8925 | Y14: ='Revenue Overview'!Y14 -> 10500 | ... AC14: ='Revenue Overview'!AC14 -> 10500 | AD14: =SUM(R14:AC14) -> 84798 | AF14: ='Revenue Overview'!AF14 -> 11035.5 | AG14: ='Revenue Overview'!AG14 -> 11035.5 | AH14: ='Revenue Overview'!AH14 -> 11035.5 | AI14: ='Revenue Overview'!AI14 -> 11035.5 | AJ14: ='Revenue Overview'!AJ14 -> 11035.5 | AK14: ='Revenue Overview'!AK14 -> 11035.5 | AL14: ='Revenue Overview'!AL14 -> 11035.5 | AM14: ='Revenue Overview'!AM14 -> 11035.5 | ... AQ14: ='Revenue Overview'!AQ14 -> 11035.5 | AR14: =SUM(AF14:AQ14) -> 132426 | AT14: ='Revenue Overview'!AT14 -> 11432.778 | AU14: ='Revenue Overview'!AU14 -> 11432.778 | AV14: ='Revenue Overview'!AV14 -> 11432.778 | AW14: ='Revenue Overview'!AW14 -> 11432.778 | AX14: ='Revenue Overview'!AX14 -> 11432.778 | AY14: ='Revenue Overview'!AY14 -> 11432.778 | AZ14: ='Revenue Overview'!AZ14 -> 11432.778 | BA14: ='Revenue Overview'!BA14 -> 11432.778 | ... BE14: ='Revenue Overview'!BE14 -> 11432.778 | BF14: =SUM(AT14:BE14) -> 137193.34 | BH14: ='Revenue Overview'!BH14 -> 11832.925 | BI14: ='Revenue Overview'!BI14 -> 11832.925 | BJ14: ='Revenue Overview'!BJ14 -> 11832.925 | BK14: ='Revenue Overview'!BK14 -> 11832.925 | BL14: ='Revenue Overview'!BL14 -> 11832.925 | BM14: ='Revenue Overview'!BM14 -> 11832.925 | BN14: ='Revenue Overview'!BN14 -> 11832.925 | BO14: ='Revenue Overview'!BO14 -> 11832.925 | ... BS14: ='Revenue Overview'!BS14 -> 11832.925 | BT14: =SUM(BH14:BS14) -> 141995.1 | BV14: ='Revenue Overview'!BV14 -> 12247.078 | BW14: ='Revenue Overview'!BW14 -> 12247.078 | BX14: ='Revenue Overview'!BX14 -> 12247.078 | BY14: ='Revenue Overview'!BY14 -> 12247.078 | BZ14: ='Revenue Overview'!BZ14 -> 12247.078 | CA14: ='Revenue Overview'!CA14 -> 12247.078 | CB14: ='Revenue Overview'!CB14 -> 12247.078 | CC14: ='Revenue Overview'!CC14 -> 12247.078 | ... CG14: ='Revenue Overview'!CG14 -> 12247.078 | CH14: =SUM(BV14:CG14) -> 146964.93
B15: ='Revenue Overview'!B15 -> Product 4 | C15: INC4 | D15: ='Revenue Overview'!D15 -> 0 | E15: ='Revenue Overview'!E15 -> 0 | F15: ='Revenue Overview'!F15 -> 0 | G15: ='Revenue Overview'!G15 -> 0 | H15: ='Revenue Overview'!H15 -> 0 | I15: ='Revenue Overview'!I15 -> 0 | J15: ='Revenue Overview'!J15 -> 0 | K15: ='Revenue Overview'!K15 -> 0 | ... O15: ='Revenue Overview'!O15 -> 693 | P15: =SUM(D15:O15) -> 1218 | R15: ='Revenue Overview'!R15 -> 840 | S15: ='Revenue Overview'!S15 -> 1050 | T15: ='Revenue Overview'!T15 -> 1575 | U15: ='Revenue Overview'!U15 -> 1575 | V15: ='Revenue Overview'!V15 -> 2100 | W15: ='Revenue Overview'!W15 -> 2625 | X15: ='Revenue Overview'!X15 -> 3675 | Y15: ='Revenue Overview'!Y15 -> 5250 | ... AC15: ='Revenue Overview'!AC15 -> 5250 | AD15: =SUM(R15:AC15) -> 39690 | AF15: ='Revenue Overview'!AF15 -> 5517.75 | AG15: ='Revenue Overview'!AG15 -> 5517.75 | AH15: ='Revenue Overview'!AH15 -> 5517.75 | AI15: ='Revenue Overview'!AI15 -> 5517.75 | AJ15: ='Revenue Overview'!AJ15 -> 5517.75 | AK15: ='Revenue Overview'!AK15 -> 5517.75 | AL15: ='Revenue Overview'!AL15 -> 5517.75 | AM15: ='Revenue Overview'!AM15 -> 5517.75 | ... AQ15: ='Revenue Overview'!AQ15 -> 5517.75 | AR15: =SUM(AF15:AQ15) -> 66213 | AT15: ='Revenue Overview'!AT15 -> 5716.389 | AU15: ='Revenue Overview'!AU15 -> 5716.389 | AV15: ='Revenue Overview'!AV15 -> 5716.389 | AW15: ='Revenue Overview'!AW15 -> 5716.389 | AX15: ='Revenue Overview'!AX15 -> 5716.389 | AY15: ='Revenue Overview'!AY15 -> 5716.389 | AZ15: ='Revenue Overview'!AZ15 -> 5716.389 | BA15: ='Revenue Overview'!BA15 -> 5716.389 | ... BE15: ='Revenue Overview'!BE15 -> 5716.389 | BF15: =SUM(AT15:BE15) -> 68596.668 | BH15: ='Revenue Overview'!BH15 -> 5916.4626 | BI15: ='Revenue Overview'!BI15 -> 5916.4626 | BJ15: ='Revenue Overview'!BJ15 -> 5916.4626 | BK15: ='Revenue Overview'!BK15 -> 5916.4626 | BL15: ='Revenue Overview'!BL15 -> 5916.4626 | BM15: ='Revenue Overview'!BM15 -> 5916.4626 | BN15: ='Revenue Overview'!BN15 -> 5916.4626 | BO15: ='Revenue Overview'!BO15 -> 5916.4626 | ... BS15: ='Revenue Overview'!BS15 -> 5916.4626 | BT15: =SUM(BH15:BS15) -> 70997.551 | BV15: ='Revenue Overview'!BV15 -> 6123.5388 | BW15: ='Revenue Overview'!BW15 -> 6123.5388 | BX15: ='Revenue Overview'!BX15 -> 6123.5388 | BY15: ='Revenue Overview'!BY15 -> 6123.5388 | BZ15: ='Revenue Overview'!BZ15 -> 6123.5388 | CA15: ='Revenue Overview'!CA15 -> 6123.5388 | CB15: ='Revenue Overview'!CB15 -> 6123.5388 | CC15: ='Revenue Overview'!CC15 -> 6123.5388 | ... CG15: ='Revenue Overview'!CG15 -> 6123.5388 | CH15: =SUM(BV15:CG15) -> 73482.466
B16: ='Revenue Overview'!B16 -> Product 5 | C16: INC5 | D16: ='Revenue Overview'!D16 -> 0 | E16: ='Revenue Overview'!E16 -> 0 | F16: ='Revenue Overview'!F16 -> 0 | G16: ='Revenue Overview'!G16 -> 0 | H16: ='Revenue Overview'!H16 -> 0 | I16: ='Revenue Overview'!I16 -> 0 | J16: ='Revenue Overview'!J16 -> 0 | K16: ='Revenue Overview'!K16 -> 0 | ... O16: ='Revenue Overview'!O16 -> 693 | P16: =SUM(D16:O16) -> 1218 | R16: ='Revenue Overview'!R16 -> 840 | S16: ='Revenue Overview'!S16 -> 1050 | T16: ='Revenue Overview'!T16 -> 1575 | U16: ='Revenue Overview'!U16 -> 1575 | V16: ='Revenue Overview'!V16 -> 2100 | W16: ='Revenue Overview'!W16 -> 2625 | X16: ='Revenue Overview'!X16 -> 3675 | Y16: ='Revenue Overview'!Y16 -> 5250 | ... AC16: ='Revenue Overview'!AC16 -> 5250 | AD16: =SUM(R16:AC16) -> 39690 | AF16: ='Revenue Overview'!AF16 -> 5517.75 | AG16: ='Revenue Overview'!AG16 -> 5517.75 | AH16: ='Revenue Overview'!AH16 -> 5517.75 | AI16: ='Revenue Overview'!AI16 -> 5517.75 | AJ16: ='Revenue Overview'!AJ16 -> 5517.75 | AK16: ='Revenue Overview'!AK16 -> 5517.75 | AL16: ='Revenue Overview'!AL16 -> 5517.75 | AM16: ='Revenue Overview'!AM16 -> 5517.75 | ... AQ16: ='Revenue Overview'!AQ16 -> 5517.75 | AR16: =SUM(AF16:AQ16) -> 66213 | AT16: ='Revenue Overview'!AT16 -> 5716.389 | AU16: ='Revenue Overview'!AU16 -> 5716.389 | AV16: ='Revenue Overview'!AV16 -> 5716.389 | AW16: ='Revenue Overview'!AW16 -> 5716.389 | AX16: ='Revenue Overview'!AX16 -> 5716.389 | AY16: ='Revenue Overview'!AY16 -> 5716.389 | AZ16: ='Revenue Overview'!AZ16 -> 5716.389 | BA16: ='Revenue Overview'!BA16 -> 5716.389 | ... BE16: ='Revenue Overview'!BE16 -> 5716.389 | BF16: =SUM(AT16:BE16) -> 68596.668 | BH16: ='Revenue Overview'!BH16 -> 5916.4626 | BI16: ='Revenue Overview'!BI16 -> 5916.4626 | BJ16: ='Revenue Overview'!BJ16 -> 5916.4626 | BK16: ='Revenue Overview'!BK16 -> 5916.4626 | BL16: ='Revenue Overview'!BL16 -> 5916.4626 | BM16: ='Revenue Overview'!BM16 -> 5916.4626 | BN16: ='Revenue Overview'!BN16 -> 5916.4626 | BO16: ='Revenue Overview'!BO16 -> 5916.4626 | ... BS16: ='Revenue Overview'!BS16 -> 5916.4626 | BT16: =SUM(BH16:BS16) -> 70997.551 | BV16: ='Revenue Overview'!BV16 -> 6123.5388 | BW16: ='Revenue Overview'!BW16 -> 6123.5388 | BX16: ='Revenue Overview'!BX16 -> 6123.5388 | BY16: ='Revenue Overview'!BY16 -> 6123.5388 | BZ16: ='Revenue Overview'!BZ16 -> 6123.5388 | CA16: ='Revenue Overview'!CA16 -> 6123.5388 | CB16: ='Revenue Overview'!CB16 -> 6123.5388 | CC16: ='Revenue Overview'!CC16 -> 6123.5388 | ... CG16: ='Revenue Overview'!CG16 -> 6123.5388 | CH16: =SUM(BV16:CG16) -> 73482.466
B17: ='Revenue Overview'!B17 -> Product 6 | C17: INC6 | D17: ='Revenue Overview'!D17 -> 0 | E17: ='Revenue Overview'!E17 -> 0 | F17: ='Revenue Overview'!F17 -> 0 | G17: ='Revenue Overview'!G17 -> 0 | H17: ='Revenue Overview'!H17 -> 0 | I17: ='Revenue Overview'!I17 -> 0 | J17: ='Revenue Overview'!J17 -> 0 | K17: ='Revenue Overview'!K17 -> 0 | ... O17: ='Revenue Overview'!O17 -> 693 | P17: =SUM(D17:O17) -> 1218 | R17: ='Revenue Overview'!R17 -> 840 | S17: ='Revenue Overview'!S17 -> 1050 | T17: ='Revenue Overview'!T17 -> 1575 | U17: ='Revenue Overview'!U17 -> 1575 | V17: ='Revenue Overview'!V17 -> 2100 | W17: ='Revenue Overview'!W17 -> 2625 | X17: ='Revenue Overview'!X17 -> 3675 | Y17: ='Revenue Overview'!Y17 -> 5250 | ... AC17: ='Revenue Overview'!AC17 -> 5250 | AD17: =SUM(R17:AC17) -> 39690 | AF17: ='Revenue Overview'!AF17 -> 5517.75 | AG17: ='Revenue Overview'!AG17 -> 5517.75 | AH17: ='Revenue Overview'!AH17 -> 5517.75 | AI17: ='Revenue Overview'!AI17 -> 5517.75 | AJ17: ='Revenue Overview'!AJ17 -> 5517.75 | AK17: ='Revenue Overview'!AK17 -> 5517.75 | AL17: ='Revenue Overview'!AL17 -> 5517.75 | AM17: ='Revenue Overview'!AM17 -> 5517.75 | ... AQ17: ='Revenue Overview'!AQ17 -> 5517.75 | AR17: =SUM(AF17:AQ17) -> 66213 | AT17: ='Revenue Overview'!AT17 -> 5716.389 | AU17: ='Revenue Overview'!AU17 -> 5716.389 | AV17: ='Revenue Overview'!AV17 -> 5716.389 | AW17: ='Revenue Overview'!AW17 -> 5716.389 | AX17: ='Revenue Overview'!AX17 -> 5716.389 | AY17: ='Revenue Overview'!AY17 -> 5716.389 | AZ17: ='Revenue Overview'!AZ17 -> 5716.389 | BA17: ='Revenue Overview'!BA17 -> 5716.389 | ... BE17: ='Revenue Overview'!BE17 -> 5716.389 | BF17: =SUM(AT17:BE17) -> 68596.668 | BH17: ='Revenue Overview'!BH17 -> 5916.4626 | BI17: ='Revenue Overview'!BI17 -> 5916.4626 | BJ17: ='Revenue Overview'!BJ17 -> 5916.4626 | BK17: ='Revenue Overview'!BK17 -> 5916.4626 | BL17: ='Revenue Overview'!BL17 -> 5916.4626 | BM17: ='Revenue Overview'!BM17 -> 5916.4626 | BN17: ='Revenue Overview'!BN17 -> 5916.4626 | BO17: ='Revenue Overview'!BO17 -> 5916.4626 | ... BS17: ='Revenue Overview'!BS17 -> 5916.4626 | BT17: =SUM(BH17:BS17) -> 70997.551 | BV17: ='Revenue Overview'!BV17 -> 6123.5388 | BW17: ='Revenue Overview'!BW17 -> 6123.5388 | BX17: ='Revenue Overview'!BX17 -> 6123.5388 | BY17: ='Revenue Overview'!BY17 -> 6123.5388 | BZ17: ='Revenue Overview'!BZ17 -> 6123.5388 | CA17: ='Revenue Overview'!CA17 -> 6123.5388 | CB17: ='Revenue Overview'!CB17 -> 6123.5388 | CC17: ='Revenue Overview'!CC17 -> 6123.5388 | ... CG17: ='Revenue Overview'!CG17 -> 6123.5388 | CH17: =SUM(BV17:CG17) -> 73482.466
B18: ='Revenue Overview'!B18 -> Product 7 | C18: INC7 | V18: ='Revenue Overview'!V18 -> 1050 | W18: ='Revenue Overview'!W18 -> 2100 | X18: ='Revenue Overview'!X18 -> 3150 | Y18: ='Revenue Overview'!Y18 -> 4725 | Z18: ='Revenue Overview'!Z18 -> 4725 | AA18: ='Revenue Overview'!AA18 -> 4725 | AB18: ='Revenue Overview'!AB18 -> 4725 | AC18: ='Revenue Overview'!AC18 -> 4725 | AD18: =SUM(R18:AC18) -> 29925 | AF18: ='Revenue Overview'!AF18 -> 4965.975 | AG18: ='Revenue Overview'!AG18 -> 4965.975 | AH18: ='Revenue Overview'!AH18 -> 4965.975 | AI18: ='Revenue Overview'!AI18 -> 4965.975 | AJ18: ='Revenue Overview'!AJ18 -> 4965.975 | AK18: ='Revenue Overview'!AK18 -> 4965.975 | AL18: ='Revenue Overview'!AL18 -> 4965.975 | AM18: ='Revenue Overview'!AM18 -> 4965.975 | ... AQ18: ='Revenue Overview'!AQ18 -> 4965.975 | AR18: =SUM(AF18:AQ18) -> 59591.7 | AT18: ='Revenue Overview'!AT18 -> 5144.7501 | AU18: ='Revenue Overview'!AU18 -> 5144.7501 | AV18: ='Revenue Overview'!AV18 -> 5144.7501 | AW18: ='Revenue Overview'!AW18 -> 5144.7501 | AX18: ='Revenue Overview'!AX18 -> 5144.7501 | AY18: ='Revenue Overview'!AY18 -> 5144.7501 | AZ18: ='Revenue Overview'!AZ18 -> 5144.7501 | BA18: ='Revenue Overview'!BA18 -> 5144.7501 | ... BE18: ='Revenue Overview'!BE18 -> 5144.7501 | BF18: =SUM(AT18:BE18) -> 61737.001 | BH18: ='Revenue Overview'!BH18 -> 5324.8164 | BI18: ='Revenue Overview'!BI18 -> 5324.8164 | BJ18: ='Revenue Overview'!BJ18 -> 5324.8164 | BK18: ='Revenue Overview'!BK18 -> 5324.8164 | BL18: ='Revenue Overview'!BL18 -> 5324.8164 | BM18: ='Revenue Overview'!BM18 -> 5324.8164 | BN18: ='Revenue Overview'!BN18 -> 5324.8164 | BO18: ='Revenue Overview'!BO18 -> 5324.8164 | ... BS18: ='Revenue Overview'!BS18 -> 5324.8164 | BT18: =SUM(BH18:BS18) -> 63897.796 | BV18: ='Revenue Overview'!BV18 -> 5511.1849 | BW18: ='Revenue Overview'!BW18 -> 5511.1849 | BX18: ='Revenue Overview'!BX18 -> 5511.1849 | BY18: ='Revenue Overview'!BY18 -> 5511.1849 | BZ18: ='Revenue Overview'!BZ18 -> 5511.1849 | CA18: ='Revenue Overview'!CA18 -> 5511.1849 | CB18: ='Revenue Overview'!CB18 -> 5511.1849 | CC18: ='Revenue Overview'!CC18 -> 5511.1849 | ... CG18: ='Revenue Overview'!CG18 -> 5511.1849 | CH18: =SUM(BV18:CG18) -> 66134.219
B19: ='Revenue Overview'!B19 -> Product 8 | C19: INC8 | V19: ='Revenue Overview'!V19 -> 1050 | W19: ='Revenue Overview'!W19 -> 2100 | X19: ='Revenue Overview'!X19 -> 3150 | Y19: ='Revenue Overview'!Y19 -> 4725 | Z19: ='Revenue Overview'!Z19 -> 4725 | AA19: ='Revenue Overview'!AA19 -> 4725 | AB19: ='Revenue Overview'!AB19 -> 4725 | AC19: ='Revenue Overview'!AC19 -> 4725 | AD19: =SUM(R19:AC19) -> 29925 | AF19: ='Revenue Overview'!AF19 -> 4965.975 | AG19: ='Revenue Overview'!AG19 -> 4965.975 | AH19: ='Revenue Overview'!AH19 -> 4965.975 | AI19: ='Revenue Overview'!AI19 -> 4965.975 | AJ19: ='Revenue Overview'!AJ19 -> 4965.975 | AK19: ='Revenue Overview'!AK19 -> 4965.975 | AL19: ='Revenue Overview'!AL19 -> 4965.975 | AM19: ='Revenue Overview'!AM19 -> 4965.975 | ... AQ19: ='Revenue Overview'!AQ19 -> 4965.975 | AR19: =SUM(AF19:AQ19) -> 59591.7 | AT19: ='Revenue Overview'!AT19 -> 5144.7501 | AU19: ='Revenue Overview'!AU19 -> 5144.7501 | AV19: ='Revenue Overview'!AV19 -> 5144.7501 | AW19: ='Revenue Overview'!AW19 -> 5144.7501 | AX19: ='Revenue Overview'!AX19 -> 5144.7501 | AY19: ='Revenue Overview'!AY19 -> 5144.7501 | AZ19: ='Revenue Overview'!AZ19 -> 5144.7501 | BA19: ='Revenue Overview'!BA19 -> 5144.7501 | ... BE19: ='Revenue Overview'!BE19 -> 5144.7501 | BF19: =SUM(AT19:BE19) -> 61737.001 | BH19: ='Revenue Overview'!BH19 -> 5324.8164 | BI19: ='Revenue Overview'!BI19 -> 5324.8164 | BJ19: ='Revenue Overview'!BJ19 -> 5324.8164 | BK19: ='Revenue Overview'!BK19 -> 5324.8164 | BL19: ='Revenue Overview'!BL19 -> 5324.8164 | BM19: ='Revenue Overview'!BM19 -> 5324.8164 | BN19: ='Revenue Overview'!BN19 -> 5324.8164 | BO19: ='Revenue Overview'!BO19 -> 5324.8164 | ... BS19: ='Revenue Overview'!BS19 -> 5324.8164 | BT19: =SUM(BH19:BS19) -> 63897.796 | BV19: ='Revenue Overview'!BV19 -> 5511.1849 | BW19: ='Revenue Overview'!BW19 -> 5511.1849 | BX19: ='Revenue Overview'!BX19 -> 5511.1849 | BY19: ='Revenue Overview'!BY19 -> 5511.1849 | BZ19: ='Revenue Overview'!BZ19 -> 5511.1849 | CA19: ='Revenue Overview'!CA19 -> 5511.1849 | CB19: ='Revenue Overview'!CB19 -> 5511.1849 | CC19: ='Revenue Overview'!CC19 -> 5511.1849 | ... CG19: ='Revenue Overview'!CG19 -> 5511.1849 | CH19: =SUM(BV19:CG19) -> 66134.219
B20: ='Revenue Overview'!B20 -> Product 9 | C20: INC9 | V20: ='Revenue Overview'!V20 -> 1050 | W20: ='Revenue Overview'!W20 -> 2100 | X20: ='Revenue Overview'!X20 -> 3150 | Y20: ='Revenue Overview'!Y20 -> 4725 | Z20: ='Revenue Overview'!Z20 -> 4725 | AA20: ='Revenue Overview'!AA20 -> 4725 | AB20: ='Revenue Overview'!AB20 -> 4725 | AC20: ='Revenue Overview'!AC20 -> 4725 | AD20: =SUM(R20:AC20) -> 29925 | AF20: ='Revenue Overview'!AF20 -> 4965.975 | AG20: ='Revenue Overview'!AG20 -> 4965.975 | AH20: ='Revenue Overview'!AH20 -> 4965.975 | AI20: ='Revenue Overview'!AI20 -> 4965.975 | AJ20: ='Revenue Overview'!AJ20 -> 4965.975 | AK20: ='Revenue Overview'!AK20 -> 4965.975 | AL20: ='Revenue Overview'!AL20 -> 4965.975 | AM20: ='Revenue Overview'!AM20 -> 4965.975 | ... AQ20: ='Revenue Overview'!AQ20 -> 4965.975 | AR20: =SUM(AF20:AQ20) -> 59591.7 | AT20: ='Revenue Overview'!AT20 -> 5144.7501 | AU20: ='Revenue Overview'!AU20 -> 5144.7501 | AV20: ='Revenue Overview'!AV20 -> 5144.7501 | AW20: ='Revenue Overview'!AW20 -> 5144.7501 | AX20: ='Revenue Overview'!AX20 -> 5144.7501 | AY20: ='Revenue Overview'!AY20 -> 5144.7501 | AZ20: ='Revenue Overview'!AZ20 -> 5144.7501 | BA20: ='Revenue Overview'!BA20 -> 5144.7501 | ... BE20: ='Revenue Overview'!BE20 -> 5144.7501 | BF20: =SUM(AT20:BE20) -> 61737.001 | BH20: ='Revenue Overview'!BH20 -> 5324.8164 | BI20: ='Revenue Overview'!BI20 -> 5324.8164 | BJ20: ='Revenue Overview'!BJ20 -> 5324.8164 | BK20: ='Revenue Overview'!BK20 -> 5324.8164 | BL20: ='Revenue Overview'!BL20 -> 5324.8164 | BM20: ='Revenue Overview'!BM20 -> 5324.8164 | BN20: ='Revenue Overview'!BN20 -> 5324.8164 | BO20: ='Revenue Overview'!BO20 -> 5324.8164 | ... BS20: ='Revenue Overview'!BS20 -> 5324.8164 | BT20: =SUM(BH20:BS20) -> 63897.796 | BV20: ='Revenue Overview'!BV20 -> 5511.1849 | BW20: ='Revenue Overview'!BW20 -> 5511.1849 | BX20: ='Revenue Overview'!BX20 -> 5511.1849 | BY20: ='Revenue Overview'!BY20 -> 5511.1849 | BZ20: ='Revenue Overview'!BZ20 -> 5511.1849 | CA20: ='Revenue Overview'!CA20 -> 5511.1849 | CB20: ='Revenue Overview'!CB20 -> 5511.1849 | CC20: ='Revenue Overview'!CC20 -> 5511.1849 | ... CG20: ='Revenue Overview'!CG20 -> 5511.1849 | CH20: =SUM(BV20:CG20) -> 66134.219
B21: ='Revenue Overview'!B21 -> Product 10 | C21: INC10 | V21: ='Revenue Overview'!V21 -> 1050 | W21: ='Revenue Overview'!W21 -> 2100 | X21: ='Revenue Overview'!X21 -> 3150 | Y21: ='Revenue Overview'!Y21 -> 4725 | Z21: ='Revenue Overview'!Z21 -> 4725 | AA21: ='Revenue Overview'!AA21 -> 4725 | AB21: ='Revenue Overview'!AB21 -> 4725 | AC21: ='Revenue Overview'!AC21 -> 4725 | AD21: =SUM(R21:AC21) -> 29925 | AF21: ='Revenue Overview'!AF21 -> 4965.975 | AG21: ='Revenue Overview'!AG21 -> 4965.975 | AH21: ='Revenue Overview'!AH21 -> 4965.975 | AI21: ='Revenue Overview'!AI21 -> 4965.975 | AJ21: ='Revenue Overview'!AJ21 -> 4965.975 | AK21: ='Revenue Overview'!AK21 -> 4965.975 | AL21: ='Revenue Overview'!AL21 -> 4965.975 | AM21: ='Revenue Overview'!AM21 -> 4965.975 | ... AQ21: ='Revenue Overview'!AQ21 -> 4965.975 | AR21: =SUM(AF21:AQ21) -> 59591.7 | AT21: ='Revenue Overview'!AT21 -> 5144.7501 | AU21: ='Revenue Overview'!AU21 -> 5144.7501 | AV21: ='Revenue Overview'!AV21 -> 5144.7501 | AW21: ='Revenue Overview'!AW21 -> 5144.7501 | AX21: ='Revenue Overview'!AX21 -> 5144.7501 | AY21: ='Revenue Overview'!AY21 -> 5144.7501 | AZ21: ='Revenue Overview'!AZ21 -> 5144.7501 | BA21: ='Revenue Overview'!BA21 -> 5144.7501 | ... BE21: ='Revenue Overview'!BE21 -> 5144.7501 | BF21: =SUM(AT21:BE21) -> 61737.001 | BH21: ='Revenue Overview'!BH21 -> 5324.8164 | BI21: ='Revenue Overview'!BI21 -> 5324.8164 | BJ21: ='Revenue Overview'!BJ21 -> 5324.8164 | BK21: ='Revenue Overview'!BK21 -> 5324.8164 | BL21: ='Revenue Overview'!BL21 -> 5324.8164 | BM21: ='Revenue Overview'!BM21 -> 5324.8164 | BN21: ='Revenue Overview'!BN21 -> 5324.8164 | BO21: ='Revenue Overview'!BO21 -> 5324.8164 | ... BS21: ='Revenue Overview'!BS21 -> 5324.8164 | BT21: =SUM(BH21:BS21) -> 63897.796 | BV21: ='Revenue Overview'!BV21 -> 5511.1849 | BW21: ='Revenue Overview'!BW21 -> 5511.1849 | BX21: ='Revenue Overview'!BX21 -> 5511.1849 | BY21: ='Revenue Overview'!BY21 -> 5511.1849 | BZ21: ='Revenue Overview'!BZ21 -> 5511.1849 | CA21: ='Revenue Overview'!CA21 -> 5511.1849 | CB21: ='Revenue Overview'!CB21 -> 5511.1849 | CC21: ='Revenue Overview'!CC21 -> 5511.1849 | ... CG21: ='Revenue Overview'!CG21 -> 5511.1849 | CH21: =SUM(BV21:CG21) -> 66134.219
B22: TOTAL Revenues | D22: =SUM(D12:D17) -> 0 | E22: =SUM(E12:E17) -> 0 | F22: =SUM(F12:F17) -> 0 | G22: =SUM(G12:G17) -> 0 | H22: =SUM(H12:H17) -> 0 | I22: =SUM(I12:I17) -> 0 | J22: =SUM(J12:J17) -> 0 | K22: =SUM(K12:K17) -> 0 | ... O22: =SUM(O12:O17) -> 6237 | P22: =SUM(D22:O22) -> 14458.5 | R22: =SUM(R12:R17) -> 7560 | S22: =SUM(S12:S17) -> 9450 | T22: =SUM(T12:T17) -> 14175 | U22: =SUM(U12:U17) -> 17325 | V22: =SUM(V12:V17) -> 22050 | W22: =SUM(W12:W17) -> 28854 | X22: =SUM(X12:X17) -> 37800 | Y22: =SUM(Y12:Y17) -> 47250 | ... AC22: =SUM(AC12:AC17) -> 47250 | AD22: =SUM(R22:AC22) -> 373464 | AF22: =SUM(AF12:AF17) -> 49659.75 | AG22: =SUM(AG12:AG17) -> 49659.75 | AH22: =SUM(AH12:AH17) -> 49659.75 | AI22: =SUM(AI12:AI17) -> 49659.75 | AJ22: =SUM(AJ12:AJ17) -> 49659.75 | AK22: =SUM(AK12:AK17) -> 49659.75 | AL22: =SUM(AL12:AL17) -> 49659.75 | AM22: =SUM(AM12:AM17) -> 49659.75 | ... AQ22: =SUM(AQ12:AQ17) -> 49659.75 | AR22: =SUM(AF22:AQ22) -> 595917 | AT22: =SUM(AT12:AT17) -> 51447.501 | AU22: =SUM(AU12:AU17) -> 51447.501 | AV22: =SUM(AV12:AV17) -> 51447.501 | AW22: =SUM(AW12:AW17) -> 51447.501 | AX22: =SUM(AX12:AX17) -> 51447.501 | AY22: =SUM(AY12:AY17) -> 51447.501 | AZ22: =SUM(AZ12:AZ17) -> 51447.501 | BA22: =SUM(BA12:BA17) -> 51447.501 | ... BE22: =SUM(BE12:BE17) -> 51447.501 | BF22: =SUM(AT22:BE22) -> 617370.01 | BH22: =SUM(BH12:BH17) -> 53248.164 | BI22: =SUM(BI12:BI17) -> 53248.164 | BJ22: =SUM(BJ12:BJ17) -> 53248.164 | BK22: =SUM(BK12:BK17) -> 53248.164 | BL22: =SUM(BL12:BL17) -> 53248.164 | BM22: =SUM(BM12:BM17) -> 53248.164 | BN22: =SUM(BN12:BN17) -> 53248.164 | BO22: =SUM(BO12:BO17) -> 53248.164 | ... BS22: =SUM(BS12:BS17) -> 53248.164 | BT22: =SUM(BH22:BS22) -> 638977.96 | BV22: =SUM(BV12:BV17) -> 55111.849 | BW22: =SUM(BW12:BW17) -> 55111.849 | BX22: =SUM(BX12:BX17) -> 55111.849 | BY22: =SUM(BY12:BY17) -> 55111.849 | BZ22: =SUM(BZ12:BZ17) -> 55111.849 | CA22: =SUM(CA12:CA17) -> 55111.849 | CB22: =SUM(CB12:CB17) -> 55111.849 | CC22: =SUM(CC12:CC17) -> 55111.849 | ... CG22: =SUM(CG12:CG17) -> 55111.849 | CH22: =SUM(BV22:CG22) -> 661342.19
B24: TOTAL REVENUES | D24: =SUM(D22) -> 0 | E24: =SUM(E22) -> 0 | F24: =SUM(F22) -> 0 | G24: =SUM(G22) -> 0 | H24: =SUM(H22) -> 0 | I24: =SUM(I22) -> 0 | J24: =SUM(J22) -> 0 | K24: =SUM(K22) -> 0 | ... P24: =SUM(P22) -> 14458.5 | R24: =SUM(R22) -> 7560 | S24: =SUM(S22) -> 9450 | T24: =SUM(T22) -> 14175 | U24: =SUM(U22) -> 17325 | V24: =SUM(V22) -> 22050 | W24: =SUM(W22) -> 28854 | X24: =SUM(X22) -> 37800 | Y24: =SUM(Y22) -> 47250 | ... AD24: =SUM(AD22) -> 373464 | AF24: =SUM(AF22) -> 49659.75 | AG24: =SUM(AG22) -> 49659.75 | AH24: =SUM(AH22) -> 49659.75 | AI24: =SUM(AI22) -> 49659.75 | AJ24: =SUM(AJ22) -> 49659.75 | AK24: =SUM(AK22) -> 49659.75 | AL24: =SUM(AL22) -> 49659.75 | AM24: =SUM(AM22) -> 49659.75 | ... AR24: =SUM(AR22) -> 595917 | AT24: =SUM(AT22) -> 51447.501 | AU24: =SUM(AU22) -> 51447.501 | AV24: =SUM(AV22) -> 51447.501 | AW24: =SUM(AW22) -> 51447.501 | AX24: =SUM(AX22) -> 51447.501 | AY24: =SUM(AY22) -> 51447.501 | AZ24: =SUM(AZ22) -> 51447.501 | BA24: =SUM(BA22) -> 51447.501 | ... BF24: =SUM(BF22) -> 617370.01 | BH24: =SUM(BH22) -> 53248.164 | BI24: =SUM(BI22) -> 53248.164 | BJ24: =SUM(BJ22) -> 53248.164 | BK24: =SUM(BK22) -> 53248.164 | BL24: =SUM(BL22) -> 53248.164 | BM24: =SUM(BM22) -> 53248.164 | BN24: =SUM(BN22) -> 53248.164 | BO24: =SUM(BO22) -> 53248.164 | ... BT24: =SUM(BT22) -> 638977.96 | BV24: =SUM(BV22) -> 55111.849 | BW24: =SUM(BW22) -> 55111.849 | BX24: =SUM(BX22) -> 55111.849 | BY24: =SUM(BY22) -> 55111.849 | BZ24: =SUM(BZ22) -> 55111.849 | CA24: =SUM(CA22) -> 55111.849 | CB24: =SUM(CB22) -> 55111.849 | CC24: =SUM(CC22) -> 55111.849 | ... CH24: =SUM(CH22) -> 661342.19
A26: TO DO | B26: =Operational!B12 -> Main Office | C26: =Operational!C12 -> O1 | D26: =Operational!D12 -> 0 | E26: =Operational!E12 -> 0 | F26: =Operational!F12 -> 0 | G26: =Operational!G12 -> 0 | H26: =Operational!H12 -> 0 | I26: =Operational!I12 -> 0 | ... O26: =Operational!O12 -> -3000 | P26: =SUM(D26:O26) -> -18000 | R26: =Operational!R12 -> -3168 | S26: =Operational!S12 -> -3168 | T26: =Operational!T12 -> -3168 | U26: =Operational!U12 -> -3168 | V26: =Operational!V12 -> -3168 | W26: =Operational!W12 -> -3168 | X26: =Operational!X12 -> -3168 | Y26: =Operational!Y12 -> -3168 | ... AC26: =Operational!AC12 -> -3168 | AD26: =SUM(R26:AC26) -> -38016 | AF26: =Operational!AF12 -> -3329.568 | AG26: =Operational!AG12 -> -3329.568 | AH26: =Operational!AH12 -> -3329.568 | AI26: =Operational!AI12 -> -3329.568 | AJ26: =Operational!AJ12 -> -3329.568 | AK26: =Operational!AK12 -> -3329.568 | AL26: =Operational!AL12 -> -3329.568 | AM26: =Operational!AM12 -> -3329.568 | ... AQ26: =Operational!AQ12 -> -3329.568 | AR26: =SUM(AF26:AQ26) -> -39954.816 | AT26: =Operational!AT12 -> -3499.376 | AU26: =Operational!AU12 -> -3499.376 | AV26: =Operational!AV12 -> -3499.376 | AW26: =Operational!AW12 -> -3499.376 | AX26: =Operational!AX12 -> -3499.376 | AY26: =Operational!AY12 -> -3499.376 | AZ26: =Operational!AZ12 -> -3499.376 | BA26: =Operational!BA12 -> -3499.376 | ... BE26: =Operational!BE12 -> -3499.376 | BF26: =SUM(AT26:BE26) -> -41992.512 | BH26: =Operational!BH12 -> -3677.8441 | BI26: =Operational!BI12 -> -3677.8441 | BJ26: =Operational!BJ12 -> -3677.8441 | BK26: =Operational!BK12 -> -3677.8441 | BL26: =Operational!BL12 -> -3677.8441 | BM26: =Operational!BM12 -> -3677.8441 | BN26: =Operational!BN12 -> -3677.8441 | BO26: =Operational!BO12 -> -3677.8441 | ... BS26: =Operational!BS12 -> -3677.8441 | BT26: =SUM(BH26:BS26) -> -44134.13 | BV26: =Operational!BV12 -> -3865.4142 | BW26: =Operational!BW12 -> -3865.4142 | BX26: =Operational!BX12 -> -3865.4142 | BY26: =Operational!BY12 -> -3865.4142 | BZ26: =Operational!BZ12 -> -3865.4142 | CA26: =Operational!CA12 -> -3865.4142 | CB26: =Operational!CB12 -> -3865.4142 | CC26: =Operational!CC12 -> -3865.4142 | ... CG26: =Operational!CG12 -> -3865.4142 | CH26: =SUM(BV26:CG26) -> -46384.97
B27: =Operational!B13 -> Storage | C27: =Operational!C13 -> 02a | D27: =Operational!D13 -> 0 | E27: =Operational!E13 -> 0 | F27: =Operational!F13 -> 0 | G27: =Operational!G13 -> 0 | H27: =Operational!H13 -> 0 | I27: =Operational!I13 -> 0 | ... O27: =Operational!O13 -> 0 | P27: =SUM(D27:O27) -> 0 | R27: =Operational!R13 -> 0 | S27: =Operational!S13 -> 0 | T27: =Operational!T13 -> 0 | U27: =Operational!U13 -> 0 | V27: =Operational!V13 -> 0 | W27: =Operational!W13 -> 0 | X27: =Operational!X13 -> 0 | Y27: =Operational!Y13 -> 0 | ... AC27: =Operational!AC13 -> 0 | AD27: =SUM(R27:AC27) -> 0 | AF27: =Operational!AF13 -> 0 | AG27: =Operational!AG13 -> 0 | AH27: =Operational!AH13 -> 0 | AI27: =Operational!AI13 -> 0 | AJ27: =Operational!AJ13 -> 0 | AK27: =Operational!AK13 -> 0 | AL27: =Operational!AL13 -> 0 | AM27: =Operational!AM13 -> 0 | ... AQ27: =Operational!AQ13 -> 0 | AR27: =SUM(AF27:AQ27) -> 0 | AT27: =Operational!AT13 -> 0 | AU27: =Operational!AU13 -> 0 | AV27: =Operational!AV13 -> 0 | AW27: =Operational!AW13 -> 0 | AX27: =Operational!AX13 -> 0 | AY27: =Operational!AY13 -> 0 | AZ27: =Operational!AZ13 -> 0 | BA27: =Operational!BA13 -> 0 | ... BE27: =Operational!BE13 -> 0 | BF27: =SUM(AT27:BE27) -> 0 | BH27: =Operational!BH13 -> 0 | BI27: =Operational!BI13 -> 0 | BJ27: =Operational!BJ13 -> 0 | BK27: =Operational!BK13 -> 0 | BL27: =Operational!BL13 -> 0 | BM27: =Operational!BM13 -> 0 | BN27: =Operational!BN13 -> 0 | BO27: =Operational!BO13 -> 0 | ... BS27: =Operational!BS13 -> 0 | BT27: =SUM(BH27:BS27) -> 0 | BV27: =Operational!BV13 -> 0 | BW27: =Operational!BW13 -> 0 | BX27: =Operational!BX13 -> 0 | BY27: =Operational!BY13 -> 0 | BZ27: =Operational!BZ13 -> 0 | CA27: =Operational!CA13 -> 0 | CB27: =Operational!CB13 -> 0 | CC27: =Operational!CC13 -> 0 | ... CG27: =Operational!CG13 -> 0 | CH27: =SUM(BV27:CG27) -> 0
B28: =Operational!B14 -> x | C28: =Operational!C14 -> O2b | D28: =Operational!D14 -> 0 | E28: =Operational!E14 -> 0 | F28: =Operational!F14 -> 0 | G28: =Operational!G14 -> 0 | H28: =Operational!H14 -> 0 | I28: =Operational!I14 -> 0 | ... O28: =Operational!O14 -> 0 | P28: =SUM(D28:O28) -> 0 | R28: =Operational!R14 -> 0 | S28: =Operational!S14 -> 0 | T28: =Operational!T14 -> 0 | U28: =Operational!U14 -> 0 | V28: =Operational!V14 -> 0 | W28: =Operational!W14 -> 0 | X28: =Operational!X14 -> 0 | Y28: =Operational!Y14 -> 0 | ... AC28: =Operational!AC14 -> 0 | AD28: =SUM(R28:AC28) -> 0 | AF28: =Operational!AF14 -> 0 | AG28: =Operational!AG14 -> 0 | AH28: =Operational!AH14 -> 0 | AI28: =Operational!AI14 -> 0 | AJ28: =Operational!AJ14 -> 0 | AK28: =Operational!AK14 -> 0 | AL28: =Operational!AL14 -> 0 | AM28: =Operational!AM14 -> 0 | ... AQ28: =Operational!AQ14 -> 0 | AR28: =SUM(AF28:AQ28) -> 0 | AT28: =Operational!AT14 -> 0 | AU28: =Operational!AU14 -> 0 | AV28: =Operational!AV14 -> 0 | AW28: =Operational!AW14 -> 0 | AX28: =Operational!AX14 -> 0 | AY28: =Operational!AY14 -> 0 | AZ28: =Operational!AZ14 -> 0 | BA28: =Operational!BA14 -> 0 | ... BE28: =Operational!BE14 -> 0 | BF28: =SUM(AT28:BE28) -> 0 | BH28: =Operational!BH14 -> 0 | BI28: =Operational!BI14 -> 0 | BJ28: =Operational!BJ14 -> 0 | BK28: =Operational!BK14 -> 0 | BL28: =Operational!BL14 -> 0 | BM28: =Operational!BM14 -> 0 | BN28: =Operational!BN14 -> 0 | BO28: =Operational!BO14 -> 0 | ... BS28: =Operational!BS14 -> 0 | BT28: =SUM(BH28:BS28) -> 0 | BV28: =Operational!BV14 -> 0 | BW28: =Operational!BW14 -> 0 | BX28: =Operational!BX14 -> 0 | BY28: =Operational!BY14 -> 0 | BZ28: =Operational!BZ14 -> 0 | CA28: =Operational!CA14 -> 0 | CB28: =Operational!CB14 -> 0 | CC28: =Operational!CC14 -> 0 | ... CG28: =Operational!CG14 -> 0 | CH28: =SUM(BV28:CG28) -> 0
B29: =Operational!B15 -> Cleaning | C29: =Operational!C15 -> O3 | D29: =Operational!D15 -> 0 | E29: =Operational!E15 -> 0 | F29: =Operational!F15 -> 0 | G29: =Operational!G15 -> 0 | H29: =Operational!H15 -> 0 | I29: =Operational!I15 -> 0 | ... O29: =Operational!O15 -> -500 | P29: =SUM(D29:O29) -> -3000 | R29: =Operational!R15 -> -528 | S29: =Operational!S15 -> -528 | T29: =Operational!T15 -> -528 | U29: =Operational!U15 -> -528 | V29: =Operational!V15 -> -528 | W29: =Operational!W15 -> -528 | X29: =Operational!X15 -> -528 | Y29: =Operational!Y15 -> -528 | ... AC29: =Operational!AC15 -> -528 | AD29: =SUM(R29:AC29) -> -6336 | AF29: =Operational!AF15 -> -554.928 | AG29: =Operational!AG15 -> -554.928 | AH29: =Operational!AH15 -> -554.928 | AI29: =Operational!AI15 -> -554.928 | AJ29: =Operational!AJ15 -> -554.928 | AK29: =Operational!AK15 -> -554.928 | AL29: =Operational!AL15 -> -554.928 | AM29: =Operational!AM15 -> -554.928 | ... AQ29: =Operational!AQ15 -> -554.928 | AR29: =SUM(AF29:AQ29) -> -6659.136 | AT29: =Operational!AT15 -> -583.22933 | AU29: =Operational!AU15 -> -583.22933 | AV29: =Operational!AV15 -> -583.22933 | AW29: =Operational!AW15 -> -583.22933 | AX29: =Operational!AX15 -> -583.22933 | AY29: =Operational!AY15 -> -583.22933 | AZ29: =Operational!AZ15 -> -583.22933 | BA29: =Operational!BA15 -> -583.22933 | ... BE29: =Operational!BE15 -> -583.22933 | BF29: =SUM(AT29:BE29) -> -6998.7519 | BH29: =Operational!BH15 -> -612.97402 | BI29: =Operational!BI15 -> -612.97402 | BJ29: =Operational!BJ15 -> -612.97402 | BK29: =Operational!BK15 -> -612.97402 | BL29: =Operational!BL15 -> -612.97402 | BM29: =Operational!BM15 -> -612.97402 | BN29: =Operational!BN15 -> -612.97402 | BO29: =Operational!BO15 -> -612.97402 | ... BS29: =Operational!BS15 -> -612.97402 | BT29: =SUM(BH29:BS29) -> -7355.6883 | BV29: =Operational!BV15 -> -644.2357 | BW29: =Operational!BW15 -> -644.2357 | BX29: =Operational!BX15 -> -644.2357 | BY29: =Operational!BY15 -> -644.2357 | BZ29: =Operational!BZ15 -> -644.2357 | CA29: =Operational!CA15 -> -644.2357 | CB29: =Operational!CB15 -> -644.2357 | CC29: =Operational!CC15 -> -644.2357 | ... CG29: =Operational!CG15 -> -644.2357 | CH29: =SUM(BV29:CG29) -> -7730.8284
B30: =Operational!B16 -> Electricity | C30: =Operational!C16 -> O4 | D30: =Operational!D16 -> 0 | E30: =Operational!E16 -> 0 | F30: =Operational!F16 -> 0 | G30: =Operational!G16 -> 0 | H30: =Operational!H16 -> 0 | I30: =Operational!I16 -> 0 | ... O30: =Operational!O16 -> -550 | P30: =SUM(D30:O30) -> -3300 | R30: =Operational!R16 -> -580.8 | S30: =Operational!S16 -> -580.8 | T30: =Operational!T16 -> -580.8 | U30: =Operational!U16 -> -580.8 | V30: =Operational!V16 -> -580.8 | W30: =Operational!W16 -> -580.8 | X30: =Operational!X16 -> -580.8 | Y30: =Operational!Y16 -> -580.8 | ... AC30: =Operational!AC16 -> -580.8 | AD30: =SUM(R30:AC30) -> -6969.6 | AF30: =Operational!AF16 -> -610.4208 | AG30: =Operational!AG16 -> -610.4208 | AH30: =Operational!AH16 -> -610.4208 | AI30: =Operational!AI16 -> -610.4208 | AJ30: =Operational!AJ16 -> -610.4208 | AK30: =Operational!AK16 -> -610.4208 | AL30: =Operational!AL16 -> -610.4208 | AM30: =Operational!AM16 -> -610.4208 | ... AQ30: =Operational!AQ16 -> -610.4208 | AR30: =SUM(AF30:AQ30) -> -7325.0496 | AT30: =Operational!AT16 -> -641.55226 | AU30: =Operational!AU16 -> -641.55226 | AV30: =Operational!AV16 -> -641.55226 | AW30: =Operational!AW16 -> -641.55226 | AX30: =Operational!AX16 -> -641.55226 | AY30: =Operational!AY16 -> -641.55226 | AZ30: =Operational!AZ16 -> -641.55226 | BA30: =Operational!BA16 -> -641.55226 | ... BE30: =Operational!BE16 -> -641.55226 | BF30: =SUM(AT30:BE30) -> -7698.6271 | BH30: =Operational!BH16 -> -674.27143 | BI30: =Operational!BI16 -> -674.27143 | BJ30: =Operational!BJ16 -> -674.27143 | BK30: =Operational!BK16 -> -674.27143 | BL30: =Operational!BL16 -> -674.27143 | BM30: =Operational!BM16 -> -674.27143 | BN30: =Operational!BN16 -> -674.27143 | BO30: =Operational!BO16 -> -674.27143 | ... BS30: =Operational!BS16 -> -674.27143 | BT30: =SUM(BH30:BS30) -> -8091.2571 | BV30: =Operational!BV16 -> -708.65927 | BW30: =Operational!BW16 -> -708.65927 | BX30: =Operational!BX16 -> -708.65927 | BY30: =Operational!BY16 -> -708.65927 | BZ30: =Operational!BZ16 -> -708.65927 | CA30: =Operational!CA16 -> -708.65927 | CB30: =Operational!CB16 -> -708.65927 | CC30: =Operational!CC16 -> -708.65927 | ... CG30: =Operational!CG16 -> -708.65927 | CH30: =SUM(BV30:CG30) -> -8503.9112
B31: =Operational!B17 -> Cooling / Heating | C31: =Operational!C17 -> O5 | D31: =Operational!D17 -> 0 | E31: =Operational!E17 -> 0 | F31: =Operational!F17 -> 0 | G31: =Operational!G17 -> 0 | H31: =Operational!H17 -> 0 | I31: =Operational!I17 -> 0 | ... O31: =Operational!O17 -> -200 | P31: =SUM(D31:O31) -> -1200 | R31: =Operational!R17 -> -211.2 | S31: =Operational!S17 -> -211.2 | T31: =Operational!T17 -> -211.2 | U31: =Operational!U17 -> -211.2 | V31: =Operational!V17 -> -211.2 | W31: =Operational!W17 -> -211.2 | X31: =Operational!X17 -> -211.2 | Y31: =Operational!Y17 -> -211.2 | ... AC31: =Operational!AC17 -> -211.2 | AD31: =SUM(R31:AC31) -> -2534.4 | AF31: =Operational!AF17 -> -221.9712 | AG31: =Operational!AG17 -> -221.9712 | AH31: =Operational!AH17 -> -221.9712 | AI31: =Operational!AI17 -> -221.9712 | AJ31: =Operational!AJ17 -> -221.9712 | AK31: =Operational!AK17 -> -221.9712 | AL31: =Operational!AL17 -> -221.9712 | AM31: =Operational!AM17 -> -221.9712 | ... AQ31: =Operational!AQ17 -> -221.9712 | AR31: =SUM(AF31:AQ31) -> -2663.6544 | AT31: =Operational!AT17 -> -233.29173 | AU31: =Operational!AU17 -> -233.29173 | AV31: =Operational!AV17 -> -233.29173 | AW31: =Operational!AW17 -> -233.29173 | AX31: =Operational!AX17 -> -233.29173 | AY31: =Operational!AY17 -> -233.29173 | AZ31: =Operational!AZ17 -> -233.29173 | BA31: =Operational!BA17 -> -233.29173 | ... BE31: =Operational!BE17 -> -233.29173 | BF31: =SUM(AT31:BE31) -> -2799.5008 | BH31: =Operational!BH17 -> -245.18961 | BI31: =Operational!BI17 -> -245.18961 | BJ31: =Operational!BJ17 -> -245.18961 | BK31: =Operational!BK17 -> -245.18961 | BL31: =Operational!BL17 -> -245.18961 | BM31: =Operational!BM17 -> -245.18961 | BN31: =Operational!BN17 -> -245.18961 | BO31: =Operational!BO17 -> -245.18961 | ... BS31: =Operational!BS17 -> -245.18961 | BT31: =SUM(BH31:BS31) -> -2942.2753 | BV31: =Operational!BV17 -> -257.69428 | BW31: =Operational!BW17 -> -257.69428 | BX31: =Operational!BX17 -> -257.69428 | BY31: =Operational!BY17 -> -257.69428 | BZ31: =Operational!BZ17 -> -257.69428 | CA31: =Operational!CA17 -> -257.69428 | CB31: =Operational!CB17 -> -257.69428 | CC31: =Operational!CC17 -> -257.69428 | ... CG31: =Operational!CG17 -> -257.69428 | CH31: =SUM(BV31:CG31) -> -3092.3314
B32: =Operational!B18 -> Service Charges | C32: =Operational!C18 -> O6 | D32: =Operational!D18 -> 0 | E32: =Operational!E18 -> 0 | F32: =Operational!F18 -> 0 | G32: =Operational!G18 -> 0 | H32: =Operational!H18 -> 0 | I32: =Operational!I18 -> 0 | ... O32: =Operational!O18 -> -350 | P32: =SUM(D32:O32) -> -2100 | R32: =Operational!R18 -> -369.6 | S32: =Operational!S18 -> -369.6 | T32: =Operational!T18 -> -369.6 | U32: =Operational!U18 -> -369.6 | V32: =Operational!V18 -> -369.6 | W32: =Operational!W18 -> -369.6 | X32: =Operational!X18 -> -369.6 | Y32: =Operational!Y18 -> -369.6 | ... AC32: =Operational!AC18 -> -369.6 | AD32: =SUM(R32:AC32) -> -4435.2 | AF32: =Operational!AF18 -> -388.4496 | AG32: =Operational!AG18 -> -388.4496 | AH32: =Operational!AH18 -> -388.4496 | AI32: =Operational!AI18 -> -388.4496 | AJ32: =Operational!AJ18 -> -388.4496 | AK32: =Operational!AK18 -> -388.4496 | AL32: =Operational!AL18 -> -388.4496 | AM32: =Operational!AM18 -> -388.4496 | ... AQ32: =Operational!AQ18 -> -388.4496 | AR32: =SUM(AF32:AQ32) -> -4661.3952 | AT32: =Operational!AT18 -> -408.26053 | AU32: =Operational!AU18 -> -408.26053 | AV32: =Operational!AV18 -> -408.26053 | AW32: =Operational!AW18 -> -408.26053 | AX32: =Operational!AX18 -> -408.26053 | AY32: =Operational!AY18 -> -408.26053 | AZ32: =Operational!AZ18 -> -408.26053 | BA32: =Operational!BA18 -> -408.26053 | ... BE32: =Operational!BE18 -> -408.26053 | BF32: =SUM(AT32:BE32) -> -4899.1264 | BH32: =Operational!BH18 -> -429.08182 | BI32: =Operational!BI18 -> -429.08182 | BJ32: =Operational!BJ18 -> -429.08182 | BK32: =Operational!BK18 -> -429.08182 | BL32: =Operational!BL18 -> -429.08182 | BM32: =Operational!BM18 -> -429.08182 | BN32: =Operational!BN18 -> -429.08182 | BO32: =Operational!BO18 -> -429.08182 | ... BS32: =Operational!BS18 -> -429.08182 | BT32: =SUM(BH32:BS32) -> -5148.9818 | BV32: =Operational!BV18 -> -450.96499 | BW32: =Operational!BW18 -> -450.96499 | BX32: =Operational!BX18 -> -450.96499 | BY32: =Operational!BY18 -> -450.96499 | BZ32: =Operational!BZ18 -> -450.96499 | CA32: =Operational!CA18 -> -450.96499 | CB32: =Operational!CB18 -> -450.96499 | CC32: =Operational!CC18 -> -450.96499 | ... CG32: =Operational!CG18 -> -450.96499 | CH32: =SUM(BV32:CG32) -> -5411.5799
B33: OPERATIONAL | D33: =SUM(D26:D32) -> 0 | E33: =SUM(E26:E32) -> 0 | F33: =SUM(F26:F32) -> 0 | G33: =SUM(G26:G32) -> 0 | H33: =SUM(H26:H32) -> 0 | I33: =SUM(I26:I32) -> 0 | J33: =SUM(J26:J32) -> -4600 | K33: =SUM(K26:K32) -> -4600 | ... O33: =SUM(O26:O32) -> -4600 | P33: =SUM(D33:O33) -> -27600 | R33: =SUM(R26:R32) -> -4857.6 | S33: =SUM(S26:S32) -> -4857.6 | T33: =SUM(T26:T32) -> -4857.6 | U33: =SUM(U26:U32) -> -4857.6 | V33: =SUM(V26:V32) -> -4857.6 | W33: =SUM(W26:W32) -> -4857.6 | X33: =SUM(X26:X32) -> -4857.6 | Y33: =SUM(Y26:Y32) -> -4857.6 | ... AC33: =SUM(AC26:AC32) -> -4857.6 | AD33: =SUM(R33:AC33) -> -58291.2 | AF33: =SUM(AF26:AF32) -> -5105.3376 | AG33: =SUM(AG26:AG32) -> -5105.3376 | AH33: =SUM(AH26:AH32) -> -5105.3376 | AI33: =SUM(AI26:AI32) -> -5105.3376 | AJ33: =SUM(AJ26:AJ32) -> -5105.3376 | AK33: =SUM(AK26:AK32) -> -5105.3376 | AL33: =SUM(AL26:AL32) -> -5105.3376 | AM33: =SUM(AM26:AM32) -> -5105.3376 | ... AQ33: =SUM(AQ26:AQ32) -> -5105.3376 | AR33: =SUM(AF33:AQ33) -> -61264.051 | AT33: =SUM(AT26:AT32) -> -5365.7098 | AU33: =SUM(AU26:AU32) -> -5365.7098 | AV33: =SUM(AV26:AV32) -> -5365.7098 | AW33: =SUM(AW26:AW32) -> -5365.7098 | AX33: =SUM(AX26:AX32) -> -5365.7098 | AY33: =SUM(AY26:AY32) -> -5365.7098 | AZ33: =SUM(AZ26:AZ32) -> -5365.7098 | BA33: =SUM(BA26:BA32) -> -5365.7098 | ... BE33: =SUM(BE26:BE32) -> -5365.7098 | BF33: =SUM(AT33:BE33) -> -64388.518 | BH33: =SUM(BH26:BH32) -> -5639.361 | BI33: =SUM(BI26:BI32) -> -5639.361 | BJ33: =SUM(BJ26:BJ32) -> -5639.361 | BK33: =SUM(BK26:BK32) -> -5639.361 | BL33: =SUM(BL26:BL32) -> -5639.361 | BM33: =SUM(BM26:BM32) -> -5639.361 | BN33: =SUM(BN26:BN32) -> -5639.361 | BO33: =SUM(BO26:BO32) -> -5639.361 | ... BS33: =SUM(BS26:BS32) -> -5639.361 | BT33: =SUM(BH33:BS33) -> -67672.332 | BV33: =SUM(BV26:BV32) -> -5926.9684 | BW33: =SUM(BW26:BW32) -> -5926.9684 | BX33: =SUM(BX26:BX32) -> -5926.9684 | BY33: =SUM(BY26:BY32) -> -5926.9684 | BZ33: =SUM(BZ26:BZ32) -> -5926.9684 | CA33: =SUM(CA26:CA32) -> -5926.9684 | CB33: =SUM(CB26:CB32) -> -5926.9684 | CC33: =SUM(CC26:CC32) -> -5926.9684 | ... CG33: =SUM(CG26:CG32) -> -5926.9684 | CH33: =SUM(BV33:CG33) -> -71123.621
B35: ='Staff - Costs 2'!B12 -> Managing Director | C35: ='Staff - Costs 2'!C12 -> P1 | D35: ='Staff - Costs 2'!D12 -> 0 | E35: ='Staff - Costs 2'!E12 -> 0 | F35: ='Staff - Costs 2'!F12 -> 0 | G35: ='Staff - Costs 2'!G12 -> 0 | H35: ='Staff - Costs 2'!H12 -> 0 | I35: ='Staff - Costs 2'!I12 -> 0 | ... O35: ='Staff - Costs 2'!O12 -> -7383.096 | P35: =SUM(D35:O35) -> -34454.448 | R35: ='Staff - Costs 2'!R12 -> -5197.6996 | S35: ='Staff - Costs 2'!S12 -> -5197.6996 | T35: ='Staff - Costs 2'!T12 -> -5197.6996 | U35: ='Staff - Costs 2'!U12 -> -5197.6996 | V35: ='Staff - Costs 2'!V12 -> -5197.6996 | W35: ='Staff - Costs 2'!W12 -> -5197.6996 | X35: ='Staff - Costs 2'!X12 -> -5197.6996 | Y35: ='Staff - Costs 2'!Y12 -> -5197.6996 | ... AC35: ='Staff - Costs 2'!AC12 -> -7796.5494 | AD35: =SUM(R35:AC35) -> -67570.095 | AF35: ='Staff - Costs 2'!AF12 -> -5462.7823 | AG35: ='Staff - Costs 2'!AG12 -> -5462.7823 | AH35: ='Staff - Costs 2'!AH12 -> -5462.7823 | AI35: ='Staff - Costs 2'!AI12 -> -5462.7823 | AJ35: ='Staff - Costs 2'!AJ12 -> -5462.7823 | AK35: ='Staff - Costs 2'!AK12 -> -5462.7823 | AL35: ='Staff - Costs 2'!AL12 -> -5462.7823 | AM35: ='Staff - Costs 2'!AM12 -> -5462.7823 | ... AQ35: ='Staff - Costs 2'!AQ12 -> -8194.1734 | AR35: =SUM(AF35:AQ35) -> -71016.169 | AT35: ='Staff - Costs 2'!AT12 -> -5741.3842 | AU35: ='Staff - Costs 2'!AU12 -> -5741.3842 | AV35: ='Staff - Costs 2'!AV12 -> -5741.3842 | AW35: ='Staff - Costs 2'!AW12 -> -5741.3842 | AX35: ='Staff - Costs 2'!AX12 -> -5741.3842 | AY35: ='Staff - Costs 2'!AY12 -> -5741.3842 | AZ35: ='Staff - Costs 2'!AZ12 -> -5741.3842 | BA35: ='Staff - Costs 2'!BA12 -> -5741.3842 | ... BE35: ='Staff - Costs 2'!BE12 -> -8612.0762 | BF35: =SUM(AT35:BE35) -> -74637.994 | BH35: ='Staff - Costs 2'!BH12 -> -6034.1947 | BI35: ='Staff - Costs 2'!BI12 -> -6034.1947 | BJ35: ='Staff - Costs 2'!BJ12 -> -6034.1947 | BK35: ='Staff - Costs 2'!BK12 -> -6034.1947 | BL35: ='Staff - Costs 2'!BL12 -> -6034.1947 | BM35: ='Staff - Costs 2'!BM12 -> -6034.1947 | BN35: ='Staff - Costs 2'!BN12 -> -6034.1947 | BO35: ='Staff - Costs 2'!BO12 -> -6034.1947 | ... BS35: ='Staff - Costs 2'!BS12 -> -9051.2921 | BT35: =SUM(BH35:BS35) -> -78444.532 | BV35: ='Staff - Costs 2'!BV12 -> -6341.9387 | BW35: ='Staff - Costs 2'!BW12 -> -6341.9387 | BX35: ='Staff - Costs 2'!BX12 -> -6341.9387 | BY35: ='Staff - Costs 2'!BY12 -> -6341.9387 | BZ35: ='Staff - Costs 2'!BZ12 -> -6341.9387 | CA35: ='Staff - Costs 2'!CA12 -> -6341.9387 | CB35: ='Staff - Costs 2'!CB12 -> -6341.9387 | CC35: ='Staff - Costs 2'!CC12 -> -6341.9387 | ... CG35: ='Staff - Costs 2'!CG12 -> -9512.908 | CH35: =SUM(BV35:CG35) -> -82445.203
B36: ='Staff - Costs 2'!B13 -> Office Manager | C36: ='Staff - Costs 2'!C13 -> P2 | D36: ='Staff - Costs 2'!D13 -> 0 | E36: ='Staff - Costs 2'!E13 -> 0 | F36: ='Staff - Costs 2'!F13 -> 0 | G36: ='Staff - Costs 2'!G13 -> 0 | H36: ='Staff - Costs 2'!H13 -> 0 | I36: ='Staff - Costs 2'!I13 -> 0 | ... O36: ='Staff - Costs 2'!O13 -> -3375.1296 | P36: =SUM(D36:O36) -> -15750.605 | R36: ='Staff - Costs 2'!R13 -> -2376.0912 | S36: ='Staff - Costs 2'!S13 -> -2376.0912 | T36: ='Staff - Costs 2'!T13 -> -2376.0912 | U36: ='Staff - Costs 2'!U13 -> -2376.0912 | V36: ='Staff - Costs 2'!V13 -> -2376.0912 | W36: ='Staff - Costs 2'!W13 -> -2376.0912 | X36: ='Staff - Costs 2'!X13 -> -2376.0912 | Y36: ='Staff - Costs 2'!Y13 -> -2376.0912 | ... AC36: ='Staff - Costs 2'!AC13 -> -3564.1369 | AD36: =SUM(R36:AC36) -> -30889.186 | AF36: ='Staff - Costs 2'!AF13 -> -2497.2719 | AG36: ='Staff - Costs 2'!AG13 -> -2497.2719 | AH36: ='Staff - Costs 2'!AH13 -> -2497.2719 | AI36: ='Staff - Costs 2'!AI13 -> -2497.2719 | AJ36: ='Staff - Costs 2'!AJ13 -> -2497.2719 | AK36: ='Staff - Costs 2'!AK13 -> -2497.2719 | AL36: ='Staff - Costs 2'!AL13 -> -2497.2719 | AM36: ='Staff - Costs 2'!AM13 -> -2497.2719 | ... AQ36: ='Staff - Costs 2'!AQ13 -> -3745.9078 | AR36: =SUM(AF36:AQ36) -> -32464.535 | AT36: ='Staff - Costs 2'!AT13 -> -2624.6328 | AU36: ='Staff - Costs 2'!AU13 -> -2624.6328 | AV36: ='Staff - Costs 2'!AV13 -> -2624.6328 | AW36: ='Staff - Costs 2'!AW13 -> -2624.6328 | AX36: ='Staff - Costs 2'!AX13 -> -2624.6328 | AY36: ='Staff - Costs 2'!AY13 -> -2624.6328 | AZ36: ='Staff - Costs 2'!AZ13 -> -2624.6328 | BA36: ='Staff - Costs 2'!BA13 -> -2624.6328 | ... BE36: ='Staff - Costs 2'!BE13 -> -3936.9491 | BF36: =SUM(AT36:BE36) -> -34120.226 | BH36: ='Staff - Costs 2'!BH13 -> -2758.489 | BI36: ='Staff - Costs 2'!BI13 -> -2758.489 | BJ36: ='Staff - Costs 2'!BJ13 -> -2758.489 | BK36: ='Staff - Costs 2'!BK13 -> -2758.489 | BL36: ='Staff - Costs 2'!BL13 -> -2758.489 | BM36: ='Staff - Costs 2'!BM13 -> -2758.489 | BN36: ='Staff - Costs 2'!BN13 -> -2758.489 | BO36: ='Staff - Costs 2'!BO13 -> -2758.489 | ... BS36: ='Staff - Costs 2'!BS13 -> -4137.7335 | BT36: =SUM(BH36:BS36) -> -35860.357 | BV36: ='Staff - Costs 2'!BV13 -> -2899.172 | BW36: ='Staff - Costs 2'!BW13 -> -2899.172 | BX36: ='Staff - Costs 2'!BX13 -> -2899.172 | BY36: ='Staff - Costs 2'!BY13 -> -2899.172 | BZ36: ='Staff - Costs 2'!BZ13 -> -2899.172 | CA36: ='Staff - Costs 2'!CA13 -> -2899.172 | CB36: ='Staff - Costs 2'!CB13 -> -2899.172 | CC36: ='Staff - Costs 2'!CC13 -> -2899.172 | ... CG36: ='Staff - Costs 2'!CG13 -> -4348.758 | CH36: =SUM(BV36:CG36) -> -37689.236
B37: ='Staff - Costs 2'!B14 -> IT | C37: ='Staff - Costs 2'!C14 -> P3 | D37: ='Staff - Costs 2'!D14 -> 0 | E37: ='Staff - Costs 2'!E14 -> 0 | F37: ='Staff - Costs 2'!F14 -> 0 | G37: ='Staff - Costs 2'!G14 -> 0 | H37: ='Staff - Costs 2'!H14 -> 0 | I37: ='Staff - Costs 2'!I14 -> 0 | ... O37: ='Staff - Costs 2'!O14 -> -1371.1464 | P37: =SUM(D37:O37) -> -6398.6832 | R37: ='Staff - Costs 2'!R14 -> -965.28707 | S37: ='Staff - Costs 2'!S14 -> -965.28707 | T37: ='Staff - Costs 2'!T14 -> -965.28707 | U37: ='Staff - Costs 2'!U14 -> -965.28707 | V37: ='Staff - Costs 2'!V14 -> -965.28707 | W37: ='Staff - Costs 2'!W14 -> -965.28707 | X37: ='Staff - Costs 2'!X14 -> -965.28707 | Y37: ='Staff - Costs 2'!Y14 -> -965.28707 | ... AC37: ='Staff - Costs 2'!AC14 -> -1447.9306 | AD37: =SUM(R37:AC37) -> -12548.732 | AF37: ='Staff - Costs 2'!AF14 -> -1014.5167 | AG37: ='Staff - Costs 2'!AG14 -> -1014.5167 | AH37: ='Staff - Costs 2'!AH14 -> -1014.5167 | AI37: ='Staff - Costs 2'!AI14 -> -1014.5167 | AJ37: ='Staff - Costs 2'!AJ14 -> -1014.5167 | AK37: ='Staff - Costs 2'!AK14 -> -1014.5167 | AL37: ='Staff - Costs 2'!AL14 -> -1014.5167 | AM37: ='Staff - Costs 2'!AM14 -> -1014.5167 | ... AQ37: ='Staff - Costs 2'!AQ14 -> -1521.7751 | AR37: =SUM(AF37:AQ37) -> -13188.717 | AT37: ='Staff - Costs 2'!AT14 -> -1066.2571 | AU37: ='Staff - Costs 2'!AU14 -> -1066.2571 | AV37: ='Staff - Costs 2'!AV14 -> -1066.2571 | AW37: ='Staff - Costs 2'!AW14 -> -1066.2571 | AX37: ='Staff - Costs 2'!AX14 -> -1066.2571 | AY37: ='Staff - Costs 2'!AY14 -> -1066.2571 | AZ37: ='Staff - Costs 2'!AZ14 -> -1066.2571 | BA37: ='Staff - Costs 2'!BA14 -> -1066.2571 | ... BE37: ='Staff - Costs 2'!BE14 -> -1599.3856 | BF37: =SUM(AT37:BE37) -> -13861.342 | BH37: ='Staff - Costs 2'!BH14 -> -1120.6362 | BI37: ='Staff - Costs 2'!BI14 -> -1120.6362 | BJ37: ='Staff - Costs 2'!BJ14 -> -1120.6362 | BK37: ='Staff - Costs 2'!BK14 -> -1120.6362 | BL37: ='Staff - Costs 2'!BL14 -> -1120.6362 | BM37: ='Staff - Costs 2'!BM14 -> -1120.6362 | BN37: ='Staff - Costs 2'!BN14 -> -1120.6362 | BO37: ='Staff - Costs 2'!BO14 -> -1120.6362 | ... BS37: ='Staff - Costs 2'!BS14 -> -1680.9543 | BT37: =SUM(BH37:BS37) -> -14568.27 | BV37: ='Staff - Costs 2'!BV14 -> -1177.7886 | BW37: ='Staff - Costs 2'!BW14 -> -1177.7886 | BX37: ='Staff - Costs 2'!BX14 -> -1177.7886 | BY37: ='Staff - Costs 2'!BY14 -> -1177.7886 | BZ37: ='Staff - Costs 2'!BZ14 -> -1177.7886 | CA37: ='Staff - Costs 2'!CA14 -> -1177.7886 | CB37: ='Staff - Costs 2'!CB14 -> -1177.7886 | CC37: ='Staff - Costs 2'!CC14 -> -1177.7886 | ... CG37: ='Staff - Costs 2'!CG14 -> -1766.6829 | CH37: =SUM(BV37:CG37) -> -15311.252
B38: ='Staff - Costs 2'!B15 | C38: ='Staff - Costs 2'!C15 | D38: ='Staff - Costs 2'!D15 | E38: ='Staff - Costs 2'!E15 | F38: ='Staff - Costs 2'!F15 | G38: ='Staff - Costs 2'!G15 | H38: ='Staff - Costs 2'!H15 | I38: ='Staff - Costs 2'!I15 | ... O38: ='Staff - Costs 2'!O15 | P38: =SUM(D38:O38) -> 0 | R38: ='Staff - Costs 2'!R15 | S38: ='Staff - Costs 2'!S15 | T38: ='Staff - Costs 2'!T15 | U38: ='Staff - Costs 2'!U15 | V38: ='Staff - Costs 2'!V15 | W38: ='Staff - Costs 2'!W15 | X38: ='Staff - Costs 2'!X15 | Y38: ='Staff - Costs 2'!Y15 | ... AC38: ='Staff - Costs 2'!AC15 | AD38: =SUM(R38:AC38) -> 0 | AF38: ='Staff - Costs 2'!AF15 | AG38: ='Staff - Costs 2'!AG15 | AH38: ='Staff - Costs 2'!AH15 | AI38: ='Staff - Costs 2'!AI15 | AJ38: ='Staff - Costs 2'!AJ15 | AK38: ='Staff - Costs 2'!AK15 | AL38: ='Staff - Costs 2'!AL15 | AM38: ='Staff - Costs 2'!AM15 | ... AQ38: ='Staff - Costs 2'!AQ15 | AR38: =SUM(AF38:AQ38) -> 0 | AT38: ='Staff - Costs 2'!AT15 | AU38: ='Staff - Costs 2'!AU15 | AV38: ='Staff - Costs 2'!AV15 | AW38: ='Staff - Costs 2'!AW15 | AX38: ='Staff - Costs 2'!AX15 | AY38: ='Staff - Costs 2'!AY15 | AZ38: ='Staff - Costs 2'!AZ15 | BA38: ='Staff - Costs 2'!BA15 | ... BE38: ='Staff - Costs 2'!BE15 | BF38: =SUM(AT38:BE38) -> 0 | BH38: ='Staff - Costs 2'!BH15 | BI38: ='Staff - Costs 2'!BI15 | BJ38: ='Staff - Costs 2'!BJ15 | BK38: ='Staff - Costs 2'!BK15 | BL38: ='Staff - Costs 2'!BL15 | BM38: ='Staff - Costs 2'!BM15 | BN38: ='Staff - Costs 2'!BN15 | BO38: ='Staff - Costs 2'!BO15 | ... BS38: ='Staff - Costs 2'!BS15 | BT38: =SUM(BH38:BS38) -> 0 | BV38: ='Staff - Costs 2'!BV15 | BW38: ='Staff - Costs 2'!BW15 | BX38: ='Staff - Costs 2'!BX15 | BY38: ='Staff - Costs 2'!BY15 | BZ38: ='Staff - Costs 2'!BZ15 | CA38: ='Staff - Costs 2'!CA15 | CB38: ='Staff - Costs 2'!CB15 | CC38: ='Staff - Costs 2'!CC15 | ... CG38: ='Staff - Costs 2'!CG15 | CH38: =SUM(BV38:CG38) -> 0
B39: ='Staff - Costs 2'!B16 -> Production - Packaging | C39: ='Staff - Costs 2'!C16 -> P4 | D39: ='Staff - Costs 2'!D16 -> 0 | E39: ='Staff - Costs 2'!E16 -> 0 | F39: ='Staff - Costs 2'!F16 -> 0 | G39: ='Staff - Costs 2'!G16 -> 0 | H39: ='Staff - Costs 2'!H16 -> 0 | I39: ='Staff - Costs 2'!I16 -> 0 | ... O39: ='Staff - Costs 2'!O16 -> -1223.4845 | P39: =SUM(D39:O39) -> -5709.5942 | R39: ='Staff - Costs 2'!R16 -> -861.33307 | S39: ='Staff - Costs 2'!S16 -> -861.33307 | T39: ='Staff - Costs 2'!T16 -> -861.33307 | U39: ='Staff - Costs 2'!U16 -> -861.33307 | V39: ='Staff - Costs 2'!V16 -> -861.33307 | W39: ='Staff - Costs 2'!W16 -> -861.33307 | X39: ='Staff - Costs 2'!X16 -> -861.33307 | Y39: ='Staff - Costs 2'!Y16 -> -861.33307 | ... AC39: ='Staff - Costs 2'!AC16 -> -1291.9996 | AD39: =SUM(R39:AC39) -> -11197.33 | AF39: ='Staff - Costs 2'!AF16 -> -905.26106 | AG39: ='Staff - Costs 2'!AG16 -> -905.26106 | AH39: ='Staff - Costs 2'!AH16 -> -905.26106 | AI39: ='Staff - Costs 2'!AI16 -> -905.26106 | AJ39: ='Staff - Costs 2'!AJ16 -> -905.26106 | AK39: ='Staff - Costs 2'!AK16 -> -905.26106 | AL39: ='Staff - Costs 2'!AL16 -> -905.26106 | AM39: ='Staff - Costs 2'!AM16 -> -905.26106 | ... AQ39: ='Staff - Costs 2'!AQ16 -> -1357.8916 | AR39: =SUM(AF39:AQ39) -> -11768.394 | AT39: ='Staff - Costs 2'!AT16 -> -951.42937 | AU39: ='Staff - Costs 2'!AU16 -> -951.42937 | AV39: ='Staff - Costs 2'!AV16 -> -951.42937 | AW39: ='Staff - Costs 2'!AW16 -> -951.42937 | AX39: ='Staff - Costs 2'!AX16 -> -951.42937 | AY39: ='Staff - Costs 2'!AY16 -> -951.42937 | AZ39: ='Staff - Costs 2'!AZ16 -> -951.42937 | BA39: ='Staff - Costs 2'!BA16 -> -951.42937 | ... BE39: ='Staff - Costs 2'!BE16 -> -1427.1441 | BF39: =SUM(AT39:BE39) -> -12368.582 | BH39: ='Staff - Costs 2'!BH16 -> -999.95227 | BI39: ='Staff - Costs 2'!BI16 -> -999.95227 | BJ39: ='Staff - Costs 2'!BJ16 -> -999.95227 | BK39: ='Staff - Costs 2'!BK16 -> -999.95227 | BL39: ='Staff - Costs 2'!BL16 -> -999.95227 | BM39: ='Staff - Costs 2'!BM16 -> -999.95227 | BN39: ='Staff - Costs 2'!BN16 -> -999.95227 | BO39: ='Staff - Costs 2'!BO16 -> -999.95227 | ... BS39: ='Staff - Costs 2'!BS16 -> -1499.9284 | BT39: =SUM(BH39:BS39) -> -12999.38 | BV39: ='Staff - Costs 2'!BV16 -> -1050.9498 | BW39: ='Staff - Costs 2'!BW16 -> -1050.9498 | BX39: ='Staff - Costs 2'!BX16 -> -1050.9498 | BY39: ='Staff - Costs 2'!BY16 -> -1050.9498 | BZ39: ='Staff - Costs 2'!BZ16 -> -1050.9498 | CA39: ='Staff - Costs 2'!CA16 -> -1050.9498 | CB39: ='Staff - Costs 2'!CB16 -> -1050.9498 | CC39: ='Staff - Costs 2'!CC16 -> -1050.9498 | ... CG39: ='Staff - Costs 2'!CG16 -> -1576.4248 | CH39: =SUM(BV39:CG39) -> -13662.348
B40: ='Staff - Costs 2'!B17 -> Production - Packaging | C40: ='Staff - Costs 2'!C17 -> P4 | D40: ='Staff - Costs 2'!D17 -> 0 | E40: ='Staff - Costs 2'!E17 -> 0 | F40: ='Staff - Costs 2'!F17 -> 0 | G40: ='Staff - Costs 2'!G17 -> 0 | H40: ='Staff - Costs 2'!H17 -> 0 | I40: ='Staff - Costs 2'!I17 -> 0 | ... O40: ='Staff - Costs 2'!O17 -> -1223.4845 | P40: =SUM(D40:O40) -> -5709.5942 | R40: ='Staff - Costs 2'!R17 -> -861.33307 | S40: ='Staff - Costs 2'!S17 -> -861.33307 | T40: ='Staff - Costs 2'!T17 -> -861.33307 | U40: ='Staff - Costs 2'!U17 -> -861.33307 | V40: ='Staff - Costs 2'!V17 -> -861.33307 | W40: ='Staff - Costs 2'!W17 -> -861.33307 | X40: ='Staff - Costs 2'!X17 -> -861.33307 | Y40: ='Staff - Costs 2'!Y17 -> -861.33307 | ... AC40: ='Staff - Costs 2'!AC17 -> -1291.9996 | AD40: =SUM(R40:AC40) -> -11197.33 | AF40: ='Staff - Costs 2'!AF17 -> -905.26106 | AG40: ='Staff - Costs 2'!AG17 -> -905.26106 | AH40: ='Staff - Costs 2'!AH17 -> -905.26106 | AI40: ='Staff - Costs 2'!AI17 -> -905.26106 | AJ40: ='Staff - Costs 2'!AJ17 -> -905.26106 | AK40: ='Staff - Costs 2'!AK17 -> -905.26106 | AL40: ='Staff - Costs 2'!AL17 -> -905.26106 | AM40: ='Staff - Costs 2'!AM17 -> -905.26106 | ... AQ40: ='Staff - Costs 2'!AQ17 -> -1357.8916 | AR40: =SUM(AF40:AQ40) -> -11768.394 | AT40: ='Staff - Costs 2'!AT17 -> -951.42937 | AU40: ='Staff - Costs 2'!AU17 -> -951.42937 | AV40: ='Staff - Costs 2'!AV17 -> -951.42937 | AW40: ='Staff - Costs 2'!AW17 -> -951.42937 | AX40: ='Staff - Costs 2'!AX17 -> -951.42937 | AY40: ='Staff - Costs 2'!AY17 -> -951.42937 | AZ40: ='Staff - Costs 2'!AZ17 -> -951.42937 | BA40: ='Staff - Costs 2'!BA17 -> -951.42937 | ... BE40: ='Staff - Costs 2'!BE17 -> -1427.1441 | BF40: =SUM(AT40:BE40) -> -12368.582 | BH40: ='Staff - Costs 2'!BH17 -> -999.95227 | BI40: ='Staff - Costs 2'!BI17 -> -999.95227 | BJ40: ='Staff - Costs 2'!BJ17 -> -999.95227 | BK40: ='Staff - Costs 2'!BK17 -> -999.95227 | BL40: ='Staff - Costs 2'!BL17 -> -999.95227 | BM40: ='Staff - Costs 2'!BM17 -> -999.95227 | BN40: ='Staff - Costs 2'!BN17 -> -999.95227 | BO40: ='Staff - Costs 2'!BO17 -> -999.95227 | ... BS40: ='Staff - Costs 2'!BS17 -> -1499.9284 | BT40: =SUM(BH40:BS40) -> -12999.38 | BV40: ='Staff - Costs 2'!BV17 -> -1050.9498 | BW40: ='Staff - Costs 2'!BW17 -> -1050.9498 | BX40: ='Staff - Costs 2'!BX17 -> -1050.9498 | BY40: ='Staff - Costs 2'!BY17 -> -1050.9498 | BZ40: ='Staff - Costs 2'!BZ17 -> -1050.9498 | CA40: ='Staff - Costs 2'!CA17 -> -1050.9498 | CB40: ='Staff - Costs 2'!CB17 -> -1050.9498 | CC40: ='Staff - Costs 2'!CC17 -> -1050.9498 | ... CG40: ='Staff - Costs 2'!CG17 -> -1576.4248 | CH40: =SUM(BV40:CG40) -> -13662.348
B41: ='Staff - Costs 2'!B18 -> Assistant | C41: ='Staff - Costs 2'!C18 -> P5 | D41: ='Staff - Costs 2'!D18 -> 0 | E41: ='Staff - Costs 2'!E18 -> 0 | F41: ='Staff - Costs 2'!F18 -> 0 | G41: ='Staff - Costs 2'!G18 -> 0 | H41: ='Staff - Costs 2'!H18 -> 0 | I41: ='Staff - Costs 2'!I18 -> 0 | ... O41: ='Staff - Costs 2'!O18 -> -1339.5046 | P41: =SUM(D41:O41) -> -6251.0213 | R41: ='Staff - Costs 2'!R18 -> -943.01121 | S41: ='Staff - Costs 2'!S18 -> -943.01121 | T41: ='Staff - Costs 2'!T18 -> -943.01121 | U41: ='Staff - Costs 2'!U18 -> -943.01121 | V41: ='Staff - Costs 2'!V18 -> -943.01121 | W41: ='Staff - Costs 2'!W18 -> -943.01121 | X41: ='Staff - Costs 2'!X18 -> -943.01121 | Y41: ='Staff - Costs 2'!Y18 -> -943.01121 | ... AC41: ='Staff - Costs 2'!AC18 -> -1414.5168 | AD41: =SUM(R41:AC41) -> -12259.146 | AF41: ='Staff - Costs 2'!AF18 -> -991.10478 | AG41: ='Staff - Costs 2'!AG18 -> -991.10478 | AH41: ='Staff - Costs 2'!AH18 -> -991.10478 | AI41: ='Staff - Costs 2'!AI18 -> -991.10478 | AJ41: ='Staff - Costs 2'!AJ18 -> -991.10478 | AK41: ='Staff - Costs 2'!AK18 -> -991.10478 | AL41: ='Staff - Costs 2'!AL18 -> -991.10478 | AM41: ='Staff - Costs 2'!AM18 -> -991.10478 | ... AQ41: ='Staff - Costs 2'!AQ18 -> -1486.6572 | AR41: =SUM(AF41:AQ41) -> -12884.362 | AT41: ='Staff - Costs 2'!AT18 -> -1041.6511 | AU41: ='Staff - Costs 2'!AU18 -> -1041.6511 | AV41: ='Staff - Costs 2'!AV18 -> -1041.6511 | AW41: ='Staff - Costs 2'!AW18 -> -1041.6511 | AX41: ='Staff - Costs 2'!AX18 -> -1041.6511 | AY41: ='Staff - Costs 2'!AY18 -> -1041.6511 | AZ41: ='Staff - Costs 2'!AZ18 -> -1041.6511 | BA41: ='Staff - Costs 2'!BA18 -> -1041.6511 | ... BE41: ='Staff - Costs 2'!BE18 -> -1562.4767 | BF41: =SUM(AT41:BE41) -> -13541.465 | BH41: ='Staff - Costs 2'!BH18 -> -1094.7753 | BI41: ='Staff - Costs 2'!BI18 -> -1094.7753 | BJ41: ='Staff - Costs 2'!BJ18 -> -1094.7753 | BK41: ='Staff - Costs 2'!BK18 -> -1094.7753 | BL41: ='Staff - Costs 2'!BL18 -> -1094.7753 | BM41: ='Staff - Costs 2'!BM18 -> -1094.7753 | BN41: ='Staff - Costs 2'!BN18 -> -1094.7753 | BO41: ='Staff - Costs 2'!BO18 -> -1094.7753 | ... BS41: ='Staff - Costs 2'!BS18 -> -1642.163 | BT41: =SUM(BH41:BS41) -> -14232.079 | BV41: ='Staff - Costs 2'!BV18 -> -1150.6089 | BW41: ='Staff - Costs 2'!BW18 -> -1150.6089 | BX41: ='Staff - Costs 2'!BX18 -> -1150.6089 | BY41: ='Staff - Costs 2'!BY18 -> -1150.6089 | BZ41: ='Staff - Costs 2'!BZ18 -> -1150.6089 | CA41: ='Staff - Costs 2'!CA18 -> -1150.6089 | CB41: ='Staff - Costs 2'!CB18 -> -1150.6089 | CC41: ='Staff - Costs 2'!CC18 -> -1150.6089 | ... CG41: ='Staff - Costs 2'!CG18 -> -1725.9133 | CH41: =SUM(BV41:CG41) -> -14957.915
B42: PERSONNEL | D42: =SUM(D35:D41) -> 0 | E42: =SUM(E35:E41) -> 0 | F42: =SUM(F35:F41) -> 0 | G42: =SUM(G35:G41) -> 0 | H42: =SUM(H35:H41) -> 0 | I42: =SUM(I35:I41) -> 0 | J42: =SUM(J35:J41) -> -10610.564 | K42: =SUM(K35:K41) -> -10610.564 | ... O42: =SUM(O35:O41) -> -15915.846 | P42: =SUM(D42:O42) -> -74273.946 | R42: =SUM(R35:R41) -> -11204.755 | S42: =SUM(S35:S41) -> -11204.755 | T42: =SUM(T35:T41) -> -11204.755 | U42: =SUM(U35:U41) -> -11204.755 | V42: =SUM(V35:V41) -> -11204.755 | W42: =SUM(W35:W41) -> -11204.755 | X42: =SUM(X35:X41) -> -11204.755 | Y42: =SUM(Y35:Y41) -> -11204.755 | ... AC42: =SUM(AC35:AC41) -> -16807.133 | AD42: =SUM(R42:AC42) -> -145661.82 | AF42: =SUM(AF35:AF41) -> -11776.198 | AG42: =SUM(AG35:AG41) -> -11776.198 | AH42: =SUM(AH35:AH41) -> -11776.198 | AI42: =SUM(AI35:AI41) -> -11776.198 | AJ42: =SUM(AJ35:AJ41) -> -11776.198 | AK42: =SUM(AK35:AK41) -> -11776.198 | AL42: =SUM(AL35:AL41) -> -11776.198 | AM42: =SUM(AM35:AM41) -> -11776.198 | ... AQ42: =SUM(AQ35:AQ41) -> -17664.297 | AR42: =SUM(AF42:AQ42) -> -153090.57 | AT42: =SUM(AT35:AT41) -> -12376.784 | AU42: =SUM(AU35:AU41) -> -12376.784 | AV42: =SUM(AV35:AV41) -> -12376.784 | AW42: =SUM(AW35:AW41) -> -12376.784 | AX42: =SUM(AX35:AX41) -> -12376.784 | AY42: =SUM(AY35:AY41) -> -12376.784 | AZ42: =SUM(AZ35:AZ41) -> -12376.784 | BA42: =SUM(BA35:BA41) -> -12376.784 | ... BE42: =SUM(BE35:BE41) -> -18565.176 | BF42: =SUM(AT42:BE42) -> -160898.19 | BH42: =SUM(BH35:BH41) -> -13008 | BI42: =SUM(BI35:BI41) -> -13008 | BJ42: =SUM(BJ35:BJ41) -> -13008 | BK42: =SUM(BK35:BK41) -> -13008 | BL42: =SUM(BL35:BL41) -> -13008 | BM42: =SUM(BM35:BM41) -> -13008 | BN42: =SUM(BN35:BN41) -> -13008 | BO42: =SUM(BO35:BO41) -> -13008 | ... BS42: =SUM(BS35:BS41) -> -19512 | BT42: =SUM(BH42:BS42) -> -169104 | BV42: =SUM(BV35:BV41) -> -13671.408 | BW42: =SUM(BW35:BW41) -> -13671.408 | BX42: =SUM(BX35:BX41) -> -13671.408 | BY42: =SUM(BY35:BY41) -> -13671.408 | BZ42: =SUM(BZ35:BZ41) -> -13671.408 | CA42: =SUM(CA35:CA41) -> -13671.408 | CB42: =SUM(CB35:CB41) -> -13671.408 | CC42: =SUM(CC35:CC41) -> -13671.408 | ... CG42: =SUM(CG35:CG41) -> -20507.112 | CH42: =SUM(BV42:CG42) -> -177728.3
B44: ='Adv & Travel'!B12 -> Travel Expenses | C44: ='Adv & Travel'!C12 -> AT1 | D44: ='Adv & Travel'!D12 -> 0 | E44: ='Adv & Travel'!E12 -> 0 | F44: ='Adv & Travel'!F12 -> 0 | G44: ='Adv & Travel'!G12 -> 0 | H44: ='Adv & Travel'!H12 -> 0 | I44: ='Adv & Travel'!I12 -> 0 | ... O44: ='Adv & Travel'!O12 -> -7500 | P44: =SUM(D44:O44) -> -15000 | R44: ='Adv & Travel'!R12 -> 0 | S44: ='Adv & Travel'!S12 -> 0 | T44: ='Adv & Travel'!T12 -> -7500 | U44: ='Adv & Travel'!U12 -> 0 | V44: ='Adv & Travel'!V12 -> 0 | W44: ='Adv & Travel'!W12 -> -5000 | X44: ='Adv & Travel'!X12 -> 0 | Y44: ='Adv & Travel'!Y12 -> 0 | ... AC44: ='Adv & Travel'!AC12 -> -7920 | AD44: =SUM(R44:AC44) -> -28340 | AF44: ='Adv & Travel'!AF12 -> 0 | AG44: ='Adv & Travel'!AG12 -> 0 | AH44: ='Adv & Travel'!AH12 -> -7882.5 | AI44: ='Adv & Travel'!AI12 -> 0 | AJ44: ='Adv & Travel'!AJ12 -> 0 | AK44: ='Adv & Travel'!AK12 -> -5255 | AL44: ='Adv & Travel'!AL12 -> 0 | AM44: ='Adv & Travel'!AM12 -> 0 | ... AQ44: ='Adv & Travel'!AQ12 -> -8323.92 | AR44: =SUM(AF44:AQ44) -> -29785.34 | AT44: ='Adv & Travel'!AT12 -> 0 | AU44: ='Adv & Travel'!AU12 -> 0 | AV44: ='Adv & Travel'!AV12 -> -8284.5075 | AW44: ='Adv & Travel'!AW12 -> 0 | AX44: ='Adv & Travel'!AX12 -> 0 | AY44: ='Adv & Travel'!AY12 -> -5523.005 | AZ44: ='Adv & Travel'!AZ12 -> 0 | BA44: ='Adv & Travel'!BA12 -> 0 | ... BE44: ='Adv & Travel'!BE12 -> -8748.4399 | BF44: =SUM(AT44:BE44) -> -31304.392 | BH44: ='Adv & Travel'!BH12 -> 0 | BI44: ='Adv & Travel'!BI12 -> 0 | BJ44: ='Adv & Travel'!BJ12 -> -8707.0174 | BK44: ='Adv & Travel'!BK12 -> 0 | BL44: ='Adv & Travel'!BL12 -> 0 | BM44: ='Adv & Travel'!BM12 -> -5804.6783 | BN44: ='Adv & Travel'!BN12 -> 0 | BO44: ='Adv & Travel'!BO12 -> 0 | ... BS44: ='Adv & Travel'!BS12 -> -9194.6104 | BT44: =SUM(BH44:BS44) -> -32900.916 | BV44: ='Adv & Travel'!BV12 -> 0 | BW44: ='Adv & Travel'!BW12 -> 0 | BX44: ='Adv & Travel'!BX12 -> -9151.0753 | BY44: ='Adv & Travel'!BY12 -> 0 | BZ44: ='Adv & Travel'!BZ12 -> 0 | CA44: ='Adv & Travel'!CA12 -> -6100.7168 | CB44: ='Adv & Travel'!CB12 -> 0 | CC44: ='Adv & Travel'!CC12 -> 0 | ... CG44: ='Adv & Travel'!CG12 -> -9663.5355 | CH44: =SUM(BV44:CG44) -> -34578.863
B45: ='Adv & Travel'!B13 -> Advertising - Consultant | C45: ='Adv & Travel'!C13 -> AT2 | D45: ='Adv & Travel'!D13 -> 0 | E45: ='Adv & Travel'!E13 -> 0 | F45: ='Adv & Travel'!F13 -> -2250 | G45: ='Adv & Travel'!G13 -> 0 | H45: ='Adv & Travel'!H13 -> 0 | I45: ='Adv & Travel'!I13 -> -2250 | ... O45: ='Adv & Travel'!O13 -> -2250 | P45: =SUM(D45:O45) -> -9000 | R45: ='Adv & Travel'!R13 -> 0 | S45: ='Adv & Travel'!S13 -> 0 | T45: ='Adv & Travel'!T13 -> -2376 | U45: ='Adv & Travel'!U13 -> 0 | V45: ='Adv & Travel'!V13 -> 0 | W45: ='Adv & Travel'!W13 -> -2376 | X45: ='Adv & Travel'!X13 -> 0 | Y45: ='Adv & Travel'!Y13 -> 0 | ... AC45: ='Adv & Travel'!AC13 -> -2376 | AD45: =SUM(R45:AC45) -> -9504 | AF45: ='Adv & Travel'!AF13 -> 0 | AG45: ='Adv & Travel'!AG13 -> 0 | AH45: ='Adv & Travel'!AH13 -> -2497.176 | AI45: ='Adv & Travel'!AI13 -> 0 | AJ45: ='Adv & Travel'!AJ13 -> 0 | AK45: ='Adv & Travel'!AK13 -> -2497.176 | AL45: ='Adv & Travel'!AL13 -> 0 | AM45: ='Adv & Travel'!AM13 -> 0 | ... AQ45: ='Adv & Travel'!AQ13 -> -2497.176 | AR45: =SUM(AF45:AQ45) -> -9988.704 | AT45: ='Adv & Travel'!AT13 -> 0 | AU45: ='Adv & Travel'!AU13 -> 0 | AV45: ='Adv & Travel'!AV13 -> -2624.532 | AW45: ='Adv & Travel'!AW13 -> 0 | AX45: ='Adv & Travel'!AX13 -> 0 | AY45: ='Adv & Travel'!AY13 -> -2624.532 | AZ45: ='Adv & Travel'!AZ13 -> 0 | BA45: ='Adv & Travel'!BA13 -> 0 | ... BE45: ='Adv & Travel'!BE13 -> -2624.532 | BF45: =SUM(AT45:BE45) -> -10498.128 | BH45: ='Adv & Travel'!BH13 -> 0 | BI45: ='Adv & Travel'!BI13 -> 0 | BJ45: ='Adv & Travel'!BJ13 -> -2758.3831 | BK45: ='Adv & Travel'!BK13 -> 0 | BL45: ='Adv & Travel'!BL13 -> 0 | BM45: ='Adv & Travel'!BM13 -> -2758.3831 | BN45: ='Adv & Travel'!BN13 -> 0 | BO45: ='Adv & Travel'!BO13 -> 0 | ... BS45: ='Adv & Travel'!BS13 -> -2758.3831 | BT45: =SUM(BH45:BS45) -> -11033.532 | BV45: ='Adv & Travel'!BV13 -> 0 | BW45: ='Adv & Travel'!BW13 -> 0 | BX45: ='Adv & Travel'!BX13 -> -2899.0606 | BY45: ='Adv & Travel'!BY13 -> 0 | BZ45: ='Adv & Travel'!BZ13 -> 0 | CA45: ='Adv & Travel'!CA13 -> -2899.0606 | CB45: ='Adv & Travel'!CB13 -> 0 | CC45: ='Adv & Travel'!CC13 -> 0 | ... CG45: ='Adv & Travel'!CG13 -> -2899.0606 | CH45: =SUM(BV45:CG45) -> -11596.243
B46: ='Adv & Travel'!B14 -> Social Media | C46: ='Adv & Travel'!C14 -> AT3 | D46: ='Adv & Travel'!D14 -> 0 | E46: ='Adv & Travel'!E14 -> 0 | F46: ='Adv & Travel'!F14 -> 0 | G46: ='Adv & Travel'!G14 -> 0 | H46: ='Adv & Travel'!H14 -> 0 | I46: ='Adv & Travel'!I14 -> 0 | ... O46: ='Adv & Travel'!O14 -> 0 | P46: =SUM(D46:O46) -> 0 | R46: ='Adv & Travel'!R14 -> 0 | S46: ='Adv & Travel'!S14 -> 0 | T46: ='Adv & Travel'!T14 -> 0 | U46: ='Adv & Travel'!U14 -> 0 | V46: ='Adv & Travel'!V14 -> 0 | W46: ='Adv & Travel'!W14 -> 0 | X46: ='Adv & Travel'!X14 -> 0 | Y46: ='Adv & Travel'!Y14 -> 0 | ... AC46: ='Adv & Travel'!AC14 -> 0 | AD46: =SUM(R46:AC46) -> 0 | AF46: ='Adv & Travel'!AF14 -> 0 | AG46: ='Adv & Travel'!AG14 -> 0 | AH46: ='Adv & Travel'!AH14 -> 0 | AI46: ='Adv & Travel'!AI14 -> 0 | AJ46: ='Adv & Travel'!AJ14 -> 0 | AK46: ='Adv & Travel'!AK14 -> 0 | AL46: ='Adv & Travel'!AL14 -> 0 | AM46: ='Adv & Travel'!AM14 -> 0 | ... AQ46: ='Adv & Travel'!AQ14 -> 0 | AR46: =SUM(AF46:AQ46) -> 0 | AT46: ='Adv & Travel'!AT14 -> 0 | AU46: ='Adv & Travel'!AU14 -> 0 | AV46: ='Adv & Travel'!AV14 -> 0 | AW46: ='Adv & Travel'!AW14 -> 0 | AX46: ='Adv & Travel'!AX14 -> 0 | AY46: ='Adv & Travel'!AY14 -> 0 | AZ46: ='Adv & Travel'!AZ14 -> 0 | BA46: ='Adv & Travel'!BA14 -> 0 | ... BE46: ='Adv & Travel'!BE14 -> 0 | BF46: =SUM(AT46:BE46) -> 0 | BH46: ='Adv & Travel'!BH14 -> 0 | BI46: ='Adv & Travel'!BI14 -> 0 | BJ46: ='Adv & Travel'!BJ14 -> 0 | BK46: ='Adv & Travel'!BK14 -> 0 | BL46: ='Adv & Travel'!BL14 -> 0 | BM46: ='Adv & Travel'!BM14 -> 0 | BN46: ='Adv & Travel'!BN14 -> 0 | BO46: ='Adv & Travel'!BO14 -> 0 | ... BS46: ='Adv & Travel'!BS14 -> 0 | BT46: =SUM(BH46:BS46) -> 0 | BV46: ='Adv & Travel'!BV14 -> 0 | BW46: ='Adv & Travel'!BW14 -> 0 | BX46: ='Adv & Travel'!BX14 -> 0 | BY46: ='Adv & Travel'!BY14 -> 0 | BZ46: ='Adv & Travel'!BZ14 -> 0 | CA46: ='Adv & Travel'!CA14 -> 0 | CB46: ='Adv & Travel'!CB14 -> 0 | CC46: ='Adv & Travel'!CC14 -> 0 | ... CG46: ='Adv & Travel'!CG14 -> 0 | CH46: =SUM(BV46:CG46) -> 0
B47: ='Adv & Travel'!B15 -> Advertising - Products | C47: ='Adv & Travel'!C15 -> AT4 | D47: ='Adv & Travel'!D15 -> 0 | E47: ='Adv & Travel'!E15 -> 0 | F47: ='Adv & Travel'!F15 -> -15000 | G47: ='Adv & Travel'!G15 -> 0 | H47: ='Adv & Travel'!H15 -> 0 | I47: ='Adv & Travel'!I15 -> -15000 | ... O47: ='Adv & Travel'!O15 -> -15000 | P47: =SUM(D47:O47) -> -60000 | R47: ='Adv & Travel'!R15 -> 0 | S47: ='Adv & Travel'!S15 -> 0 | T47: ='Adv & Travel'!T15 -> -15840 | U47: ='Adv & Travel'!U15 -> 0 | V47: ='Adv & Travel'!V15 -> 0 | W47: ='Adv & Travel'!W15 -> -15840 | X47: ='Adv & Travel'!X15 -> 0 | Y47: ='Adv & Travel'!Y15 -> 0 | ... AC47: ='Adv & Travel'!AC15 -> -15840 | AD47: =SUM(R47:AC47) -> -63360 | AF47: ='Adv & Travel'!AF15 -> 0 | AG47: ='Adv & Travel'!AG15 -> 0 | AH47: ='Adv & Travel'!AH15 -> -16647.84 | AI47: ='Adv & Travel'!AI15 -> 0 | AJ47: ='Adv & Travel'!AJ15 -> 0 | AK47: ='Adv & Travel'!AK15 -> -16647.84 | AL47: ='Adv & Travel'!AL15 -> 0 | AM47: ='Adv & Travel'!AM15 -> 0 | ... AQ47: ='Adv & Travel'!AQ15 -> -16647.84 | AR47: =SUM(AF47:AQ47) -> -66591.36 | AT47: ='Adv & Travel'!AT15 -> 0 | AU47: ='Adv & Travel'!AU15 -> 0 | AV47: ='Adv & Travel'!AV15 -> -17496.88 | AW47: ='Adv & Travel'!AW15 -> 0 | AX47: ='Adv & Travel'!AX15 -> 0 | AY47: ='Adv & Travel'!AY15 -> -17496.88 | AZ47: ='Adv & Travel'!AZ15 -> 0 | BA47: ='Adv & Travel'!BA15 -> 0 | ... BE47: ='Adv & Travel'!BE15 -> -17496.88 | BF47: =SUM(AT47:BE47) -> -69987.519 | BH47: ='Adv & Travel'!BH15 -> 0 | BI47: ='Adv & Travel'!BI15 -> 0 | BJ47: ='Adv & Travel'!BJ15 -> -18389.221 | BK47: ='Adv & Travel'!BK15 -> 0 | BL47: ='Adv & Travel'!BL15 -> 0 | BM47: ='Adv & Travel'!BM15 -> -18389.221 | BN47: ='Adv & Travel'!BN15 -> 0 | BO47: ='Adv & Travel'!BO15 -> 0 | ... BS47: ='Adv & Travel'!BS15 -> -18389.221 | BT47: =SUM(BH47:BS47) -> -73556.883 | BV47: ='Adv & Travel'!BV15 -> 0 | BW47: ='Adv & Travel'!BW15 -> 0 | BX47: ='Adv & Travel'!BX15 -> -19327.071 | BY47: ='Adv & Travel'!BY15 -> 0 | BZ47: ='Adv & Travel'!BZ15 -> 0 | CA47: ='Adv & Travel'!CA15 -> -19327.071 | CB47: ='Adv & Travel'!CB15 -> 0 | CC47: ='Adv & Travel'!CC15 -> 0 | ... CG47: ='Adv & Travel'!CG15 -> -19327.071 | CH47: =SUM(BV47:CG47) -> -77308.284
B48: ='Adv & Travel'!B16 -> x | C48: ='Adv & Travel'!C16 -> x | D48: ='Adv & Travel'!D16 -> 0 | E48: ='Adv & Travel'!E16 -> 0 | F48: ='Adv & Travel'!F16 -> 0 | G48: ='Adv & Travel'!G16 -> 0 | H48: ='Adv & Travel'!H16 -> 0 | I48: ='Adv & Travel'!I16 -> 0 | ... O48: ='Adv & Travel'!O16 -> 0 | P48: =SUM(D48:O48) -> 0 | R48: ='Adv & Travel'!R16 -> 0 | S48: ='Adv & Travel'!S16 -> 0 | T48: ='Adv & Travel'!T16 -> 0 | U48: ='Adv & Travel'!U16 -> 0 | V48: ='Adv & Travel'!V16 -> 0 | W48: ='Adv & Travel'!W16 -> 0 | X48: ='Adv & Travel'!X16 -> 0 | Y48: ='Adv & Travel'!Y16 -> 0 | ... AC48: ='Adv & Travel'!AC16 -> 0 | AD48: =SUM(R48:AC48) -> 0 | AF48: ='Adv & Travel'!AF16 -> 0 | AG48: ='Adv & Travel'!AG16 -> 0 | AH48: ='Adv & Travel'!AH16 -> 0 | AI48: ='Adv & Travel'!AI16 -> 0 | AJ48: ='Adv & Travel'!AJ16 -> 0 | AK48: ='Adv & Travel'!AK16 -> 0 | AL48: ='Adv & Travel'!AL16 -> 0 | AM48: ='Adv & Travel'!AM16 -> 0 | ... AQ48: ='Adv & Travel'!AQ16 -> 0 | AR48: =SUM(AF48:AQ48) -> 0 | AT48: ='Adv & Travel'!AT16 -> 0 | AU48: ='Adv & Travel'!AU16 -> 0 | AV48: ='Adv & Travel'!AV16 -> 0 | AW48: ='Adv & Travel'!AW16 -> 0 | AX48: ='Adv & Travel'!AX16 -> 0 | AY48: ='Adv & Travel'!AY16 -> 0 | AZ48: ='Adv & Travel'!AZ16 -> 0 | BA48: ='Adv & Travel'!BA16 -> 0 | ... BE48: ='Adv & Travel'!BE16 -> 0 | BF48: =SUM(AT48:BE48) -> 0 | BH48: ='Adv & Travel'!BH16 -> 0 | BI48: ='Adv & Travel'!BI16 -> 0 | BJ48: ='Adv & Travel'!BJ16 -> 0 | BK48: ='Adv & Travel'!BK16 -> 0 | BL48: ='Adv & Travel'!BL16 -> 0 | BM48: ='Adv & Travel'!BM16 -> 0 | BN48: ='Adv & Travel'!BN16 -> 0 | BO48: ='Adv & Travel'!BO16 -> 0 | ... BS48: ='Adv & Travel'!BS16 -> 0 | BT48: =SUM(BH48:BS48) -> 0 | BV48: ='Adv & Travel'!BV16 -> 0 | BW48: ='Adv & Travel'!BW16 -> 0 | BX48: ='Adv & Travel'!BX16 -> 0 | BY48: ='Adv & Travel'!BY16 -> 0 | BZ48: ='Adv & Travel'!BZ16 -> 0 | CA48: ='Adv & Travel'!CA16 -> 0 | CB48: ='Adv & Travel'!CB16 -> 0 | CC48: ='Adv & Travel'!CC16 -> 0 | ... CG48: ='Adv & Travel'!CG16 -> 0 | CH48: =SUM(BV48:CG48) -> 0
B49: ADVERTISING & TRAVEL | D49: =SUM(D44:D48) -> 0 | E49: =SUM(E44:E48) -> 0 | F49: =SUM(F44:F48) -> -17250 | G49: =SUM(G44:G48) -> 0 | H49: =SUM(H44:H48) -> 0 | I49: =SUM(I44:I48) -> -17250 | J49: =SUM(J44:J48) -> 0 | K49: =SUM(K44:K48) -> 0 | ... O49: =SUM(O44:O48) -> -24750 | P49: =SUM(D49:O49) -> -84000 | R49: =SUM(R44:R48) -> 0 | S49: =SUM(S44:S48) -> 0 | T49: =SUM(T44:T48) -> -25716 | U49: =SUM(U44:U48) -> 0 | V49: =SUM(V44:V48) -> 0 | W49: =SUM(W44:W48) -> -23216 | X49: =SUM(X44:X48) -> 0 | Y49: =SUM(Y44:Y48) -> 0 | ... AC49: =SUM(AC44:AC48) -> -26136 | AD49: =SUM(R49:AC49) -> -101204 | AF49: =SUM(AF44:AF48) -> 0 | AG49: =SUM(AG44:AG48) -> 0 | AH49: =SUM(AH44:AH48) -> -27027.516 | AI49: =SUM(AI44:AI48) -> 0 | AJ49: =SUM(AJ44:AJ48) -> 0 | AK49: =SUM(AK44:AK48) -> -24400.016 | AL49: =SUM(AL44:AL48) -> 0 | AM49: =SUM(AM44:AM48) -> 0 | ... AQ49: =SUM(AQ44:AQ48) -> -27468.936 | AR49: =SUM(AF49:AQ49) -> -106365.4 | AT49: =SUM(AT44:AT48) -> 0 | AU49: =SUM(AU44:AU48) -> 0 | AV49: =SUM(AV44:AV48) -> -28405.919 | AW49: =SUM(AW44:AW48) -> 0 | AX49: =SUM(AX44:AX48) -> 0 | AY49: =SUM(AY44:AY48) -> -25644.417 | AZ49: =SUM(AZ44:AZ48) -> 0 | BA49: =SUM(BA44:BA48) -> 0 | ... BE49: =SUM(BE44:BE48) -> -28869.852 | BF49: =SUM(AT49:BE49) -> -111790.04 | BH49: =SUM(BH44:BH48) -> 0 | BI49: =SUM(BI44:BI48) -> 0 | BJ49: =SUM(BJ44:BJ48) -> -29854.621 | BK49: =SUM(BK44:BK48) -> 0 | BL49: =SUM(BL44:BL48) -> 0 | BM49: =SUM(BM44:BM48) -> -26952.282 | BN49: =SUM(BN44:BN48) -> 0 | BO49: =SUM(BO44:BO48) -> 0 | ... BS49: =SUM(BS44:BS48) -> -30342.214 | BT49: =SUM(BH49:BS49) -> -117491.33 | BV49: =SUM(BV44:BV48) -> 0 | BW49: =SUM(BW44:BW48) -> 0 | BX49: =SUM(BX44:BX48) -> -31377.207 | BY49: =SUM(BY44:BY48) -> 0 | BZ49: =SUM(BZ44:BZ48) -> 0 | CA49: =SUM(CA44:CA48) -> -28326.848 | CB49: =SUM(CB44:CB48) -> 0 | CC49: =SUM(CC44:CC48) -> 0 | ... CG49: =SUM(CG44:CG48) -> -31889.667 | CH49: =SUM(BV49:CG49) -> -123483.39
B51: =Admin!B12 -> Office supplies | C51: =Admin!C12 -> A1 | D51: =Admin!D12 -> 0 | E51: =Admin!E12 -> 0 | F51: =Admin!F12 -> 0 | G51: =Admin!G12 -> 0 | H51: =Admin!H12 -> 0 | I51: =Admin!I12 -> 0 | ... O51: =Admin!O12 -> 0 | P51: =SUM(D51:O51) -> 250 | R51: =Admin!R12 -> 0 | S51: =Admin!S12 -> 0 | T51: =Admin!T12 -> 0 | U51: =Admin!U12 -> 0 | V51: =Admin!V12 -> 0 | W51: =Admin!W12 -> 0 | X51: =Admin!X12 -> 264 | Y51: =Admin!Y12 -> 0 | ... AC51: =Admin!AC12 -> 0 | AD51: =SUM(R51:AC51) -> 264 | AF51: =Admin!AF12 -> 0 | AG51: =Admin!AG12 -> 0 | AH51: =Admin!AH12 -> 0 | AI51: =Admin!AI12 -> 0 | AJ51: =Admin!AJ12 -> 0 | AK51: =Admin!AK12 -> 0 | AL51: =Admin!AL12 -> 277.464 | AM51: =Admin!AM12 -> 0 | ... AQ51: =Admin!AQ12 -> 0 | AR51: =SUM(AF51:AQ51) -> 277.464 | AT51: =Admin!AT12 -> 0 | AU51: =Admin!AU12 -> 0 | AV51: =Admin!AV12 -> 0 | AW51: =Admin!AW12 -> 0 | AX51: =Admin!AX12 -> 0 | AY51: =Admin!AY12 -> 0 | AZ51: =Admin!AZ12 -> 291.61466 | BA51: =Admin!BA12 -> 0 | ... BE51: =Admin!BE12 -> 0 | BF51: =SUM(AT51:BE51) -> 291.61466 | BH51: =Admin!BH12 -> 0 | BI51: =Admin!BI12 -> 0 | BJ51: =Admin!BJ12 -> 0 | BK51: =Admin!BK12 -> 0 | BL51: =Admin!BL12 -> 0 | BM51: =Admin!BM12 -> 0 | BN51: =Admin!BN12 -> 306.48701 | BO51: =Admin!BO12 -> 0 | ... BS51: =Admin!BS12 -> 0 | BT51: =SUM(BH51:BS51) -> 306.48701 | BV51: =Admin!BV12 -> 0 | BW51: =Admin!BW12 -> 0 | BX51: =Admin!BX12 -> 0 | BY51: =Admin!BY12 -> 0 | BZ51: =Admin!BZ12 -> 0 | CA51: =Admin!CA12 -> 0 | CB51: =Admin!CB12 -> 322.11785 | CC51: =Admin!CC12 -> 0 | ... CG51: =Admin!CG12 -> 0 | CH51: =SUM(BV51:CG51) -> 322.11785
B52: =Admin!B13 -> Office & Tech equipment | C52: =Admin!C13 -> A2 | D52: =Admin!D13 -> 0 | E52: =Admin!E13 -> 0 | F52: =Admin!F13 -> 0 | G52: =Admin!G13 -> 0 | H52: =Admin!H13 -> 0 | I52: =Admin!I13 -> 0 | ... O52: =Admin!O13 -> 0 | P52: =SUM(D52:O52) -> 10000 | R52: =Admin!R13 -> 0 | S52: =Admin!S13 -> 5000 | T52: =Admin!T13 -> 0 | U52: =Admin!U13 -> 0 | V52: =Admin!V13 -> 0 | W52: =Admin!W13 -> 0 | X52: =Admin!X13 -> 10560 | Y52: =Admin!Y13 -> 0 | ... AC52: =Admin!AC13 -> 0 | AD52: =SUM(R52:AC52) -> 15560 | AF52: =Admin!AF13 -> 0 | AG52: =Admin!AG13 -> 5255 | AH52: =Admin!AH13 -> 0 | AI52: =Admin!AI13 -> 0 | AJ52: =Admin!AJ13 -> 0 | AK52: =Admin!AK13 -> 0 | AL52: =Admin!AL13 -> 11098.56 | AM52: =Admin!AM13 -> 0 | ... AQ52: =Admin!AQ13 -> 0 | AR52: =SUM(AF52:AQ52) -> 16353.56 | AT52: =Admin!AT13 -> 0 | AU52: =Admin!AU13 -> 5523.005 | AV52: =Admin!AV13 -> 0 | AW52: =Admin!AW13 -> 0 | AX52: =Admin!AX13 -> 0 | AY52: =Admin!AY13 -> 0 | AZ52: =Admin!AZ13 -> 11664.587 | BA52: =Admin!BA13 -> 0 | ... BE52: =Admin!BE13 -> 0 | BF52: =SUM(AT52:BE52) -> 17187.592 | BH52: =Admin!BH13 -> 0 | BI52: =Admin!BI13 -> 5804.6783 | BJ52: =Admin!BJ13 -> 0 | BK52: =Admin!BK13 -> 0 | BL52: =Admin!BL13 -> 0 | BM52: =Admin!BM13 -> 0 | BN52: =Admin!BN13 -> 12259.48 | BO52: =Admin!BO13 -> 0 | ... BS52: =Admin!BS13 -> 0 | BT52: =SUM(BH52:BS52) -> 18064.159 | BV52: =Admin!BV13 -> 0 | BW52: =Admin!BW13 -> 6100.7168 | BX52: =Admin!BX13 -> 0 | BY52: =Admin!BY13 -> 0 | BZ52: =Admin!BZ13 -> 0 | CA52: =Admin!CA13 -> 0 | CB52: =Admin!CB13 -> 12884.714 | CC52: =Admin!CC13 -> 0 | ... CG52: =Admin!CG13 -> 0 | CH52: =SUM(BV52:CG52) -> 18985.431
B53: =Admin!B14 -> Internet & Phone | C53: =Admin!C14 -> A3 | D53: =Admin!D14 -> 0 | E53: =Admin!E14 -> 0 | F53: =Admin!F14 -> 0 | G53: =Admin!G14 -> 0 | H53: =Admin!H14 -> 0 | I53: =Admin!I14 -> 0 | ... O53: =Admin!O14 -> 150 | P53: =SUM(D53:O53) -> 900 | R53: =Admin!R14 -> 158.4 | S53: =Admin!S14 -> 158.4 | T53: =Admin!T14 -> 158.4 | U53: =Admin!U14 -> 158.4 | V53: =Admin!V14 -> 158.4 | W53: =Admin!W14 -> 158.4 | X53: =Admin!X14 -> 158.4 | Y53: =Admin!Y14 -> 158.4 | ... AC53: =Admin!AC14 -> 158.4 | AD53: =SUM(R53:AC53) -> 1900.8 | AF53: =Admin!AF14 -> 166.4784 | AG53: =Admin!AG14 -> 166.4784 | AH53: =Admin!AH14 -> 166.4784 | AI53: =Admin!AI14 -> 166.4784 | AJ53: =Admin!AJ14 -> 166.4784 | AK53: =Admin!AK14 -> 166.4784 | AL53: =Admin!AL14 -> 166.4784 | AM53: =Admin!AM14 -> 166.4784 | ... AQ53: =Admin!AQ14 -> 166.4784 | AR53: =SUM(AF53:AQ53) -> 1997.7408 | AT53: =Admin!AT14 -> 174.9688 | AU53: =Admin!AU14 -> 174.9688 | AV53: =Admin!AV14 -> 174.9688 | AW53: =Admin!AW14 -> 174.9688 | AX53: =Admin!AX14 -> 174.9688 | AY53: =Admin!AY14 -> 174.9688 | AZ53: =Admin!AZ14 -> 174.9688 | BA53: =Admin!BA14 -> 174.9688 | ... BE53: =Admin!BE14 -> 174.9688 | BF53: =SUM(AT53:BE53) -> 2099.6256 | BH53: =Admin!BH14 -> 183.89221 | BI53: =Admin!BI14 -> 183.89221 | BJ53: =Admin!BJ14 -> 183.89221 | BK53: =Admin!BK14 -> 183.89221 | BL53: =Admin!BL14 -> 183.89221 | BM53: =Admin!BM14 -> 183.89221 | BN53: =Admin!BN14 -> 183.89221 | BO53: =Admin!BO14 -> 183.89221 | ... BS53: =Admin!BS14 -> 183.89221 | BT53: =SUM(BH53:BS53) -> 2206.7065 | BV53: =Admin!BV14 -> 193.27071 | BW53: =Admin!BW14 -> 193.27071 | BX53: =Admin!BX14 -> 193.27071 | BY53: =Admin!BY14 -> 193.27071 | BZ53: =Admin!BZ14 -> 193.27071 | CA53: =Admin!CA14 -> 193.27071 | CB53: =Admin!CB14 -> 193.27071 | CC53: =Admin!CC14 -> 193.27071 | ... CG53: =Admin!CG14 -> 193.27071 | CH53: =SUM(BV53:CG53) -> 2319.2485
B54: =Admin!B15 -> bank fees | C54: =Admin!C15 -> A4 | D54: =Admin!D15 -> 0 | E54: =Admin!E15 -> 0 | F54: =Admin!F15 -> 0 | G54: =Admin!G15 -> 0 | H54: =Admin!H15 -> 0 | I54: =Admin!I15 -> 0 | ... O54: =Admin!O15 -> 0 | P54: =SUM(D54:O54) -> 0 | R54: =Admin!R15 -> 0 | S54: =Admin!S15 -> 0 | T54: =Admin!T15 -> 0 | U54: =Admin!U15 -> 0 | V54: =Admin!V15 -> 0 | W54: =Admin!W15 -> 0 | X54: =Admin!X15 -> 0 | Y54: =Admin!Y15 -> 0 | ... AC54: =Admin!AC15 -> 0 | AD54: =SUM(R54:AC54) -> 0 | AF54: =Admin!AF15 -> 0 | AG54: =Admin!AG15 -> 0 | AH54: =Admin!AH15 -> 0 | AI54: =Admin!AI15 -> 0 | AJ54: =Admin!AJ15 -> 0 | AK54: =Admin!AK15 -> 0 | AL54: =Admin!AL15 -> 0 | AM54: =Admin!AM15 -> 0 | ... AQ54: =Admin!AQ15 -> 0 | AR54: =SUM(AF54:AQ54) -> 0 | AT54: =Admin!AT15 -> 0 | AU54: =Admin!AU15 -> 0 | AV54: =Admin!AV15 -> 0 | AW54: =Admin!AW15 -> 0 | AX54: =Admin!AX15 -> 0 | AY54: =Admin!AY15 -> 0 | AZ54: =Admin!AZ15 -> 0 | BA54: =Admin!BA15 -> 0 | ... BE54: =Admin!BE15 -> 0 | BF54: =SUM(AT54:BE54) -> 0 | BH54: =Admin!BH15 -> 0 | BI54: =Admin!BI15 -> 0 | BJ54: =Admin!BJ15 -> 0 | BK54: =Admin!BK15 -> 0 | BL54: =Admin!BL15 -> 0 | BM54: =Admin!BM15 -> 0 | BN54: =Admin!BN15 -> 0 | BO54: =Admin!BO15 -> 0 | ... BS54: =Admin!BS15 -> 0 | BT54: =SUM(BH54:BS54) -> 0 | BV54: =Admin!BV15 -> 0 | BW54: =Admin!BW15 -> 0 | BX54: =Admin!BX15 -> 0 | BY54: =Admin!BY15 -> 0 | BZ54: =Admin!BZ15 -> 0 | CA54: =Admin!CA15 -> 0 | CB54: =Admin!CB15 -> 0 | CC54: =Admin!CC15 -> 0 | ... CG54: =Admin!CG15 -> 0 | CH54: =SUM(BV54:CG54) -> 0
B55: =Admin!B16 -> intrest costs | C55: =Admin!C16 -> A5 | D55: =Admin!D16 -> 0 | E55: =Admin!E16 -> 0 | F55: =Admin!F16 -> 0 | G55: =Admin!G16 -> 0 | H55: =Admin!H16 -> 0 | I55: =Admin!I16 -> 0 | ... O55: =Admin!O16 -> 0 | P55: =SUM(D55:O55) -> 0 | R55: =Admin!R16 -> 0 | S55: =Admin!S16 -> 0 | T55: =Admin!T16 -> 0 | U55: =Admin!U16 -> 0 | V55: =Admin!V16 -> 0 | W55: =Admin!W16 -> 0 | X55: =Admin!X16 -> 0 | Y55: =Admin!Y16 -> 0 | ... AC55: =Admin!AC16 -> 0 | AD55: =SUM(R55:AC55) -> 0 | AF55: =Admin!AF16 -> 0 | AG55: =Admin!AG16 -> 0 | AH55: =Admin!AH16 -> 0 | AI55: =Admin!AI16 -> 0 | AJ55: =Admin!AJ16 -> 0 | AK55: =Admin!AK16 -> 0 | AL55: =Admin!AL16 -> 0 | AM55: =Admin!AM16 -> 0 | ... AQ55: =Admin!AQ16 -> 0 | AR55: =SUM(AF55:AQ55) -> 0 | AT55: =Admin!AT16 -> 0 | AU55: =Admin!AU16 -> 0 | AV55: =Admin!AV16 -> 0 | AW55: =Admin!AW16 -> 0 | AX55: =Admin!AX16 -> 0 | AY55: =Admin!AY16 -> 0 | AZ55: =Admin!AZ16 -> 0 | BA55: =Admin!BA16 -> 0 | ... BE55: =Admin!BE16 -> 0 | BF55: =SUM(AT55:BE55) -> 0 | BH55: =Admin!BH16 -> 0 | BI55: =Admin!BI16 -> 0 | BJ55: =Admin!BJ16 -> 0 | BK55: =Admin!BK16 -> 0 | BL55: =Admin!BL16 -> 0 | BM55: =Admin!BM16 -> 0 | BN55: =Admin!BN16 -> 0 | BO55: =Admin!BO16 -> 0 | ... BS55: =Admin!BS16 -> 0 | BT55: =SUM(BH55:BS55) -> 0 | BV55: =Admin!BV16 -> 0 | BW55: =Admin!BW16 -> 0 | BX55: =Admin!BX16 -> 0 | BY55: =Admin!BY16 -> 0 | BZ55: =Admin!BZ16 -> 0 | CA55: =Admin!CA16 -> 0 | CB55: =Admin!CB16 -> 0 | CC55: =Admin!CC16 -> 0 | ... CG55: =Admin!CG16 -> 0 | CH55: =SUM(BV55:CG55) -> 0
B56: =Admin!B17 -> Software/Licences | C56: =Admin!C17 -> A6 | D56: =Admin!D17 -> 0 | E56: =Admin!E17 -> 0 | F56: =Admin!F17 -> 0 | G56: =Admin!G17 -> 0 | H56: =Admin!H17 -> 0 | I56: =Admin!I17 -> 0 | ... O56: =Admin!O17 -> 350 | P56: =SUM(D56:O56) -> 2100 | R56: =Admin!R17 -> 369.6 | S56: =Admin!S17 -> 369.6 | T56: =Admin!T17 -> 369.6 | U56: =Admin!U17 -> 369.6 | V56: =Admin!V17 -> 369.6 | W56: =Admin!W17 -> 369.6 | X56: =Admin!X17 -> 369.6 | Y56: =Admin!Y17 -> 369.6 | ... AC56: =Admin!AC17 -> 369.6 | AD56: =SUM(R56:AC56) -> 4435.2 | AF56: =Admin!AF17 -> 388.4496 | AG56: =Admin!AG17 -> 388.4496 | AH56: =Admin!AH17 -> 388.4496 | AI56: =Admin!AI17 -> 388.4496 | AJ56: =Admin!AJ17 -> 388.4496 | AK56: =Admin!AK17 -> 388.4496 | AL56: =Admin!AL17 -> 388.4496 | AM56: =Admin!AM17 -> 388.4496 | ... AQ56: =Admin!AQ17 -> 388.4496 | AR56: =SUM(AF56:AQ56) -> 4661.3952 | AT56: =Admin!AT17 -> 408.26053 | AU56: =Admin!AU17 -> 408.26053 | AV56: =Admin!AV17 -> 408.26053 | AW56: =Admin!AW17 -> 408.26053 | AX56: =Admin!AX17 -> 408.26053 | AY56: =Admin!AY17 -> 408.26053 | AZ56: =Admin!AZ17 -> 408.26053 | BA56: =Admin!BA17 -> 408.26053 | ... BE56: =Admin!BE17 -> 408.26053 | BF56: =SUM(AT56:BE56) -> 4899.1264 | BH56: =Admin!BH17 -> 429.08182 | BI56: =Admin!BI17 -> 429.08182 | BJ56: =Admin!BJ17 -> 429.08182 | BK56: =Admin!BK17 -> 429.08182 | BL56: =Admin!BL17 -> 429.08182 | BM56: =Admin!BM17 -> 429.08182 | BN56: =Admin!BN17 -> 429.08182 | BO56: =Admin!BO17 -> 429.08182 | ... BS56: =Admin!BS17 -> 429.08182 | BT56: =SUM(BH56:BS56) -> 5148.9818 | BV56: =Admin!BV17 -> 450.96499 | BW56: =Admin!BW17 -> 450.96499 | BX56: =Admin!BX17 -> 450.96499 | BY56: =Admin!BY17 -> 450.96499 | BZ56: =Admin!BZ17 -> 450.96499 | CA56: =Admin!CA17 -> 450.96499 | CB56: =Admin!CB17 -> 450.96499 | CC56: =Admin!CC17 -> 450.96499 | ... CG56: =Admin!CG17 -> 450.96499 | CH56: =SUM(BV56:CG56) -> 5411.5799
B57: =Admin!B18 -> Capex - Maintenance | C57: =Admin!C18 -> A7 | D57: =Admin!D18 -> 0 | E57: =Admin!E18 -> 0 | F57: =Admin!F18 -> 0 | G57: =Admin!G18 -> 0 | H57: =Admin!H18 -> 0 | I57: =Admin!I18 -> 0 | ... O57: =Admin!O18 -> 0 | P57: =SUM(D57:O57) -> 0 | R57: =Admin!R18 -> 0 | S57: =Admin!S18 -> 0 | T57: =Admin!T18 -> 0 | U57: =Admin!U18 -> 0 | V57: =Admin!V18 -> 0 | W57: =Admin!W18 -> 0 | X57: =Admin!X18 -> 0 | Y57: =Admin!Y18 -> 0 | ... AC57: =Admin!AC18 -> 0 | AD57: =SUM(R57:AC57) -> 0 | AF57: =Admin!AF18 -> 0 | AG57: =Admin!AG18 -> 0 | AH57: =Admin!AH18 -> 0 | AI57: =Admin!AI18 -> 0 | AJ57: =Admin!AJ18 -> 0 | AK57: =Admin!AK18 -> 0 | AL57: =Admin!AL18 -> 0 | AM57: =Admin!AM18 -> 0 | ... AQ57: =Admin!AQ18 -> 0 | AR57: =SUM(AF57:AQ57) -> 0 | AT57: =Admin!AT18 -> 0 | AU57: =Admin!AU18 -> 0 | AV57: =Admin!AV18 -> 0 | AW57: =Admin!AW18 -> 0 | AX57: =Admin!AX18 -> 0 | AY57: =Admin!AY18 -> 0 | AZ57: =Admin!AZ18 -> 0 | BA57: =Admin!BA18 -> 0 | ... BE57: =Admin!BE18 -> 0 | BF57: =SUM(AT57:BE57) -> 0 | BH57: =Admin!BH18 -> 0 | BI57: =Admin!BI18 -> 0 | BJ57: =Admin!BJ18 -> 0 | BK57: =Admin!BK18 -> 0 | BL57: =Admin!BL18 -> 0 | BM57: =Admin!BM18 -> 0 | BN57: =Admin!BN18 -> 0 | BO57: =Admin!BO18 -> 0 | ... BS57: =Admin!BS18 -> 0 | BT57: =SUM(BH57:BS57) -> 0 | BV57: =Admin!BV18 -> 0 | BW57: =Admin!BW18 -> 0 | BX57: =Admin!BX18 -> 0 | BY57: =Admin!BY18 -> 0 | BZ57: =Admin!BZ18 -> 0 | CA57: =Admin!CA18 -> 0 | CB57: =Admin!CB18 -> 0 | CC57: =Admin!CC18 -> 0 | ... CG57: =Admin!CG18 -> 0 | CH57: =SUM(BV57:CG57) -> 0
B58: ADMINISTRATIVE | D58: =SUM(D51:D57) -> 0 | E58: =SUM(E51:E57) -> 0 | F58: =SUM(F51:F57) -> 0 | G58: =SUM(G51:G57) -> 0 | H58: =SUM(H51:H57) -> 0 | I58: =SUM(I51:I57) -> 0 | J58: =SUM(J51:J57) -> 10750 | K58: =SUM(K51:K57) -> 500 | ... O58: =SUM(O51:O57) -> 500 | P58: =SUM(D58:O58) -> 13250 | R58: =SUM(R51:R57) -> 528 | S58: =SUM(S51:S57) -> 5528 | T58: =SUM(T51:T57) -> 528 | U58: =SUM(U51:U57) -> 528 | V58: =SUM(V51:V57) -> 528 | W58: =SUM(W51:W57) -> 528 | X58: =SUM(X51:X57) -> 11352 | Y58: =SUM(Y51:Y57) -> 528 | ... AC58: =SUM(AC51:AC57) -> 528 | AD58: =SUM(R58:AC58) -> 22160 | AF58: =SUM(AF51:AF57) -> 554.928 | AG58: =SUM(AG51:AG57) -> 5809.928 | AH58: =SUM(AH51:AH57) -> 554.928 | AI58: =SUM(AI51:AI57) -> 554.928 | AJ58: =SUM(AJ51:AJ57) -> 554.928 | AK58: =SUM(AK51:AK57) -> 554.928 | AL58: =SUM(AL51:AL57) -> 11930.952 | AM58: =SUM(AM51:AM57) -> 554.928 | ... AQ58: =SUM(AQ51:AQ57) -> 554.928 | AR58: =SUM(AF58:AQ58) -> 23290.16 | AT58: =SUM(AT51:AT57) -> 583.22933 | AU58: =SUM(AU51:AU57) -> 6106.2343 | AV58: =SUM(AV51:AV57) -> 583.22933 | AW58: =SUM(AW51:AW57) -> 583.22933 | AX58: =SUM(AX51:AX57) -> 583.22933 | AY58: =SUM(AY51:AY57) -> 583.22933 | AZ58: =SUM(AZ51:AZ57) -> 12539.431 | BA58: =SUM(BA51:BA57) -> 583.22933 | ... BE58: =SUM(BE51:BE57) -> 583.22933 | BF58: =SUM(AT58:BE58) -> 24477.958 | BH58: =SUM(BH51:BH57) -> 612.97402 | BI58: =SUM(BI51:BI57) -> 6417.6523 | BJ58: =SUM(BJ51:BJ57) -> 612.97402 | BK58: =SUM(BK51:BK57) -> 612.97402 | BL58: =SUM(BL51:BL57) -> 612.97402 | BM58: =SUM(BM51:BM57) -> 612.97402 | BN58: =SUM(BN51:BN57) -> 13178.942 | BO58: =SUM(BO51:BO57) -> 612.97402 | ... BS58: =SUM(BS51:BS57) -> 612.97402 | BT58: =SUM(BH58:BS58) -> 25726.334 | BV58: =SUM(BV51:BV57) -> 644.2357 | BW58: =SUM(BW51:BW57) -> 6744.9525 | BX58: =SUM(BX51:BX57) -> 644.2357 | BY58: =SUM(BY51:BY57) -> 644.2357 | BZ58: =SUM(BZ51:BZ57) -> 644.2357 | CA58: =SUM(CA51:CA57) -> 644.2357 | CB58: =SUM(CB51:CB57) -> 13851.068 | CC58: =SUM(CC51:CC57) -> 644.2357 | ... CG58: =SUM(CG51:CG57) -> 644.2357 | CH58: =SUM(BV58:CG58) -> 27038.377
B60: =Consulting!B12 -> Legal Fees - Adriana | C60: =Consulting!C12 -> C1 | D60: =Consulting!D12 -> 0 | E60: =Consulting!E12 -> 0 | F60: =Consulting!F12 -> 0 | G60: =Consulting!G12 -> 0 | H60: =Consulting!H12 -> -1500 | I60: =Consulting!I12 -> -1500 | ... O60: =Consulting!O12 -> -1500 | P60: =SUM(D60:O60) -> -12000 | R60: =Consulting!R12 -> -1500 | S60: =Consulting!S12 -> -1500 | T60: =Consulting!T12 -> -1500 | U60: =Consulting!U12 -> -1500 | V60: =Consulting!V12 -> -1000 | W60: =Consulting!W12 -> -1000 | X60: =Consulting!X12 -> -1000 | Y60: =Consulting!Y12 -> -1000 | ... AC60: =Consulting!AC12 -> -1000 | AD60: =SUM(R60:AC60) -> -14000 | AF60: =Consulting!AF12 -> -1051 | AG60: =Consulting!AG12 -> -1051 | AH60: =Consulting!AH12 -> -1051 | AI60: =Consulting!AI12 -> -1051 | AJ60: =Consulting!AJ12 -> -1051 | AK60: =Consulting!AK12 -> -1051 | AL60: =Consulting!AL12 -> -1051 | AM60: =Consulting!AM12 -> -1051 | ... AQ60: =Consulting!AQ12 -> -1051 | AR60: =SUM(AF60:AQ60) -> -12612 | AT60: =Consulting!AT12 -> -1104.601 | AU60: =Consulting!AU12 -> -1104.601 | AV60: =Consulting!AV12 -> -1104.601 | AW60: =Consulting!AW12 -> -1104.601 | AX60: =Consulting!AX12 -> -1104.601 | AY60: =Consulting!AY12 -> -1104.601 | AZ60: =Consulting!AZ12 -> -1104.601 | BA60: =Consulting!BA12 -> -1104.601 | ... BE60: =Consulting!BE12 -> -1104.601 | BF60: =SUM(AT60:BE60) -> -13255.212 | BH60: =Consulting!BH12 -> -1160.9357 | BI60: =Consulting!BI12 -> -1160.9357 | BJ60: =Consulting!BJ12 -> -1160.9357 | BK60: =Consulting!BK12 -> -1160.9357 | BL60: =Consulting!BL12 -> -1160.9357 | BM60: =Consulting!BM12 -> -1160.9357 | BN60: =Consulting!BN12 -> -1160.9357 | BO60: =Consulting!BO12 -> -1160.9357 | ... BS60: =Consulting!BS12 -> -1160.9357 | BT60: =SUM(BH60:BS60) -> -13931.228 | BV60: =Consulting!BV12 -> -1220.1434 | BW60: =Consulting!BW12 -> -1220.1434 | BX60: =Consulting!BX12 -> -1220.1434 | BY60: =Consulting!BY12 -> -1220.1434 | BZ60: =Consulting!BZ12 -> -1220.1434 | CA60: =Consulting!CA12 -> -1220.1434 | CB60: =Consulting!CB12 -> -1220.1434 | CC60: =Consulting!CC12 -> -1220.1434 | ... CG60: =Consulting!CG12 -> -1220.1434 | CH60: =SUM(BV60:CG60) -> -14641.72
B61: =Consulting!B13 -> Marketing - Rebu | C61: =Consulting!C13 -> C2 | D61: =Consulting!D13 -> 0 | E61: =Consulting!E13 -> 0 | F61: =Consulting!F13 -> -20000 | G61: =Consulting!G13 -> 0 | H61: =Consulting!H13 -> 0 | I61: =Consulting!I13 -> 0 | ... O61: =Consulting!O13 -> 0 | P61: =SUM(D61:O61) -> -30000 | R61: =Consulting!R13 -> 0 | S61: =Consulting!S13 -> 0 | T61: =Consulting!T13 -> -21120 | U61: =Consulting!U13 -> 0 | V61: =Consulting!V13 -> 0 | W61: =Consulting!W13 -> 0 | X61: =Consulting!X13 -> 0 | Y61: =Consulting!Y13 -> 0 | ... AC61: =Consulting!AC13 -> 0 | AD61: =SUM(R61:AC61) -> -31680 | AF61: =Consulting!AF13 -> 0 | AG61: =Consulting!AG13 -> 0 | AH61: =Consulting!AH13 -> -22197.12 | AI61: =Consulting!AI13 -> 0 | AJ61: =Consulting!AJ13 -> 0 | AK61: =Consulting!AK13 -> 0 | AL61: =Consulting!AL13 -> 0 | AM61: =Consulting!AM13 -> 0 | ... AQ61: =Consulting!AQ13 -> 0 | AR61: =SUM(AF61:AQ61) -> -33295.68 | AT61: =Consulting!AT13 -> 0 | AU61: =Consulting!AU13 -> 0 | AV61: =Consulting!AV13 -> -23329.173 | AW61: =Consulting!AW13 -> 0 | AX61: =Consulting!AX13 -> 0 | AY61: =Consulting!AY13 -> 0 | AZ61: =Consulting!AZ13 -> 0 | BA61: =Consulting!BA13 -> 0 | ... BE61: =Consulting!BE13 -> 0 | BF61: =SUM(AT61:BE61) -> -34993.76 | BH61: =Consulting!BH13 -> 0 | BI61: =Consulting!BI13 -> 0 | BJ61: =Consulting!BJ13 -> -24518.961 | BK61: =Consulting!BK13 -> 0 | BL61: =Consulting!BL13 -> 0 | BM61: =Consulting!BM13 -> 0 | BN61: =Consulting!BN13 -> 0 | BO61: =Consulting!BO13 -> 0 | ... BS61: =Consulting!BS13 -> 0 | BT61: =SUM(BH61:BS61) -> -36778.441 | BV61: =Consulting!BV13 -> 0 | BW61: =Consulting!BW13 -> 0 | BX61: =Consulting!BX13 -> -25769.428 | BY61: =Consulting!BY13 -> 0 | BZ61: =Consulting!BZ13 -> 0 | CA61: =Consulting!CA13 -> 0 | CB61: =Consulting!CB13 -> 0 | CC61: =Consulting!CC13 -> 0 | ... CG61: =Consulting!CG13 -> 0 | CH61: =SUM(BV61:CG61) -> -38654.142
B62: =Consulting!B14 -> Accounting | C62: =Consulting!C14 -> C3 | D62: =Consulting!D14 -> -128 | E62: =Consulting!E14 -> -128 | F62: =Consulting!F14 -> -128 | G62: =Consulting!G14 -> -128 | H62: =Consulting!H14 -> -128 | I62: =Consulting!I14 -> -128 | ... O62: =Consulting!O14 -> -200 | P62: =SUM(D62:O62) -> -1968 | R62: =Consulting!R14 -> -211.2 | S62: =Consulting!S14 -> -211.2 | T62: =Consulting!T14 -> -211.2 | U62: =Consulting!U14 -> -211.2 | V62: =Consulting!V14 -> -135.168 | W62: =Consulting!W14 -> -135.168 | X62: =Consulting!X14 -> -211.2 | Y62: =Consulting!Y14 -> -211.2 | ... AC62: =Consulting!AC14 -> -211.2 | AD62: =SUM(R62:AC62) -> -2382.336 | AF62: =Consulting!AF14 -> -221.9712 | AG62: =Consulting!AG14 -> -221.9712 | AH62: =Consulting!AH14 -> -221.9712 | AI62: =Consulting!AI14 -> -221.9712 | AJ62: =Consulting!AJ14 -> -142.06157 | AK62: =Consulting!AK14 -> -142.06157 | AL62: =Consulting!AL14 -> -221.9712 | AM62: =Consulting!AM14 -> -221.9712 | ... AQ62: =Consulting!AQ14 -> -221.9712 | AR62: =SUM(AF62:AQ62) -> -2503.8351 | AT62: =Consulting!AT14 -> -233.29173 | AU62: =Consulting!AU14 -> -233.29173 | AV62: =Consulting!AV14 -> -233.29173 | AW62: =Consulting!AW14 -> -233.29173 | AX62: =Consulting!AX14 -> -149.30671 | AY62: =Consulting!AY14 -> -149.30671 | AZ62: =Consulting!AZ14 -> -233.29173 | BA62: =Consulting!BA14 -> -233.29173 | ... BE62: =Consulting!BE14 -> -233.29173 | BF62: =SUM(AT62:BE62) -> -2631.5307 | BH62: =Consulting!BH14 -> -245.18961 | BI62: =Consulting!BI14 -> -245.18961 | BJ62: =Consulting!BJ14 -> -245.18961 | BK62: =Consulting!BK14 -> -245.18961 | BL62: =Consulting!BL14 -> -156.92135 | BM62: =Consulting!BM14 -> -156.92135 | BN62: =Consulting!BN14 -> -245.18961 | BO62: =Consulting!BO14 -> -245.18961 | ... BS62: =Consulting!BS14 -> -245.18961 | BT62: =SUM(BH62:BS62) -> -2765.7388 | BW62: =Consulting!BW14 -> -257.69428 | BX62: =Consulting!BX14 -> -257.69428 | BY62: =Consulting!BY14 -> -257.69428 | BZ62: =Consulting!BZ14 -> -164.92434 | CA62: =Consulting!CA14 -> -164.92434 | CB62: =Consulting!CB14 -> -257.69428 | CC62: =Consulting!CC14 -> -257.69428 | CD62: =Consulting!CD14 -> -257.69428 | ... CG62: =Consulting!CG14 -> -257.69428 | CH62: =SUM(BV62:CG62) -> -2649.0972
B63: =Consulting!B15 -> Tax Advisory Fees | C63: =Consulting!C15 -> C4 | D63: =Consulting!D15 -> 0 | E63: =Consulting!E15 -> 0 | F63: =Consulting!F15 -> 0 | G63: =Consulting!G15 -> 0 | H63: =Consulting!H15 -> 0 | I63: =Consulting!I15 -> 0 | ... O63: =Consulting!O15 -> -3000 | P63: =SUM(D63:O63) -> -6000 | R63: =Consulting!R15 -> 0 | S63: =Consulting!S15 -> 0 | T63: =Consulting!T15 -> 0 | U63: =Consulting!U15 -> 0 | V63: =Consulting!V15 -> 0 | W63: =Consulting!W15 -> 0 | X63: =Consulting!X15 -> 0 | Y63: =Consulting!Y15 -> 0 | ... AC63: =Consulting!AC15 -> -3168 | AD63: =SUM(R63:AC63) -> -6336 | AF63: =Consulting!AF15 -> 0 | AG63: =Consulting!AG15 -> 0 | AH63: =Consulting!AH15 -> 0 | AI63: =Consulting!AI15 -> 0 | AJ63: =Consulting!AJ15 -> 0 | AK63: =Consulting!AK15 -> 0 | AL63: =Consulting!AL15 -> 0 | AM63: =Consulting!AM15 -> 0 | ... AQ63: =Consulting!AQ15 -> -3329.568 | AR63: =SUM(AF63:AQ63) -> -6659.136 | AT63: =Consulting!AT15 -> 0 | AU63: =Consulting!AU15 -> 0 | AV63: =Consulting!AV15 -> 0 | AW63: =Consulting!AW15 -> 0 | AX63: =Consulting!AX15 -> 0 | AY63: =Consulting!AY15 -> 0 | AZ63: =Consulting!AZ15 -> 0 | BA63: =Consulting!BA15 -> 0 | ... BE63: =Consulting!BE15 -> -3499.376 | BF63: =SUM(AT63:BE63) -> -6998.7519 | BH63: =Consulting!BH15 -> 0 | BI63: =Consulting!BI15 -> 0 | BJ63: =Consulting!BJ15 -> 0 | BK63: =Consulting!BK15 -> 0 | BL63: =Consulting!BL15 -> 0 | BM63: =Consulting!BM15 -> 0 | BN63: =Consulting!BN15 -> 0 | BO63: =Consulting!BO15 -> 0 | ... BS63: =Consulting!BS15 -> -3677.8441 | BT63: =SUM(BH63:BS63) -> -7355.6883 | BV63: =Consulting!BV15 -> 0 | BW63: =Consulting!BW15 -> 0 | BX63: =Consulting!BX15 -> 0 | BY63: =Consulting!BY15 -> 0 | BZ63: =Consulting!BZ15 -> 0 | CA63: =Consulting!CA15 -> 0 | CB63: =Consulting!CB15 -> 0 | CC63: =Consulting!CC15 -> 0 | ... CG63: =Consulting!CG15 -> -3865.4142 | CH63: =SUM(BV63:CG63) -> -7730.8284
B64: =Consulting!B16 -> Web / IT / E-Commerce | C64: =Consulting!C16 -> C5 | D64: =Consulting!D16 -> 0 | E64: =Consulting!E16 -> 0 | F64: =Consulting!F16 -> 0 | G64: =Consulting!G16 -> 0 | H64: =Consulting!H16 -> 0 | I64: =Consulting!I16 -> -500 | ... O64: =Consulting!O16 -> -635 | P64: =SUM(D64:O64) -> -4175 | R64: =Consulting!R16 -> 0 | S64: =Consulting!S16 -> 0 | T64: =Consulting!T16 -> 0 | U64: =Consulting!U16 -> 0 | V64: =Consulting!V16 -> 0 | W64: =Consulting!W16 -> -528 | X64: =Consulting!X16 -> -528 | Y64: =Consulting!Y16 -> -670.56 | ... AC64: =Consulting!AC16 -> -670.56 | AD64: =SUM(R64:AC64) -> -4408.8 | AF64: =Consulting!AF16 -> 0 | AG64: =Consulting!AG16 -> 0 | AH64: =Consulting!AH16 -> 0 | AI64: =Consulting!AI16 -> 0 | AJ64: =Consulting!AJ16 -> 0 | AK64: =Consulting!AK16 -> -554.928 | AL64: =Consulting!AL16 -> -554.928 | AM64: =Consulting!AM16 -> -704.75856 | ... AQ64: =Consulting!AQ16 -> -704.75856 | AR64: =SUM(AF64:AQ64) -> -4633.6488 | AT64: =Consulting!AT16 -> 0 | AU64: =Consulting!AU16 -> 0 | AV64: =Consulting!AV16 -> 0 | AW64: =Consulting!AW16 -> 0 | AX64: =Consulting!AX16 -> 0 | AY64: =Consulting!AY16 -> -583.22933 | AZ64: =Consulting!AZ16 -> -583.22933 | BA64: =Consulting!BA16 -> -740.70125 | ... BE64: =Consulting!BE16 -> -740.70125 | BF64: =SUM(AT64:BE64) -> -4869.9649 | BH64: =Consulting!BH16 -> 0 | BI64: =Consulting!BI16 -> 0 | BJ64: =Consulting!BJ16 -> 0 | BK64: =Consulting!BK16 -> 0 | BL64: =Consulting!BL16 -> 0 | BM64: =Consulting!BM16 -> -612.97402 | BN64: =Consulting!BN16 -> -612.97402 | BO64: =Consulting!BO16 -> -778.47701 | ... BS64: =Consulting!BS16 -> -778.47701 | BT64: =SUM(BH64:BS64) -> -5118.3331 | BV64: =Consulting!BV16 -> 0 | BW64: =Consulting!BW16 -> 0 | BX64: =Consulting!BX16 -> 0 | BY64: =Consulting!BY16 -> 0 | BZ64: =Consulting!BZ16 -> 0 | CA64: =Consulting!CA16 -> -644.2357 | CB64: =Consulting!CB16 -> -644.2357 | CC64: =Consulting!CC16 -> -818.17934 | ... CG64: =Consulting!CG16 -> -818.17934 | CH64: =SUM(BV64:CG64) -> -5379.3681
B65: =Consulting!B17 -> Architect | C65: =Consulting!C17 -> C6 | D65: =Consulting!D17 -> 0 | E65: =Consulting!E17 -> 0 | F65: =Consulting!F17 -> 0 | G65: =Consulting!G17 -> 0 | H65: =Consulting!H17 -> 0 | I65: =Consulting!I17 -> -2100 | ... O65: =Consulting!O17 -> 0 | P65: =SUM(D65:O65) -> -6300 | R65: =Consulting!R17 -> 0 | S65: =Consulting!S17 -> 0 | T65: =Consulting!T17 -> 0 | U65: =Consulting!U17 -> 0 | V65: =Consulting!V17 -> 0 | W65: =Consulting!W17 -> -2217.6 | X65: =Consulting!X17 -> -2217.6 | Y65: =Consulting!Y17 -> -2217.6 | ... AC65: =Consulting!AC17 -> 0 | AD65: =SUM(R65:AC65) -> -6652.8 | AF65: =Consulting!AF17 -> 0 | AG65: =Consulting!AG17 -> 0 | AH65: =Consulting!AH17 -> 0 | AI65: =Consulting!AI17 -> 0 | AJ65: =Consulting!AJ17 -> 0 | AK65: =Consulting!AK17 -> -2330.6976 | AL65: =Consulting!AL17 -> -2330.6976 | AM65: =Consulting!AM17 -> -2330.6976 | ... AQ65: =Consulting!AQ17 -> 0 | AR65: =SUM(AF65:AQ65) -> -6992.0928 | AT65: =Consulting!AT17 -> 0 | AU65: =Consulting!AU17 -> 0 | AV65: =Consulting!AV17 -> 0 | AW65: =Consulting!AW17 -> 0 | AX65: =Consulting!AX17 -> 0 | AY65: =Consulting!AY17 -> -2449.5632 | AZ65: =Consulting!AZ17 -> -2449.5632 | BA65: =Consulting!BA17 -> -2449.5632 | ... BE65: =Consulting!BE17 -> 0 | BF65: =SUM(AT65:BE65) -> -7348.6895 | BH65: =Consulting!BH17 -> 0 | BI65: =Consulting!BI17 -> 0 | BJ65: =Consulting!BJ17 -> 0 | BK65: =Consulting!BK17 -> 0 | BL65: =Consulting!BL17 -> 0 | BM65: =Consulting!BM17 -> -2574.4909 | BN65: =Consulting!BN17 -> -2574.4909 | BO65: =Consulting!BO17 -> -2574.4909 | ... BS65: =Consulting!BS17 -> 0 | BT65: =SUM(BH65:BS65) -> -7723.4727 | BV65: =Consulting!BV17 -> 0 | BW65: =Consulting!BW17 -> 0 | BX65: =Consulting!BX17 -> 0 | BY65: =Consulting!BY17 -> 0 | BZ65: =Consulting!BZ17 -> 0 | CA65: =Consulting!CA17 -> -2705.7899 | CB65: =Consulting!CB17 -> -2705.7899 | CC65: =Consulting!CC17 -> -2705.7899 | ... CG65: =Consulting!CG17 -> 0 | CH65: =SUM(BV65:CG65) -> -8117.3698
B66: =Consulting!B18 -> Refurbishment | C66: =Consulting!C18 -> C7 | D66: =Consulting!D18 -> 0 | E66: =Consulting!E18 -> 0 | F66: =Consulting!F18 -> 0 | G66: =Consulting!G18 -> 0 | H66: =Consulting!H18 -> 0 | I66: =Consulting!I18 -> 0 | ... O66: =Consulting!O18 -> 0 | P66: =SUM(D66:O66) -> -21000 | R66: =Consulting!R18 -> 0 | S66: =Consulting!S18 -> 0 | T66: =Consulting!T18 -> 0 | U66: =Consulting!U18 -> 0 | V66: =Consulting!V18 -> 0 | W66: =Consulting!W18 -> 0 | X66: =Consulting!X18 -> -7392 | Y66: =Consulting!Y18 -> -7392 | ... AC66: =Consulting!AC18 -> 0 | AD66: =SUM(R66:AC66) -> -22176 | AF66: =Consulting!AF18 -> 0 | AG66: =Consulting!AG18 -> 0 | AH66: =Consulting!AH18 -> 0 | AI66: =Consulting!AI18 -> 0 | AJ66: =Consulting!AJ18 -> 0 | AK66: =Consulting!AK18 -> 0 | AL66: =Consulting!AL18 -> -7768.992 | AM66: =Consulting!AM18 -> -7768.992 | ... AQ66: =Consulting!AQ18 -> 0 | AR66: =SUM(AF66:AQ66) -> -23306.976 | AT66: =Consulting!AT18 -> 0 | AU66: =Consulting!AU18 -> 0 | AV66: =Consulting!AV18 -> 0 | AW66: =Consulting!AW18 -> 0 | AX66: =Consulting!AX18 -> 0 | AY66: =Consulting!AY18 -> 0 | AZ66: =Consulting!AZ18 -> -8165.2106 | BA66: =Consulting!BA18 -> -8165.2106 | ... BE66: =Consulting!BE18 -> 0 | BF66: =SUM(AT66:BE66) -> -24495.632 | BH66: =Consulting!BH18 -> 0 | BI66: =Consulting!BI18 -> 0 | BJ66: =Consulting!BJ18 -> 0 | BK66: =Consulting!BK18 -> 0 | BL66: =Consulting!BL18 -> 0 | BM66: =Consulting!BM18 -> 0 | BN66: =Consulting!BN18 -> -8581.6363 | BO66: =Consulting!BO18 -> -8581.6363 | ... BS66: =Consulting!BS18 -> 0 | BT66: =SUM(BH66:BS66) -> -25744.909 | BV66: =Consulting!BV18 -> 0 | BW66: =Consulting!BW18 -> 0 | BX66: =Consulting!BX18 -> 0 | BY66: =Consulting!BY18 -> 0 | BZ66: =Consulting!BZ18 -> 0 | CA66: =Consulting!CA18 -> 0 | CB66: =Consulting!CB18 -> -9019.2998 | CC66: =Consulting!CC18 -> -9019.2998 | ... CG66: =Consulting!CG18 -> 0 | CH66: =SUM(BV66:CG66) -> -27057.899
B67: CONSULTING | D67: =SUM(D60:D66) -> -128 | E67: =SUM(E60:E66) -> -128 | F67: =SUM(F60:F66) -> -20128 | G67: =SUM(G60:G66) -> -128 | H67: =SUM(H60:H66) -> -1628 | I67: =SUM(I60:I66) -> -4228 | J67: =SUM(J60:J66) -> -11300 | K67: =SUM(K60:K66) -> -11435 | ... O67: =SUM(O60:O66) -> -5335 | P67: =SUM(D67:O67) -> -81443 | R67: =SUM(R60:R66) -> -1711.2 | S67: =SUM(S60:S66) -> -1711.2 | T67: =SUM(T60:T66) -> -22831.2 | U67: =SUM(U60:U66) -> -1711.2 | V67: =SUM(V60:V66) -> -1135.168 | W67: =SUM(W60:W66) -> -3880.768 | X67: =SUM(X60:X66) -> -11348.8 | Y67: =SUM(Y60:Y66) -> -11491.36 | ... AC67: =SUM(AC60:AC66) -> -5049.76 | AD67: =SUM(R67:AC67) -> -87635.936 | AF67: =SUM(AF60:AF66) -> -1272.9712 | AG67: =SUM(AG60:AG66) -> -1272.9712 | AH67: =SUM(AH60:AH66) -> -23470.091 | AI67: =SUM(AI60:AI66) -> -1272.9712 | AJ67: =SUM(AJ60:AJ66) -> -1193.0616 | AK67: =SUM(AK60:AK66) -> -4078.6872 | AL67: =SUM(AL60:AL66) -> -11927.589 | AM67: =SUM(AM60:AM66) -> -12077.419 | ... AQ67: =SUM(AQ60:AQ66) -> -5307.2978 | AR67: =SUM(AF67:AQ67) -> -90003.369 | AT67: =SUM(AT60:AT66) -> -1337.8927 | AU67: =SUM(AU60:AU66) -> -1337.8927 | AV67: =SUM(AV60:AV66) -> -24667.066 | AW67: =SUM(AW60:AW66) -> -1337.8927 | AX67: =SUM(AX60:AX66) -> -1253.9077 | AY67: =SUM(AY60:AY66) -> -4286.7002 | AZ67: =SUM(AZ60:AZ66) -> -12535.896 | BA67: =SUM(BA60:BA66) -> -12693.368 | ... BE67: =SUM(BE60:BE66) -> -5577.9699 | BF67: =SUM(AT67:BE67) -> -94593.541 | BH67: =SUM(BH60:BH66) -> -1406.1253 | BI67: =SUM(BI60:BI66) -> -1406.1253 | BJ67: =SUM(BJ60:BJ66) -> -25925.086 | BK67: =SUM(BK60:BK66) -> -1406.1253 | BL67: =SUM(BL60:BL66) -> -1317.857 | BM67: =SUM(BM60:BM66) -> -4505.3219 | BN67: =SUM(BN60:BN66) -> -13175.227 | BO67: =SUM(BO60:BO66) -> -13340.729 | ... BS67: =SUM(BS60:BS66) -> -5862.4464 | BT67: =SUM(BH67:BS67) -> -99417.811 | BV67: =SUM(BV60:BV66) -> -1220.1434 | BW67: =SUM(BW60:BW66) -> -1477.8376 | BX67: =SUM(BX60:BX66) -> -27247.266 | BY67: =SUM(BY60:BY66) -> -1477.8376 | BZ67: =SUM(BZ60:BZ66) -> -1385.0677 | CA67: =SUM(CA60:CA66) -> -4735.0933 | CB67: =SUM(CB60:CB66) -> -13847.163 | CC67: =SUM(CC60:CC66) -> -14021.107 | ... CG67: =SUM(CG60:CG66) -> -6161.4312 | CH67: =SUM(BV67:CG67) -> -104230.43
B70: TOTAL EXPENSES | D70: =D33+D42+D49+D58+D67 -> -128 | E70: =E33+E42+E49+E58+E67 -> -128 | F70: =F33+F42+F49+F58+F67 -> -37378 | G70: =G33+G42+G49+G58+G67 -> -128 | H70: =H33+H42+H49+H58+H67 -> -1628 | I70: =I33+I42+I49+I58+I67 -> -21478 | J70: =J33+J42+J49+J58+J67 -> -15760.564 | K70: =K33+K42+K49+K58+K67 -> -26145.564 | ... P70: =P33+P42+P49+P58+P67 -> -254066.95 | R70: =R33+R42+R49+R58+R67 -> -17245.555 | S70: =S33+S42+S49+S58+S67 -> -12245.555 | T70: =T33+T42+T49+T58+T67 -> -64081.555 | U70: =U33+U42+U49+U58+U67 -> -17245.555 | V70: =V33+V42+V49+V58+V67 -> -16669.523 | W70: =W33+W42+W49+W58+W67 -> -42631.123 | X70: =X33+X42+X49+X58+X67 -> -16059.155 | Y70: =Y33+Y42+Y49+Y58+Y67 -> -27025.715 | ... AD70: =AD33+AD42+AD49+AD58+AD67 -> -370632.95 | AF70: =AF33+AF42+AF49+AF58+AF67 -> -17599.579 | AG70: =AG33+AG42+AG49+AG58+AG67 -> -12344.579 | AH70: =AH33+AH42+AH49+AH58+AH67 -> -66824.215 | AI70: =AI33+AI42+AI49+AI58+AI67 -> -17599.579 | AJ70: =AJ33+AJ42+AJ49+AJ58+AJ67 -> -17519.669 | AK70: =AK33+AK42+AK49+AK58+AK67 -> -44805.311 | AL70: =AL33+AL42+AL49+AL58+AL67 -> -16878.172 | AM70: =AM33+AM42+AM49+AM58+AM67 -> -28404.027 | ... AR70: =AR33+AR42+AR49+AR58+AR67 -> -387433.23 | AT70: =AT33+AT42+AT49+AT58+AT67 -> -18497.157 | AU70: =AU33+AU42+AU49+AU58+AU67 -> -12974.152 | AV70: =AV33+AV42+AV49+AV58+AV67 -> -70232.25 | AW70: =AW33+AW42+AW49+AW58+AW67 -> -18497.157 | AX70: =AX33+AX42+AX49+AX58+AX67 -> -18413.172 | AY70: =AY33+AY42+AY49+AY58+AY67 -> -47090.381 | AZ70: =AZ33+AZ42+AZ49+AZ58+AZ67 -> -17738.959 | BA70: =BA33+BA42+BA49+BA58+BA67 -> -29852.632 | ... BF70: =BF33+BF42+BF49+BF58+BF67 -> -407192.33 | BH70: =BH33+BH42+BH49+BH58+BH67 -> -19440.512 | BI70: =BI33+BI42+BI49+BI58+BI67 -> -13635.834 | BJ70: =BJ33+BJ42+BJ49+BJ58+BJ67 -> -73814.094 | BK70: =BK33+BK42+BK49+BK58+BK67 -> -19440.512 | BL70: =BL33+BL42+BL49+BL58+BL67 -> -19352.244 | BM70: =BM33+BM42+BM49+BM58+BM67 -> -49491.991 | BN70: =BN33+BN42+BN49+BN58+BN67 -> -18643.646 | BO70: =BO33+BO42+BO49+BO58+BO67 -> -31375.116 | ... BT70: =BT33+BT42+BT49+BT58+BT67 -> -427959.14 | BV70: =BV33+BV42+BV49+BV58+BV67 -> -20174.284 | BW70: =BW33+BW42+BW49+BW58+BW67 -> -14331.261 | BX70: =BX33+BX42+BX49+BX58+BX67 -> -77578.613 | BY70: =BY33+BY42+BY49+BY58+BY67 -> -20431.978 | BZ70: =BZ33+BZ42+BZ49+BZ58+BZ67 -> -20339.208 | CA70: =CA33+CA42+CA49+CA58+CA67 -> -52016.082 | CB70: =CB33+CB42+CB49+CB58+CB67 -> -19594.472 | CC70: =CC33+CC42+CC49+CC58+CC67 -> -32975.247 | ... CH70: =CH33+CH42+CH49+CH58+CH67 -> -449527.36
B72: EBITDA | D72: =SUM(D70,D24) -> -128 | E72: =SUM(E70,E24) -> -128 | F72: =SUM(F70,F24) -> -37378 | G72: =SUM(G70,G24) -> -128 | H72: =SUM(H70,H24) -> -1628 | I72: =SUM(I70,I24) -> -21478 | J72: =SUM(J70,J24) -> -15760.564 | K72: =SUM(K70,K24) -> -26145.564 | ... P72: =SUM(P70,P24) -> -239608.45 | R72: =SUM(R70,R24) -> -9685.5552 | S72: =SUM(S70,S24) -> -2795.5552 | T72: =SUM(T70,T24) -> -49906.555 | U72: =SUM(U70,U24) -> 79.444754 | V72: =SUM(V70,V24) -> 5380.4768 | W72: =SUM(W70,W24) -> -13777.123 | X72: =SUM(X70,X24) -> 21740.845 | Y72: =SUM(Y70,Y24) -> 20224.285 | ... AD72: =SUM(AD70,AD24) -> 2831.0458 | AF72: =SUM(AF70,AF24) -> 32060.171 | AG72: =SUM(AG70,AG24) -> 37315.171 | AH72: =SUM(AH70,AH24) -> -17164.465 | AI72: =SUM(AI70,AI24) -> 32060.171 | AJ72: =SUM(AJ70,AJ24) -> 32140.081 | AK72: =SUM(AK70,AK24) -> 4854.4395 | AL72: =SUM(AL70,AL24) -> 32781.578 | AM72: =SUM(AM70,AM24) -> 21255.723 | ... AR72: =SUM(AR70,AR24) -> 208483.77 | AT72: =SUM(AT70,AT24) -> 32950.344 | AU72: =SUM(AU70,AU24) -> 38473.349 | AV72: =SUM(AV70,AV24) -> -18784.749 | AW72: =SUM(AW70,AW24) -> 32950.344 | AX72: =SUM(AX70,AX24) -> 33034.329 | AY72: =SUM(AY70,AY24) -> 4357.1196 | AZ72: =SUM(AZ70,AZ24) -> 33708.542 | BA72: =SUM(BA70,BA24) -> 21594.869 | ... BF72: =SUM(BF70,BF24) -> 210177.68 | BH72: =SUM(BH70,BH24) -> 33807.651 | BI72: =SUM(BI70,BI24) -> 39612.33 | BJ72: =SUM(BJ70,BJ24) -> -20565.931 | BK72: =SUM(BK70,BK24) -> 33807.651 | BL72: =SUM(BL70,BL24) -> 33895.92 | BM72: =SUM(BM70,BM24) -> 3756.1727 | BN72: =SUM(BN70,BN24) -> 34604.518 | BO72: =SUM(BO70,BO24) -> 21873.047 | ... BT72: =SUM(BT70,BT24) -> 211018.82 | BV72: =SUM(BV70,BV24) -> 34937.565 | BW72: =SUM(BW70,BW24) -> 40780.588 | BX72: =SUM(BX70,BX24) -> -22466.764 | BY72: =SUM(BY70,BY24) -> 34679.871 | BZ72: =SUM(BZ70,BZ24) -> 34772.641 | CA72: =SUM(CA70,CA24) -> 3095.7669 | CB72: =SUM(CB70,CB24) -> 35517.377 | CC72: =SUM(CC70,CC24) -> 22136.602 | ... CH72: =SUM(CH70,CH24) -> 211814.83
B74: Depreciation1 | C74: D1 | D74: 0 | E74: 0 | F74: 0 | G74: 0 | H74: 0 | I74: 0 | J74: 0 | K74: 0 | L74: 0 | M74: 0 | N74: 0 | O74: 0 | P74: =SUM(D74:O74) -> 0 | R74: 0 | S74: 0 | T74: 0 | U74: 0 | V74: 0 | W74: 0 | X74: 0 | Y74: 0 | Z74: 0 | AA74: 0 | AB74: 0 | AC74: 0 | AD74: =SUM(R74:AC74) -> 0 | AF74: 0 | AG74: 0 | AH74: 0 | AI74: 0 | AJ74: 0 | AK74: 0 | AL74: 0 | AM74: 0 | AN74: 0 | AO74: 0 | AP74: 0 | AQ74: 0 | AR74: =SUM(AF74:AQ74) -> 0 | AT74: 0 | AU74: 0 | AV74: 0 | AW74: 0 | AX74: 0 | AY74: 0 | AZ74: 0 | BA74: 0 | BB74: 0 | BC74: 0 | BD74: 0 | BE74: 0 | BF74: =SUM(AT74:BE74) -> 0 | BH74: 0 | BI74: 0 | BJ74: 0 | BK74: 0 | BL74: 0 | BM74: 0 | BN74: 0 | BO74: 0 | BP74: 0 | BQ74: 0 | BR74: 0 | BS74: 0 | BT74: =SUM(BH74:BS74) -> 0 | BV74: 0 | BW74: 0 | BX74: 0 | BY74: 0 | BZ74: 0 | CA74: 0 | CB74: 0 | CC74: 0 | CD74: 0 | CE74: 0 | CF74: 0 | CG74: 0 | CH74: =SUM(BV74:CG74) -> 0
B75: Depreciation2 | C75: D2 | D75: 0 | E75: 0 | F75: 0 | G75: 0 | H75: 0 | I75: 0 | J75: 0 | K75: 0 | L75: 0 | M75: 0 | N75: 0 | O75: 0 | P75: =SUM(D75:O75) -> 0 | R75: 0 | S75: 0 | T75: 0 | U75: 0 | V75: 0 | W75: 0 | X75: 0 | Y75: 0 | Z75: 0 | AA75: 0 | AB75: 0 | AC75: 0 | AD75: =SUM(R75:AC75) -> 0 | AF75: 0 | AG75: 0 | AH75: 0 | AI75: 0 | AJ75: 0 | AK75: 0 | AL75: 0 | AM75: 0 | AN75: 0 | AO75: 0 | AP75: 0 | AQ75: 0 | AR75: =SUM(AF75:AQ75) -> 0 | AT75: 0 | AU75: 0 | AV75: 0 | AW75: 0 | AX75: 0 | AY75: 0 | AZ75: 0 | BA75: 0 | BB75: 0 | BC75: 0 | BD75: 0 | BE75: 0 | BF75: =SUM(AT75:BE75) -> 0 | BH75: 0 | BI75: 0 | BJ75: 0 | BK75: 0 | BL75: 0 | BM75: 0 | BN75: 0 | BO75: 0 | BP75: 0 | BQ75: 0 | BR75: 0 | BS75: 0 | BT75: =SUM(BH75:BS75) -> 0 | BV75: 0 | BW75: 0 | BX75: 0 | BY75: 0 | BZ75: 0 | CA75: 0 | CB75: 0 | CC75: 0 | CD75: 0 | CE75: 0 | CF75: 0 | CG75: 0 | CH75: =SUM(BV75:CG75) -> 0
B76: DEPRECIATION | D76: =SUM(D74:D75) -> 0 | E76: =SUM(E74:E75) -> 0 | F76: =SUM(F74:F75) -> 0 | G76: =SUM(G74:G75) -> 0 | H76: =SUM(H74:H75) -> 0 | I76: =SUM(I74:I75) -> 0 | J76: =SUM(J74:J75) -> 0 | K76: =SUM(K74:K75) -> 0 | ... P76: =SUM(P74:P75) -> 0 | R76: =SUM(R74:R75) -> 0 | S76: =SUM(S74:S75) -> 0 | T76: =SUM(T74:T75) -> 0 | U76: =SUM(U74:U75) -> 0 | V76: =SUM(V74:V75) -> 0 | W76: =SUM(W74:W75) -> 0 | X76: =SUM(X74:X75) -> 0 | Y76: =SUM(Y74:Y75) -> 0 | ... AD76: =SUM(AD74:AD75) -> 0 | AF76: =SUM(AF74:AF75) -> 0 | AG76: =SUM(AG74:AG75) -> 0 | AH76: =SUM(AH74:AH75) -> 0 | AI76: =SUM(AI74:AI75) -> 0 | AJ76: =SUM(AJ74:AJ75) -> 0 | AK76: =SUM(AK74:AK75) -> 0 | AL76: =SUM(AL74:AL75) -> 0 | AM76: =SUM(AM74:AM75) -> 0 | ... AR76: =SUM(AR74:AR75) -> 0 | AT76: =SUM(AT74:AT75) -> 0 | AU76: =SUM(AU74:AU75) -> 0 | AV76: =SUM(AV74:AV75) -> 0 | AW76: =SUM(AW74:AW75) -> 0 | AX76: =SUM(AX74:AX75) -> 0 | AY76: =SUM(AY74:AY75) -> 0 | AZ76: =SUM(AZ74:AZ75) -> 0 | BA76: =SUM(BA74:BA75) -> 0 | ... BF76: =SUM(BF74:BF75) -> 0 | BH76: =SUM(BH74:BH75) -> 0 | BI76: =SUM(BI74:BI75) -> 0 | BJ76: =SUM(BJ74:BJ75) -> 0 | BK76: =SUM(BK74:BK75) -> 0 | BL76: =SUM(BL74:BL75) -> 0 | BM76: =SUM(BM74:BM75) -> 0 | BN76: =SUM(BN74:BN75) -> 0 | BO76: =SUM(BO74:BO75) -> 0 | ... BT76: =SUM(BT74:BT75) -> 0 | BV76: =SUM(BV74:BV75) -> 0 | BW76: =SUM(BW74:BW75) -> 0 | BX76: =SUM(BX74:BX75) -> 0 | BY76: =SUM(BY74:BY75) -> 0 | BZ76: =SUM(BZ74:BZ75) -> 0 | CA76: =SUM(CA74:CA75) -> 0 | CB76: =SUM(CB74:CB75) -> 0 | CC76: =SUM(CC74:CC75) -> 0 | ... CH76: =SUM(CH74:CH75) -> 0
B78: EBIT | D78: =SUM(D72,D76) -> -128 | E78: =SUM(E72,E76) -> -128 | F78: =SUM(F72,F76) -> -37378 | G78: =SUM(G72,G76) -> -128 | H78: =SUM(H72,H76) -> -1628 | I78: =SUM(I72,I76) -> -21478 | J78: =SUM(J72,J76) -> -15760.564 | K78: =SUM(K72,K76) -> -26145.564 | ... P78: =SUM(P72,P76) -> -239608.45 | R78: =SUM(R72,R76) -> -9685.5552 | S78: =SUM(S72,S76) -> -2795.5552 | T78: =SUM(T72,T76) -> -49906.555 | U78: =SUM(U72,U76) -> 79.444754 | V78: =SUM(V72,V76) -> 5380.4768 | W78: =SUM(W72,W76) -> -13777.123 | X78: =SUM(X72,X76) -> 21740.845 | Y78: =SUM(Y72,Y76) -> 20224.285 | ... AD78: =SUM(AD72,AD76) -> 2831.0458 | AF78: =SUM(AF72,AF76) -> 32060.171 | AG78: =SUM(AG72,AG76) -> 37315.171 | AH78: =SUM(AH72,AH76) -> -17164.465 | AI78: =SUM(AI72,AI76) -> 32060.171 | AJ78: =SUM(AJ72,AJ76) -> 32140.081 | AK78: =SUM(AK72,AK76) -> 4854.4395 | AL78: =SUM(AL72,AL76) -> 32781.578 | AM78: =SUM(AM72,AM76) -> 21255.723 | ... AR78: =SUM(AR72,AR76) -> 208483.77 | AT78: =SUM(AT72,AT76) -> 32950.344 | AU78: =SUM(AU72,AU76) -> 38473.349 | AV78: =SUM(AV72,AV76) -> -18784.749 | AW78: =SUM(AW72,AW76) -> 32950.344 | AX78: =SUM(AX72,AX76) -> 33034.329 | AY78: =SUM(AY72,AY76) -> 4357.1196 | AZ78: =SUM(AZ72,AZ76) -> 33708.542 | BA78: =SUM(BA72,BA76) -> 21594.869 | ... BF78: =SUM(BF72,BF76) -> 210177.68 | BH78: =SUM(BH72,BH76) -> 33807.651 | BI78: =SUM(BI72,BI76) -> 39612.33 | BJ78: =SUM(BJ72,BJ76) -> -20565.931 | BK78: =SUM(BK72,BK76) -> 33807.651 | BL78: =SUM(BL72,BL76) -> 33895.92 | BM78: =SUM(BM72,BM76) -> 3756.1727 | BN78: =SUM(BN72,BN76) -> 34604.518 | BO78: =SUM(BO72,BO76) -> 21873.047 | ... BT78: =SUM(BT72,BT76) -> 211018.82 | BV78: =SUM(BV72,BV76) -> 34937.565 | BW78: =SUM(BW72,BW76) -> 40780.588 | BX78: =SUM(BX72,BX76) -> -22466.764 | BY78: =SUM(BY72,BY76) -> 34679.871 | BZ78: =SUM(BZ72,BZ76) -> 34772.641 | CA78: =SUM(CA72,CA76) -> 3095.7669 | CB78: =SUM(CB72,CB76) -> 35517.377 | CC78: =SUM(CC72,CC76) -> 22136.602 | ... CH78: =SUM(CH72,CH76) -> 211814.83
B80: CORPORATE INCOME TAX (Group Taxation) | D80: 0 | E80: 0 | F80: 0 | G80: 0 | H80: 0 | I80: 0 | J80: 0 | K80: 0 | L80: 0 | M80: 0 | N80: 0 | O80: =IF(P78>0,P78*0.25,0) -> 0 | P80: =IF(Q78>0,Q78*0.25,0) -> 0 | R80: 0 | S80: 0 | T80: 0 | U80: 0 | V80: 0 | W80: 0 | X80: 0 | Y80: 0 | Z80: 0 | AA80: 0 | AB80: 0 | AC80: 0 | AD80: 0 | AF80: 0 | AG80: 0 | AH80: 0 | AI80: 0 | AJ80: 0 | AK80: 0 | AL80: 0 | AM80: 0 | AN80: 0 | AO80: 0 | AP80: 0 | AQ80: 0 | AR80: 0 | AT80: 0 | AU80: 0 | AV80: 0 | AW80: 0 | AX80: 0 | AY80: 0 | AZ80: 0 | BA80: 0 | BB80: 0 | BC80: 0 | BD80: 0 | BE80: 0 | BF80: 0 | BH80: 0 | BI80: 0 | BJ80: 0 | BK80: 0 | BL80: 0 | BM80: 0 | BN80: 0 | BO80: 0 | BP80: 0 | BQ80: 0 | BR80: 0 | BS80: 0 | BT80: 0 | BV80: 0 | BW80: 0 | BX80: 0 | BY80: 0 | BZ80: 0 | CA80: 0 | CB80: 0 | CC80: 0 | CD80: 0 | CE80: 0 | CF80: 0 | CG80: 0 | CH80: 0
B82: NET INCOME | D82: =SUM(D80,D78) -> -128 | E82: =SUM(E80,E78) -> -128 | F82: =SUM(F80,F78) -> -37378 | G82: =SUM(G80,G78) -> -128 | H82: =SUM(H80,H78) -> -1628 | I82: =SUM(I80,I78) -> -21478 | J82: =SUM(J80,J78) -> -15760.564 | K82: =SUM(K80,K78) -> -26145.564 | ... P82: =SUM(P80,P78) -> -239608.45 | R82: =SUM(R80,R78) -> -9685.5552 | S82: =SUM(S80,S78) -> -2795.5552 | T82: =SUM(T80,T78) -> -49906.555 | U82: =SUM(U80,U78) -> 79.444754 | V82: =SUM(V80,V78) -> 5380.4768 | W82: =SUM(W80,W78) -> -13777.123 | X82: =SUM(X80,X78) -> 21740.845 | Y82: =SUM(Y80,Y78) -> 20224.285 | ... AD82: =SUM(AD80,AD78) -> 2831.0458 | AF82: =SUM(AF80,AF78) -> 32060.171 | AG82: =SUM(AG80,AG78) -> 37315.171 | AH82: =SUM(AH80,AH78) -> -17164.465 | AI82: =SUM(AI80,AI78) -> 32060.171 | AJ82: =SUM(AJ80,AJ78) -> 32140.081 | AK82: =SUM(AK80,AK78) -> 4854.4395 | AL82: =SUM(AL80,AL78) -> 32781.578 | AM82: =SUM(AM80,AM78) -> 21255.723 | ... AR82: =SUM(AR80,AR78) -> 208483.77 | AT82: =SUM(AT80,AT78) -> 32950.344 | AU82: =SUM(AU80,AU78) -> 38473.349 | AV82: =SUM(AV80,AV78) -> -18784.749 | AW82: =SUM(AW80,AW78) -> 32950.344 | AX82: =SUM(AX80,AX78) -> 33034.329 | AY82: =SUM(AY80,AY78) -> 4357.1196 | AZ82: =SUM(AZ80,AZ78) -> 33708.542 | BA82: =SUM(BA80,BA78) -> 21594.869 | ... BF82: =SUM(BF80,BF78) -> 210177.68 | BH82: =SUM(BH80,BH78) -> 33807.651 | BI82: =SUM(BI80,BI78) -> 39612.33 | BJ82: =SUM(BJ80,BJ78) -> -20565.931 | BK82: =SUM(BK80,BK78) -> 33807.651 | BL82: =SUM(BL80,BL78) -> 33895.92 | BM82: =SUM(BM80,BM78) -> 3756.1727 | BN82: =SUM(BN80,BN78) -> 34604.518 | BO82: =SUM(BO80,BO78) -> 21873.047 | ... BT82: =SUM(BT80,BT78) -> 211018.82 | BV82: =SUM(BV80,BV78) -> 34937.565 | BW82: =SUM(BW80,BW78) -> 40780.588 | BX82: =SUM(BX80,BX78) -> -22466.764 | BY82: =SUM(BY80,BY78) -> 34679.871 | BZ82: =SUM(BZ80,BZ78) -> 34772.641 | CA82: =SUM(CA80,CA78) -> 3095.7669 | CB82: =SUM(CB80,CB78) -> 35517.377 | CC82: =SUM(CC80,CC78) -> 22136.602 | ... CH82: =SUM(CH80,CH78) -> 211814.83

Sheet Base Data
A3: BASE DATA
A5: Company | B5: ZHY
A7: YEAR | B7: 2025
A8: YEAR+1 | B8: =+B7+1 -> 2026 | D8: Indexation | E8: 0.056
A9: YEAR+2 | B9: =+B8+1 -> 2027 | D9: Indexation | E9: 0.051
A10: YEAR+3 | B10: =+B9+1 -> 2028 | D10: Indexation | E10: 0.036
A11: YEAR+4 | B11: =+B10+1 -> 2029 | D11: Indexation | E11: 0.035
A12: YEAR+5 | B12: =+B11+1 -> 2030 | D12: Indexation | E12: 0.035
A13: YEAR+6 | B13: =+B12+1 -> 2031 | D13: Indexation | E13: 0.035
A15: MONTH | B15: 12

Sheet INPUT Costs -->

Sheet Operational
B1: Comp | D1: =+COMP -> ZHY | E1: =+COMP -> ZHY | F1: =+COMP -> ZHY | G1: =+COMP -> ZHY | H1: =+COMP -> ZHY | I1: =+COMP -> ZHY | J1: =+COMP -> ZHY | K1: =+COMP -> ZHY | ... P1: =+COMP -> ZHY | R1: =+COMP -> ZHY | S1: =+COMP -> ZHY | T1: =+COMP -> ZHY | U1: =+COMP -> ZHY | V1: =+COMP -> ZHY | W1: =+COMP -> ZHY | X1: =+COMP -> ZHY | Y1: =+COMP -> ZHY | ... AD1: =+COMP -> ZHY | AF1: =+COMP -> ZHY | AG1: =+COMP -> ZHY | AH1: =+COMP -> ZHY | AI1: =+COMP -> ZHY | AJ1: =+COMP -> ZHY | AK1: =+COMP -> ZHY | AL1: =+COMP -> ZHY | AM1: =+COMP -> ZHY | ... AR1: =+COMP -> ZHY | AT1: =+COMP -> ZHY | AU1: =+COMP -> ZHY | AV1: =+COMP -> ZHY | AW1: =+COMP -> ZHY | AX1: =+COMP -> ZHY | AY1: =+COMP -> ZHY | AZ1: =+COMP -> ZHY | BA1: =+COMP -> ZHY | ... BF1: =+COMP -> ZHY | BH1: =+COMP -> ZHY | BI1: =+COMP -> ZHY | BJ1: =+COMP -> ZHY | BK1: =+COMP -> ZHY | BL1: =+COMP -> ZHY | BM1: =+COMP -> ZHY | BN1: =+COMP -> ZHY | BO1: =+COMP -> ZHY | ... BT1: =+COMP -> ZHY | BV1: =+COMP -> ZHY | BW1: =+COMP -> ZHY | BX1: =+COMP -> ZHY | BY1: =+COMP -> ZHY | BZ1: =+COMP -> ZHY | CA1: =+COMP -> ZHY | CB1: =+COMP -> ZHY | CC1: =+COMP -> ZHY | ... CH1: =+COMP -> ZHY
B2: YEAR | D2: =+YEAR -> 2025 | E2: =+YEAR -> 2025 | F2: =+YEAR -> 2025 | G2: =+YEAR -> 2025 | H2: =+YEAR -> 2025 | I2: =+YEAR -> 2025 | J2: =+YEAR -> 2025 | K2: =+YEAR -> 2025 | ... P2: =+YEAR -> 2025 | R2: =+YEAR_1 -> 2026 | S2: =+YEAR_1 -> 2026 | T2: =+YEAR_1 -> 2026 | U2: =+YEAR_1 -> 2026 | V2: =+YEAR_1 -> 2026 | W2: =+YEAR_1 -> 2026 | X2: =+YEAR_1 -> 2026 | Y2: =+YEAR_1 -> 2026 | ... AC2: =+YEAR_1 -> 2026 | AD2: =+YEAR+1 -> 2026 | AF2: =+YEAR_2 -> 2027 | AG2: =+YEAR_2 -> 2027 | AH2: =+YEAR_2 -> 2027 | AI2: =+YEAR_2 -> 2027 | AJ2: =+YEAR_2 -> 2027 | AK2: =+YEAR_2 -> 2027 | AL2: =+YEAR_2 -> 2027 | AM2: =+YEAR_2 -> 2027 | ... AQ2: =+YEAR_2 -> 2027 | AR2: =+YEAR+2 -> 2027 | AT2: =+YEAR_3 -> 2028 | AU2: =+YEAR_3 -> 2028 | AV2: =+YEAR_3 -> 2028 | AW2: =+YEAR_3 -> 2028 | AX2: =+YEAR_3 -> 2028 | AY2: =+YEAR_3 -> 2028 | AZ2: =+YEAR_3 -> 2028 | BA2: =+YEAR_3 -> 2028 | ... BE2: =+YEAR_3 -> 2028 | BF2: =+YEAR+3 -> 2028 | BH2: =+YEAR_4 -> 2029 | BI2: =+YEAR_4 -> 2029 | BJ2: =+YEAR_4 -> 2029 | BK2: =+YEAR_4 -> 2029 | BL2: =+YEAR_4 -> 2029 | BM2: =+YEAR_4 -> 2029 | BN2: =+YEAR_4 -> 2029 | BO2: =+YEAR_4 -> 2029 | ... BS2: =+YEAR_4 -> 2029 | BT2: =+YEAR+4 -> 2029 | BV2: =+YEAR_5 -> 2030 | BW2: =+YEAR_5 -> 2030 | BX2: =+YEAR_5 -> 2030 | BY2: =+YEAR_5 -> 2030 | BZ2: =+YEAR_5 -> 2030 | CA2: =+YEAR_5 -> 2030 | CB2: =+YEAR_5 -> 2030 | CC2: =+YEAR_5 -> 2030 | ... CG2: =+YEAR_5 -> 2030 | CH2: =+YEAR+5 -> 2030
B3: Version | D3: P&L | E3: P&L | F3: P&L | G3: P&L | H3: P&L | I3: P&L | J3: P&L | K3: P&L | L3: P&L | M3: P&L | N3: P&L | O3: P&L | P3: P&L | R3: P&L | S3: P&L | T3: P&L | U3: P&L | V3: P&L | W3: P&L | X3: P&L | Y3: P&L | Z3: P&L | AA3: P&L | AB3: P&L | AC3: P&L | AD3: P&L | AF3: P&L | AG3: P&L | AH3: P&L | AI3: P&L | AJ3: P&L | AK3: P&L | AL3: P&L | AM3: P&L | AN3: P&L | AO3: P&L | AP3: P&L | AQ3: P&L | AR3: P&L | AT3: P&L | AU3: P&L | AV3: P&L | AW3: P&L | AX3: P&L | AY3: P&L | AZ3: P&L | BA3: P&L | BB3: P&L | BC3: P&L | BD3: P&L | BE3: P&L | BF3: P&L | BH3: P&L | BI3: P&L | BJ3: P&L | BK3: P&L | BL3: P&L | BM3: P&L | BN3: P&L | BO3: P&L | BP3: P&L | BQ3: P&L | BR3: P&L | BS3: P&L | BT3: P&L | BV3: P&L | BW3: P&L | BX3: P&L | BY3: P&L | BZ3: P&L | CA3: P&L | CB3: P&L | CC3: P&L | CD3: P&L | CE3: P&L | CF3: P&L | CG3: P&L | CH3: P&L
B4: Month | D4: 1 | E4: =+D4+1 -> 2 | F4: =+E4+1 -> 3 | G4: =+F4+1 -> 4 | H4: =+G4+1 -> 5 | I4: =+H4+1 -> 6 | J4: =+I4+1 -> 7 | K4: =+J4+1 -> 8 | L4: =+K4+1 -> 9 | ... O4: =+N4+1 -> 12 | P4: TOTAL | R4: 1 | S4: =+R4+1 -> 2 | T4: =+S4+1 -> 3 | U4: =+T4+1 -> 4 | V4: =+U4+1 -> 5 | W4: =+V4+1 -> 6 | X4: =+W4+1 -> 7 | Y4: =+X4+1 -> 8 | Z4: =+Y4+1 -> 9 | ... AC4: =+AB4+1 -> 12 | AD4: TOTAL | AF4: 1 | AG4: =+AF4+1 -> 2 | AH4: =+AG4+1 -> 3 | AI4: =+AH4+1 -> 4 | AJ4: =+AI4+1 -> 5 | AK4: =+AJ4+1 -> 6 | AL4: =+AK4+1 -> 7 | AM4: =+AL4+1 -> 8 | AN4: =+AM4+1 -> 9 | ... AQ4: =+AP4+1 -> 12 | AR4: TOTAL | AT4: 1 | AU4: =+AT4+1 -> 2 | AV4: =+AU4+1 -> 3 | AW4: =+AV4+1 -> 4 | AX4: =+AW4+1 -> 5 | AY4: =+AX4+1 -> 6 | AZ4: =+AY4+1 -> 7 | BA4: =+AZ4+1 -> 8 | BB4: =+BA4+1 -> 9 | ... BE4: =+BD4+1 -> 12 | BF4: TOTAL | BH4: 1 | BI4: =+BH4+1 -> 2 | BJ4: =+BI4+1 -> 3 | BK4: =+BJ4+1 -> 4 | BL4: =+BK4+1 -> 5 | BM4: =+BL4+1 -> 6 | BN4: =+BM4+1 -> 7 | BO4: =+BN4+1 -> 8 | BP4: =+BO4+1 -> 9 | ... BS4: =+BR4+1 -> 12 | BT4: TOTAL | BV4: 1 | BW4: =+BV4+1 -> 2 | BX4: =+BW4+1 -> 3 | BY4: =+BX4+1 -> 4 | BZ4: =+BY4+1 -> 5 | CA4: =+BZ4+1 -> 6 | CB4: =+CA4+1 -> 7 | CC4: =+CB4+1 -> 8 | CD4: =+CC4+1 -> 9 | ... CF4: =+CE4+1 -> 11 | CG4: =+CE4+1 -> 11 | CH4: TOTAL
B5: Quarter | D5: Q1 | E5: Q1 | F5: Q1 | G5: Q2 | H5: Q2 | I5: Q2 | J5: Q3 | K5: Q3 | L5: Q3 | M5: Q4 | N5: Q4 | O5: Q4 | R5: Q1 | S5: Q1 | T5: Q1 | U5: Q2 | V5: Q2 | W5: Q2 | X5: Q3 | Y5: Q3 | Z5: Q3 | AA5: Q4 | AB5: Q4 | AC5: Q4 | AF5: Q1 | AG5: Q1 | AH5: Q1 | AI5: Q2 | AJ5: Q2 | AK5: Q2 | AL5: Q3 | AM5: Q3 | AN5: Q3 | AO5: Q4 | AP5: Q4 | AQ5: Q4 | AT5: Q1 | AU5: Q1 | AV5: Q1 | AW5: Q2 | AX5: Q2 | AY5: Q2 | AZ5: Q3 | BA5: Q3 | BB5: Q3 | BC5: Q4 | BD5: Q4 | BE5: Q4 | BH5: Q1 | BI5: Q1 | BJ5: Q1 | BK5: Q2 | BL5: Q2 | BM5: Q2 | BN5: Q3 | BO5: Q3 | BP5: Q3 | BQ5: Q4 | BR5: Q4 | BS5: Q4 | BV5: Q1 | BW5: Q1 | BX5: Q1 | BY5: Q2 | BZ5: Q2 | CA5: Q2 | CB5: Q3 | CC5: Q3 | CD5: Q3 | CE5: Q4 | CF5: Q4 | CG5: Q4
B6: Active Months | D6: =+IF(D4<=MONTH,1,0) -> 1 | E6: =+IF(E4<=MONTH,1,0) -> 1 | F6: =+IF(F4<=MONTH,1,0) -> 1 | G6: =+IF(G4<=MONTH,1,0) -> 1 | H6: =+IF(H4<=MONTH,1,0) -> 1 | I6: =+IF(I4<=MONTH,1,0) -> 1 | J6: =+IF(J4<=MONTH,1,0) -> 1 | K6: =+IF(K4<=MONTH,1,0) -> 1 | ... O6: =+IF(O4<=MONTH,1,0) -> 1 | R6: =+IF(R4<=MONTH,1,0) -> 1 | S6: =+IF(S4<=MONTH,1,0) -> 1 | T6: =+IF(T4<=MONTH,1,0) -> 1 | U6: =+IF(U4<=MONTH,1,0) -> 1 | V6: =+IF(V4<=MONTH,1,0) -> 1 | W6: =+IF(W4<=MONTH,1,0) -> 1 | X6: =+IF(X4<=MONTH,1,0) -> 1 | Y6: =+IF(Y4<=MONTH,1,0) -> 1 | ... AC6: =+IF(AC4<=MONTH,1,0) -> 1 | AF6: =+IF(AF4<=MONTH,1,0) -> 1 | AG6: =+IF(AG4<=MONTH,1,0) -> 1 | AH6: =+IF(AH4<=MONTH,1,0) -> 1 | AI6: =+IF(AI4<=MONTH,1,0) -> 1 | AJ6: =+IF(AJ4<=MONTH,1,0) -> 1 | AK6: =+IF(AK4<=MONTH,1,0) -> 1 | AL6: =+IF(AL4<=MONTH,1,0) -> 1 | AM6: =+IF(AM4<=MONTH,1,0) -> 1 | ... AQ6: =+IF(AQ4<=MONTH,1,0) -> 1 | AT6: =+IF(AT4<=MONTH,1,0) -> 1 | AU6: =+IF(AU4<=MONTH,1,0) -> 1 | AV6: =+IF(AV4<=MONTH,1,0) -> 1 | AW6: =+IF(AW4<=MONTH,1,0) -> 1 | AX6: =+IF(AX4<=MONTH,1,0) -> 1 | AY6: =+IF(AY4<=MONTH,1,0) -> 1 | AZ6: =+IF(AZ4<=MONTH,1,0) -> 1 | BA6: =+IF(BA4<=MONTH,1,0) -> 1 | ... BE6: =+IF(BE4<=MONTH,1,0) -> 1 | BH6: =+IF(BH4<=MONTH,1,0) -> 1 | BI6: =+IF(BI4<=MONTH,1,0) -> 1 | BJ6: =+IF(BJ4<=MONTH,1,0) -> 1 | BK6: =+IF(BK4<=MONTH,1,0) -> 1 | BL6: =+IF(BL4<=MONTH,1,0) -> 1 | BM6: =+IF(BM4<=MONTH,1,0) -> 1 | BN6: =+IF(BN4<=MONTH,1,0) -> 1 | BO6: =+IF(BO4<=MONTH,1,0) -> 1 | ... BS6: =+IF(BS4<=MONTH,1,0) -> 1 | BV6: =+IF(BV4<=MONTH,1,0) -> 1 | BW6: =+IF(BW4<=MONTH,1,0) -> 1 | BX6: =+IF(BX4<=MONTH,1,0) -> 1 | BY6: =+IF(BY4<=MONTH,1,0) -> 1 | BZ6: =+IF(BZ4<=MONTH,1,0) -> 1 | CA6: =+IF(CA4<=MONTH,1,0) -> 1 | CB6: =+IF(CB4<=MONTH,1,0) -> 1 | CC6: =+IF(CC4<=MONTH,1,0) -> 1 | ... CG6: =+IF(CG4<=MONTH,1,0) -> 1
R7: =IND_YEAR_1 -> 0.056 | S7: Inflation | AF7: =IND_YEAR_2 -> 0.051 | AG7: Inflation | AT7: =IND_YEAR_3 -> 0.036 | AU7: Inflation | BH7: =IND_YEAR_4 -> 0.035 | BI7: Inflation | BV7: =IND_YEAR_4 -> 0.035 | BW7: Inflation
B8: ADVERTISING & TRAVEL EXPENSES
D10: =+D2 -> 2025 | E10: =+E2 -> 2025 | F10: =+F2 -> 2025 | G10: =+G2 -> 2025 | H10: =+H2 -> 2025 | I10: =+I2 -> 2025 | J10: =+J2 -> 2025 | K10: =+K2 -> 2025 | ... P10: =+P2 -> 2025 | R10: =+R2 -> 2026 | S10: =+S2 -> 2026 | T10: =+T2 -> 2026 | U10: =+U2 -> 2026 | V10: =+V2 -> 2026 | W10: =+W2 -> 2026 | X10: =+X2 -> 2026 | Y10: =+Y2 -> 2026 | ... AD10: =+AD2 -> 2026 | AF10: =+AF2 -> 2027 | AG10: =+AG2 -> 2027 | AH10: =+AH2 -> 2027 | AI10: =+AI2 -> 2027 | AJ10: =+AJ2 -> 2027 | AK10: =+AK2 -> 2027 | AL10: =+AL2 -> 2027 | AM10: =+AM2 -> 2027 | ... AR10: =+AR2 -> 2027 | AT10: =+AT2 -> 2028 | AU10: =+AU2 -> 2028 | AV10: =+AV2 -> 2028 | AW10: =+AW2 -> 2028 | AX10: =+AX2 -> 2028 | AY10: =+AY2 -> 2028 | AZ10: =+AZ2 -> 2028 | BA10: =+BA2 -> 2028 | ... BF10: =+BF2 -> 2028 | BH10: =+BH2 -> 2029 | BI10: =+BI2 -> 2029 | BJ10: =+BJ2 -> 2029 | BK10: =+BK2 -> 2029 | BL10: =+BL2 -> 2029 | BM10: =+BM2 -> 2029 | BN10: =+BN2 -> 2029 | BO10: =+BO2 -> 2029 | ... BT10: =+BT2 -> 2029 | BV10: =+BV2 -> 2030 | BW10: =+BW2 -> 2030 | BX10: =+BX2 -> 2030 | BY10: =+BY2 -> 2030 | BZ10: =+BZ2 -> 2030 | CA10: =+CA2 -> 2030 | CB10: =+CB2 -> 2030 | CC10: =+CC2 -> 2030 | ... CH10: =+CH2 -> 2030
D11: Jan | E11: Feb | F11: March | G11: April | H11: May | I11: June | J11: July | K11: Aug | L11: Sept | M11: Oct | N11: Nov | O11: Dec | P11: TOTAL | R11: Jan | S11: Feb | T11: March | U11: April | V11: May | W11: June | X11: July | Y11: Aug | Z11: Sept | AA11: Oct | AB11: Nov | AC11: Dec | AD11: TOTAL | AF11: Jan | AG11: Feb | AH11: March | AI11: April | AJ11: May | AK11: June | AL11: July | AM11: Aug | AN11: Sept | AO11: Oct | AP11: Nov | AQ11: Dec | AR11: TOTAL | AT11: Jan | AU11: Feb | AV11: March | AW11: April | AX11: May | AY11: June | AZ11: July | BA11: Aug | BB11: Sept | BC11: Oct | BD11: Nov | BE11: Dec | BF11: TOTAL | BH11: Jan | BI11: Feb | BJ11: March | BK11: April | BL11: May | BM11: June | BN11: July | BO11: Aug | BP11: Sept | BQ11: Oct | BR11: Nov | BS11: Dec | BT11: TOTAL | BV11: Jan | BW11: Feb | BX11: March | BY11: April | BZ11: May | CA11: June | CB11: July | CC11: Aug | CD11: Sept | CE11: Oct | CF11: Nov | CG11: Dec | CH11: TOTAL
B12: Main Office | C12: O1 | D12: 0 | E12: 0 | F12: 0 | G12: 0 | H12: 0 | I12: 0 | J12: -3000 | K12: -3000 | L12: -3000 | M12: -3000 | N12: -3000 | O12: -3000 | P12: =SUM(D12:O12) -> -18000 | R12: =J12*(1+$R$7) -> -3168 | S12: =R12 -> -3168 | T12: =S12 -> -3168 | U12: =T12 -> -3168 | V12: =U12 -> -3168 | W12: =V12 -> -3168 | X12: =J12*(1+$R$7) -> -3168 | Y12: =K12*(1+$R$7) -> -3168 | Z12: =L12*(1+$R$7) -> -3168 | AA12: =M12*(1+$R$7) -> -3168 | AB12: =N12*(1+$R$7) -> -3168 | AC12: =O12*(1+$R$7) -> -3168 | AD12: =SUM(R12:AC12) -> -38016 | AF12: =R12*(1+$AF$7) -> -3329.568 | AG12: =S12*(1+$AF$7) -> -3329.568 | AH12: =T12*(1+$AF$7) -> -3329.568 | AI12: =U12*(1+$AF$7) -> -3329.568 | AJ12: =V12*(1+$AF$7) -> -3329.568 | AK12: =W12*(1+$AF$7) -> -3329.568 | AL12: =X12*(1+$AF$7) -> -3329.568 | AM12: =Y12*(1+$AF$7) -> -3329.568 | ... AQ12: =AC12*(1+$AF$7) -> -3329.568 | AR12: =SUM(AF12:AQ12) -> -39954.816 | AT12: =AF12*(1+$AF$7) -> -3499.376 | AU12: =AG12*(1+$AF$7) -> -3499.376 | AV12: =AH12*(1+$AF$7) -> -3499.376 | AW12: =AI12*(1+$AF$7) -> -3499.376 | AX12: =AJ12*(1+$AF$7) -> -3499.376 | AY12: =AK12*(1+$AF$7) -> -3499.376 | AZ12: =AL12*(1+$AF$7) -> -3499.376 | BA12: =AM12*(1+$AF$7) -> -3499.376 | ... BE12: =AQ12*(1+$AF$7) -> -3499.376 | BF12: =SUM(AT12:BE12) -> -41992.512 | BH12: =AT12*(1+$AF$7) -> -3677.8441 | BI12: =AU12*(1+$AF$7) -> -3677.8441 | BJ12: =AV12*(1+$AF$7) -> -3677.8441 | BK12: =AW12*(1+$AF$7) -> -3677.8441 | BL12: =AX12*(1+$AF$7) -> -3677.8441 | BM12: =AY12*(1+$AF$7) -> -3677.8441 | BN12: =AZ12*(1+$AF$7) -> -3677.8441 | BO12: =BA12*(1+$AF$7) -> -3677.8441 | ... BS12: =BE12*(1+$AF$7) -> -3677.8441 | BT12: =SUM(BH12:BS12) -> -44134.13 | BV12: =BH12*(1+$AF$7) -> -3865.4142 | BW12: =BI12*(1+$AF$7) -> -3865.4142 | BX12: =BJ12*(1+$AF$7) -> -3865.4142 | BY12: =BK12*(1+$AF$7) -> -3865.4142 | BZ12: =BL12*(1+$AF$7) -> -3865.4142 | CA12: =BM12*(1+$AF$7) -> -3865.4142 | CB12: =BN12*(1+$AF$7) -> -3865.4142 | CC12: =BO12*(1+$AF$7) -> -3865.4142 | ... CG12: =BS12*(1+$AF$7) -> -3865.4142 | CH12: =SUM(BV12:CG12) -> -46384.97
B13: Storage | C13: 02a | D13: 0 | E13: 0 | F13: 0 | G13: 0 | H13: 0 | I13: 0 | J13: 0 | K13: 0 | L13: 0 | M13: 0 | N13: 0 | O13: 0 | P13: =SUM(D13:O13) -> 0 | R13: =J13*(1+$R$7) -> 0 | S13: =R13 -> 0 | T13: =S13 -> 0 | U13: =T13 -> 0 | V13: =U13 -> 0 | W13: =V13 -> 0 | X13: =J13*(1+$R$7) -> 0 | Y13: =K13*(1+$R$7) -> 0 | Z13: =L13*(1+$R$7) -> 0 | AA13: =M13*(1+$R$7) -> 0 | AB13: =N13*(1+$R$7) -> 0 | AC13: =O13*(1+$R$7) -> 0 | AD13: =SUM(R13:AC13) -> 0 | AF13: =R13*(1+$AF$7) -> 0 | AG13: =S13*(1+$AF$7) -> 0 | AH13: =T13*(1+$AF$7) -> 0 | AI13: =U13*(1+$AF$7) -> 0 | AJ13: =V13*(1+$AF$7) -> 0 | AK13: =W13*(1+$AF$7) -> 0 | AL13: =X13*(1+$AF$7) -> 0 | AM13: =Y13*(1+$AF$7) -> 0 | ... AQ13: =AC13*(1+$AF$7) -> 0 | AR13: =SUM(AF13:AQ13) -> 0 | AT13: =AF13*(1+$AF$7) -> 0 | AU13: =AG13*(1+$AF$7) -> 0 | AV13: =AH13*(1+$AF$7) -> 0 | AW13: =AI13*(1+$AF$7) -> 0 | AX13: =AJ13*(1+$AF$7) -> 0 | AY13: =AK13*(1+$AF$7) -> 0 | AZ13: =AL13*(1+$AF$7) -> 0 | BA13: =AM13*(1+$AF$7) -> 0 | ... BE13: =AQ13*(1+$AF$7) -> 0 | BF13: =SUM(AT13:BE13) -> 0 | BH13: =AT13*(1+$AF$7) -> 0 | BI13: =AU13*(1+$AF$7) -> 0 | BJ13: =AV13*(1+$AF$7) -> 0 | BK13: =AW13*(1+$AF$7) -> 0 | BL13: =AX13*(1+$AF$7) -> 0 | BM13: =AY13*(1+$AF$7) -> 0 | BN13: =AZ13*(1+$AF$7) -> 0 | BO13: =BA13*(1+$AF$7) -> 0 | ... BS13: =BE13*(1+$AF$7) -> 0 | BT13: =SUM(BH13:BS13) -> 0 | BV13: =BH13*(1+$AF$7) -> 0 | BW13: =BI13*(1+$AF$7) -> 0 | BX13: =BJ13*(1+$AF$7) -> 0 | BY13: =BK13*(1+$AF$7) -> 0 | BZ13: =BL13*(1+$AF$7) -> 0 | CA13: =BM13*(1+$AF$7) -> 0 | CB13: =BN13*(1+$AF$7) -> 0 | CC13: =BO13*(1+$AF$7) -> 0 | ... CG13: =BS13*(1+$AF$7) -> 0 | CH13: =SUM(BV13:CG13) -> 0
B14: x | C14: O2b | D14: 0 | E14: 0 | F14: 0 | G14: 0 | H14: 0 | I14: 0 | J14: 0 | K14: 0 | L14: 0 | M14: 0 | N14: 0 | O14: 0 | P14: =SUM(D14:O14) -> 0 | R14: =J14*(1+$R$7) -> 0 | S14: =R14 -> 0 | T14: =S14 -> 0 | U14: =T14 -> 0 | V14: =U14 -> 0 | W14: =V14 -> 0 | X14: =J14*(1+$R$7) -> 0 | Y14: =K14*(1+$R$7) -> 0 | Z14: =L14*(1+$R$7) -> 0 | AA14: =M14*(1+$R$7) -> 0 | AB14: =N14*(1+$R$7) -> 0 | AC14: =O14*(1+$R$7) -> 0 | AD14: =SUM(R14:AC14) -> 0 | AF14: =R14*(1+$AF$7) -> 0 | AG14: =S14*(1+$AF$7) -> 0 | AH14: =T14*(1+$AF$7) -> 0 | AI14: =U14*(1+$AF$7) -> 0 | AJ14: =V14*(1+$AF$7) -> 0 | AK14: =W14*(1+$AF$7) -> 0 | AL14: =X14*(1+$AF$7) -> 0 | AM14: =Y14*(1+$AF$7) -> 0 | ... AQ14: =AC14*(1+$AF$7) -> 0 | AR14: =SUM(AF14:AQ14) -> 0 | AT14: =AF14*(1+$AF$7) -> 0 | AU14: =AG14*(1+$AF$7) -> 0 | AV14: =AH14*(1+$AF$7) -> 0 | AW14: =AI14*(1+$AF$7) -> 0 | AX14: =AJ14*(1+$AF$7) -> 0 | AY14: =AK14*(1+$AF$7) -> 0 | AZ14: =AL14*(1+$AF$7) -> 0 | BA14: =AM14*(1+$AF$7) -> 0 | ... BE14: =AQ14*(1+$AF$7) -> 0 | BF14: =SUM(AT14:BE14) -> 0 | BH14: =AT14*(1+$AF$7) -> 0 | BI14: =AU14*(1+$AF$7) -> 0 | BJ14: =AV14*(1+$AF$7) -> 0 | BK14: =AW14*(1+$AF$7) -> 0 | BL14: =AX14*(1+$AF$7) -> 0 | BM14: =AY14*(1+$AF$7) -> 0 | BN14: =AZ14*(1+$AF$7) -> 0 | BO14: =BA14*(1+$AF$7) -> 0 | ... BS14: =BE14*(1+$AF$7) -> 0 | BT14: =SUM(BH14:BS14) -> 0 | BV14: =BH14*(1+$AF$7) -> 0 | BW14: =BI14*(1+$AF$7) -> 0 | BX14: =BJ14*(1+$AF$7) -> 0 | BY14: =BK14*(1+$AF$7) -> 0 | BZ14: =BL14*(1+$AF$7) -> 0 | CA14: =BM14*(1+$AF$7) -> 0 | CB14: =BN14*(1+$AF$7) -> 0 | CC14: =BO14*(1+$AF$7) -> 0 | ... CG14: =BS14*(1+$AF$7) -> 0 | CH14: =SUM(BV14:CG14) -> 0
B15: Cleaning | C15: O3 | D15: 0 | E15: 0 | F15: 0 | G15: 0 | H15: 0 | I15: 0 | J15: -500 | K15: =J15 -> -500 | L15: =K15 -> -500 | M15: =L15 -> -500 | N15: =M15 -> -500 | O15: =N15 -> -500 | P15: =SUM(D15:O15) -> -3000 | R15: =J15*(1+$R$7) -> -528 | S15: =R15 -> -528 | T15: =S15 -> -528 | U15: =T15 -> -528 | V15: =U15 -> -528 | W15: =V15 -> -528 | X15: =J15*(1+$R$7) -> -528 | Y15: =K15*(1+$R$7) -> -528 | Z15: =L15*(1+$R$7) -> -528 | AA15: =M15*(1+$R$7) -> -528 | AB15: =N15*(1+$R$7) -> -528 | AC15: =O15*(1+$R$7) -> -528 | AD15: =SUM(R15:AC15) -> -6336 | AF15: =R15*(1+$AF$7) -> -554.928 | AG15: =S15*(1+$AF$7) -> -554.928 | AH15: =T15*(1+$AF$7) -> -554.928 | AI15: =U15*(1+$AF$7) -> -554.928 | AJ15: =V15*(1+$AF$7) -> -554.928 | AK15: =W15*(1+$AF$7) -> -554.928 | AL15: =X15*(1+$AF$7) -> -554.928 | AM15: =Y15*(1+$AF$7) -> -554.928 | ... AQ15: =AC15*(1+$AF$7) -> -554.928 | AR15: =SUM(AF15:AQ15) -> -6659.136 | AT15: =AF15*(1+$AF$7) -> -583.22933 | AU15: =AG15*(1+$AF$7) -> -583.22933 | AV15: =AH15*(1+$AF$7) -> -583.22933 | AW15: =AI15*(1+$AF$7) -> -583.22933 | AX15: =AJ15*(1+$AF$7) -> -583.22933 | AY15: =AK15*(1+$AF$7) -> -583.22933 | AZ15: =AL15*(1+$AF$7) -> -583.22933 | BA15: =AM15*(1+$AF$7) -> -583.22933 | ... BE15: =AQ15*(1+$AF$7) -> -583.22933 | BF15: =SUM(AT15:BE15) -> -6998.7519 | BH15: =AT15*(1+$AF$7) -> -612.97402 | BI15: =AU15*(1+$AF$7) -> -612.97402 | BJ15: =AV15*(1+$AF$7) -> -612.97402 | BK15: =AW15*(1+$AF$7) -> -612.97402 | BL15: =AX15*(1+$AF$7) -> -612.97402 | BM15: =AY15*(1+$AF$7) -> -612.97402 | BN15: =AZ15*(1+$AF$7) -> -612.97402 | BO15: =BA15*(1+$AF$7) -> -612.97402 | ... BS15: =BE15*(1+$AF$7) -> -612.97402 | BT15: =SUM(BH15:BS15) -> -7355.6883 | BV15: =BH15*(1+$AF$7) -> -644.2357 | BW15: =BI15*(1+$AF$7) -> -644.2357 | BX15: =BJ15*(1+$AF$7) -> -644.2357 | BY15: =BK15*(1+$AF$7) -> -644.2357 | BZ15: =BL15*(1+$AF$7) -> -644.2357 | CA15: =BM15*(1+$AF$7) -> -644.2357 | CB15: =BN15*(1+$AF$7) -> -644.2357 | CC15: =BO15*(1+$AF$7) -> -644.2357 | ... CG15: =BS15*(1+$AF$7) -> -644.2357 | CH15: =SUM(BV15:CG15) -> -7730.8284
B16: Electricity | C16: O4 | D16: 0 | E16: 0 | F16: 0 | G16: 0 | H16: 0 | I16: 0 | J16: -550 | K16: -550 | L16: -550 | M16: -550 | N16: -550 | O16: -550 | P16: =SUM(D16:O16) -> -3300 | R16: =J16*(1+$R$7) -> -580.8 | S16: =R16 -> -580.8 | T16: =S16 -> -580.8 | U16: =T16 -> -580.8 | V16: =U16 -> -580.8 | W16: =V16 -> -580.8 | X16: =J16*(1+$R$7) -> -580.8 | Y16: =K16*(1+$R$7) -> -580.8 | Z16: =L16*(1+$R$7) -> -580.8 | AA16: =M16*(1+$R$7) -> -580.8 | AB16: =N16*(1+$R$7) -> -580.8 | AC16: =O16*(1+$R$7) -> -580.8 | AD16: =SUM(R16:AC16) -> -6969.6 | AF16: =R16*(1+$AF$7) -> -610.4208 | AG16: =S16*(1+$AF$7) -> -610.4208 | AH16: =T16*(1+$AF$7) -> -610.4208 | AI16: =U16*(1+$AF$7) -> -610.4208 | AJ16: =V16*(1+$AF$7) -> -610.4208 | AK16: =W16*(1+$AF$7) -> -610.4208 | AL16: =X16*(1+$AF$7) -> -610.4208 | AM16: =Y16*(1+$AF$7) -> -610.4208 | ... AQ16: =AC16*(1+$AF$7) -> -610.4208 | AR16: =SUM(AF16:AQ16) -> -7325.0496 | AT16: =AF16*(1+$AF$7) -> -641.55226 | AU16: =AG16*(1+$AF$7) -> -641.55226 | AV16: =AH16*(1+$AF$7) -> -641.55226 | AW16: =AI16*(1+$AF$7) -> -641.55226 | AX16: =AJ16*(1+$AF$7) -> -641.55226 | AY16: =AK16*(1+$AF$7) -> -641.55226 | AZ16: =AL16*(1+$AF$7) -> -641.55226 | BA16: =AM16*(1+$AF$7) -> -641.55226 | ... BE16: =AQ16*(1+$AF$7) -> -641.55226 | BF16: =SUM(AT16:BE16) -> -7698.6271 | BH16: =AT16*(1+$AF$7) -> -674.27143 | BI16: =AU16*(1+$AF$7) -> -674.27143 | BJ16: =AV16*(1+$AF$7) -> -674.27143 | BK16: =AW16*(1+$AF$7) -> -674.27143 | BL16: =AX16*(1+$AF$7) -> -674.27143 | BM16: =AY16*(1+$AF$7) -> -674.27143 | BN16: =AZ16*(1+$AF$7) -> -674.27143 | BO16: =BA16*(1+$AF$7) -> -674.27143 | ... BS16: =BE16*(1+$AF$7) -> -674.27143 | BT16: =SUM(BH16:BS16) -> -8091.2571 | BV16: =BH16*(1+$AF$7) -> -708.65927 | BW16: =BI16*(1+$AF$7) -> -708.65927 | BX16: =BJ16*(1+$AF$7) -> -708.65927 | BY16: =BK16*(1+$AF$7) -> -708.65927 | BZ16: =BL16*(1+$AF$7) -> -708.65927 | CA16: =BM16*(1+$AF$7) -> -708.65927 | CB16: =BN16*(1+$AF$7) -> -708.65927 | CC16: =BO16*(1+$AF$7) -> -708.65927 | ... CG16: =BS16*(1+$AF$7) -> -708.65927 | CH16: =SUM(BV16:CG16) -> -8503.9112
B17: Cooling / Heating | C17: O5 | D17: 0 | E17: 0 | F17: 0 | G17: 0 | H17: 0 | I17: 0 | J17: -200 | K17: -200 | L17: -200 | M17: -200 | N17: -200 | O17: -200 | P17: =SUM(D17:O17) -> -1200 | R17: =J17*(1+$R$7) -> -211.2 | S17: =R17 -> -211.2 | T17: =S17 -> -211.2 | U17: =T17 -> -211.2 | V17: =U17 -> -211.2 | W17: =V17 -> -211.2 | X17: =J17*(1+$R$7) -> -211.2 | Y17: =K17*(1+$R$7) -> -211.2 | Z17: =L17*(1+$R$7) -> -211.2 | AA17: =M17*(1+$R$7) -> -211.2 | AB17: =N17*(1+$R$7) -> -211.2 | AC17: =O17*(1+$R$7) -> -211.2 | AD17: =SUM(R17:AC17) -> -2534.4 | AF17: =R17*(1+$AF$7) -> -221.9712 | AG17: =S17*(1+$AF$7) -> -221.9712 | AH17: =T17*(1+$AF$7) -> -221.9712 | AI17: =U17*(1+$AF$7) -> -221.9712 | AJ17: =V17*(1+$AF$7) -> -221.9712 | AK17: =W17*(1+$AF$7) -> -221.9712 | AL17: =X17*(1+$AF$7) -> -221.9712 | AM17: =Y17*(1+$AF$7) -> -221.9712 | ... AQ17: =AC17*(1+$AF$7) -> -221.9712 | AR17: =SUM(AF17:AQ17) -> -2663.6544 | AT17: =AF17*(1+$AF$7) -> -233.29173 | AU17: =AG17*(1+$AF$7) -> -233.29173 | AV17: =AH17*(1+$AF$7) -> -233.29173 | AW17: =AI17*(1+$AF$7) -> -233.29173 | AX17: =AJ17*(1+$AF$7) -> -233.29173 | AY17: =AK17*(1+$AF$7) -> -233.29173 | AZ17: =AL17*(1+$AF$7) -> -233.29173 | BA17: =AM17*(1+$AF$7) -> -233.29173 | ... BE17: =AQ17*(1+$AF$7) -> -233.29173 | BF17: =SUM(AT17:BE17) -> -2799.5008 | BG17: =SUM(AT17:BE17) -> -2799.5008 | BH17: =AT17*(1+$AF$7) -> -245.18961 | BI17: =AU17*(1+$AF$7) -> -245.18961 | BJ17: =AV17*(1+$AF$7) -> -245.18961 | BK17: =AW17*(1+$AF$7) -> -245.18961 | BL17: =AX17*(1+$AF$7) -> -245.18961 | BM17: =AY17*(1+$AF$7) -> -245.18961 | BN17: =AZ17*(1+$AF$7) -> -245.18961 | BO17: =BA17*(1+$AF$7) -> -245.18961 | ... BS17: =BE17*(1+$AF$7) -> -245.18961 | BT17: =SUM(BH17:BS17) -> -2942.2753 | BV17: =BH17*(1+$AF$7) -> -257.69428 | BW17: =BI17*(1+$AF$7) -> -257.69428 | BX17: =BJ17*(1+$AF$7) -> -257.69428 | BY17: =BK17*(1+$AF$7) -> -257.69428 | BZ17: =BL17*(1+$AF$7) -> -257.69428 | CA17: =BM17*(1+$AF$7) -> -257.69428 | CB17: =BN17*(1+$AF$7) -> -257.69428 | CC17: =BO17*(1+$AF$7) -> -257.69428 | ... CG17: =BS17*(1+$AF$7) -> -257.69428 | CH17: =SUM(BV17:CG17) -> -3092.3314
B18: Service Charges | C18: O6 | D18: 0 | E18: 0 | F18: 0 | G18: 0 | H18: 0 | I18: 0 | J18: -350 | K18: -350 | L18: -350 | M18: -350 | N18: -350 | O18: -350 | P18: =SUM(D18:O18) -> -2100 | R18: =J18*(1+$R$7) -> -369.6 | S18: =R18 -> -369.6 | T18: =S18 -> -369.6 | U18: =T18 -> -369.6 | V18: =U18 -> -369.6 | W18: =V18 -> -369.6 | X18: =J18*(1+$R$7) -> -369.6 | Y18: =K18*(1+$R$7) -> -369.6 | Z18: =L18*(1+$R$7) -> -369.6 | AA18: =M18*(1+$R$7) -> -369.6 | AB18: =N18*(1+$R$7) -> -369.6 | AC18: =O18*(1+$R$7) -> -369.6 | AD18: =SUM(R18:AC18) -> -4435.2 | AF18: =R18*(1+$AF$7) -> -388.4496 | AG18: =S18*(1+$AF$7) -> -388.4496 | AH18: =T18*(1+$AF$7) -> -388.4496 | AI18: =U18*(1+$AF$7) -> -388.4496 | AJ18: =V18*(1+$AF$7) -> -388.4496 | AK18: =W18*(1+$AF$7) -> -388.4496 | AL18: =X18*(1+$AF$7) -> -388.4496 | AM18: =Y18*(1+$AF$7) -> -388.4496 | ... AQ18: =AC18*(1+$AF$7) -> -388.4496 | AR18: =SUM(AF18:AQ18) -> -4661.3952 | AT18: =AF18*(1+$AF$7) -> -408.26053 | AU18: =AG18*(1+$AF$7) -> -408.26053 | AV18: =AH18*(1+$AF$7) -> -408.26053 | AW18: =AI18*(1+$AF$7) -> -408.26053 | AX18: =AJ18*(1+$AF$7) -> -408.26053 | AY18: =AK18*(1+$AF$7) -> -408.26053 | AZ18: =AL18*(1+$AF$7) -> -408.26053 | BA18: =AM18*(1+$AF$7) -> -408.26053 | ... BE18: =AQ18*(1+$AF$7) -> -408.26053 | BF18: =SUM(AT18:BE18) -> -4899.1264 | BG18: =SUM(AT18:BE18) -> -4899.1264 | BH18: =AT18*(1+$AF$7) -> -429.08182 | BI18: =AU18*(1+$AF$7) -> -429.08182 | BJ18: =AV18*(1+$AF$7) -> -429.08182 | BK18: =AW18*(1+$AF$7) -> -429.08182 | BL18: =AX18*(1+$AF$7) -> -429.08182 | BM18: =AY18*(1+$AF$7) -> -429.08182 | BN18: =AZ18*(1+$AF$7) -> -429.08182 | BO18: =BA18*(1+$AF$7) -> -429.08182 | ... BS18: =BE18*(1+$AF$7) -> -429.08182 | BT18: =SUM(BH18:BS18) -> -5148.9818 | BV18: =BH18*(1+$AF$7) -> -450.96499 | BW18: =BI18*(1+$AF$7) -> -450.96499 | BX18: =BJ18*(1+$AF$7) -> -450.96499 | BY18: =BK18*(1+$AF$7) -> -450.96499 | BZ18: =BL18*(1+$AF$7) -> -450.96499 | CA18: =BM18*(1+$AF$7) -> -450.96499 | CB18: =BN18*(1+$AF$7) -> -450.96499 | CC18: =BO18*(1+$AF$7) -> -450.96499 | ... CG18: =BS18*(1+$AF$7) -> -450.96499 | CH18: =SUM(BV18:CG18) -> -5411.5799

Sheet Staff - Costs 2
B1: Comp | D1: =+COMP -> ZHY | E1: =+COMP -> ZHY | F1: =+COMP -> ZHY | G1: =+COMP -> ZHY | H1: =+COMP -> ZHY | I1: =+COMP -> ZHY | J1: =+COMP -> ZHY | K1: =+COMP -> ZHY | ... P1: =+COMP -> ZHY | R1: =+COMP -> ZHY | S1: =+COMP -> ZHY | T1: =+COMP -> ZHY | U1: =+COMP -> ZHY | V1: =+COMP -> ZHY | W1: =+COMP -> ZHY | X1: =+COMP -> ZHY | Y1: =+COMP -> ZHY | ... AD1: =+COMP -> ZHY | AF1: =+COMP -> ZHY | AG1: =+COMP -> ZHY | AH1: =+COMP -> ZHY | AI1: =+COMP -> ZHY | AJ1: =+COMP -> ZHY | AK1: =+COMP -> ZHY | AL1: =+COMP -> ZHY | AM1: =+COMP -> ZHY | ... AR1: =+COMP -> ZHY | AT1: =+COMP -> ZHY | AU1: =+COMP -> ZHY | AV1: =+COMP -> ZHY | AW1: =+COMP -> ZHY | AX1: =+COMP -> ZHY | AY1: =+COMP -> ZHY | AZ1: =+COMP -> ZHY | BA1: =+COMP -> ZHY | ... BF1: =+COMP -> ZHY | BH1: =+COMP -> ZHY | BI1: =+COMP -> ZHY | BJ1: =+COMP -> ZHY | BK1: =+COMP -> ZHY | BL1: =+COMP -> ZHY | BM1: =+COMP -> ZHY | BN1: =+COMP -> ZHY | BO1: =+COMP -> ZHY | ... BT1: =+COMP -> ZHY | BV1: =+COMP -> ZHY | BW1: =+COMP -> ZHY | BX1: =+COMP -> ZHY | BY1: =+COMP -> ZHY | BZ1: =+COMP -> ZHY | CA1: =+COMP -> ZHY | CB1: =+COMP -> ZHY | CC1: =+COMP -> ZHY | ... CH1: =+COMP -> ZHY
B2: YEAR | D2: =+YEAR -> 2025 | E2: =+YEAR -> 2025 | F2: =+YEAR -> 2025 | G2: =+YEAR -> 2025 | H2: =+YEAR -> 2025 | I2: =+YEAR -> 2025 | J2: =+YEAR -> 2025 | K2: =+YEAR -> 2025 | ... P2: =+YEAR -> 2025 | R2: =+YEAR_1 -> 2026 | S2: =+YEAR_1 -> 2026 | T2: =+YEAR_1 -> 2026 | U2: =+YEAR_1 -> 2026 | V2: =+YEAR_1 -> 2026 | W2: =+YEAR_1 -> 2026 | X2: =+YEAR_1 -> 2026 | Y2: =+YEAR_1 -> 2026 | ... AC2: =+YEAR_1 -> 2026 | AD2: =+YEAR+1 -> 2026 | AF2: =+YEAR_2 -> 2027 | AG2: =+YEAR_2 -> 2027 | AH2: =+YEAR_2 -> 2027 | AI2: =+YEAR_2 -> 2027 | AJ2: =+YEAR_2 -> 2027 | AK2: =+YEAR_2 -> 2027 | AL2: =+YEAR_2 -> 2027 | AM2: =+YEAR_2 -> 2027 | ... AQ2: =+YEAR_2 -> 2027 | AR2: =+YEAR+2 -> 2027 | AT2: =+YEAR_3 -> 2028 | AU2: =+YEAR_3 -> 2028 | AV2: =+YEAR_3 -> 2028 | AW2: =+YEAR_3 -> 2028 | AX2: =+YEAR_3 -> 2028 | AY2: =+YEAR_3 -> 2028 | AZ2: =+YEAR_3 -> 2028 | BA2: =+YEAR_3 -> 2028 | ... BE2: =+YEAR_3 -> 2028 | BF2: =+YEAR+3 -> 2028 | BH2: =+YEAR_4 -> 2029 | BI2: =+YEAR_4 -> 2029 | BJ2: =+YEAR_4 -> 2029 | BK2: =+YEAR_4 -> 2029 | BL2: =+YEAR_4 -> 2029 | BM2: =+YEAR_4 -> 2029 | BN2: =+YEAR_4 -> 2029 | BO2: =+YEAR_4 -> 2029 | ... BS2: =+YEAR_4 -> 2029 | BT2: =+YEAR+4 -> 2029 | BV2: =+YEAR_5 -> 2030 | BW2: =+YEAR_5 -> 2030 | BX2: =+YEAR_5 -> 2030 | BY2: =+YEAR_5 -> 2030 | BZ2: =+YEAR_5 -> 2030 | CA2: =+YEAR_5 -> 2030 | CB2: =+YEAR_5 -> 2030 | CC2: =+YEAR_5 -> 2030 | ... CG2: =+YEAR_5 -> 2030 | CH2: =+YEAR+5 -> 2030
B3: Version | D3: P&L | E3: P&L | F3: P&L | G3: P&L | H3: P&L | I3: P&L | J3: P&L | K3: P&L | L3: P&L | M3: P&L | N3: P&L | O3: P&L | P3: P&L | R3: P&L | S3: P&L | T3: P&L | U3: P&L | V3: P&L | W3: P&L | X3: P&L | Y3: P&L | Z3: P&L | AA3: P&L | AB3: P&L | AC3: P&L | AD3: P&L | AF3: P&L | AG3: P&L | AH3: P&L | AI3: P&L | AJ3: P&L | AK3: P&L | AL3: P&L | AM3: P&L | AN3: P&L | AO3: P&L | AP3: P&L | AQ3: P&L | AR3: P&L | AT3: P&L | AU3: P&L | AV3: P&L | AW3: P&L | AX3: P&L | AY3: P&L | AZ3: P&L | BA3: P&L | BB3: P&L | BC3: P&L | BD3: P&L | BE3: P&L | BF3: P&L | BH3: P&L | BI3: P&L | BJ3: P&L | BK3: P&L | BL3: P&L | BM3: P&L | BN3: P&L | BO3: P&L | BP3: P&L | BQ3: P&L | BR3: P&L | BS3: P&L | BT3: P&L | BV3: P&L | BW3: P&L | BX3: P&L | BY3: P&L | BZ3: P&L | CA3: P&L | CB3: P&L | CC3: P&L | CD3: P&L | CE3: P&L | CF3: P&L | CG3: P&L | CH3: P&L
B4: Month | D4: 1 | E4: =+D4+1 -> 2 | F4: =+E4+1 -> 3 | G4: =+F4+1 -> 4 | H4: =+G4+1 -> 5 | I4: =+H4+1 -> 6 | J4: =+I4+1 -> 7 | K4: =+J4+1 -> 8 | L4: =+K4+1 -> 9 | ... O4: =+N4+1 -> 12 | P4: TOTAL | R4: 1 | S4: =+R4+1 -> 2 | T4: =+S4+1 -> 3 | U4: =+T4+1 -> 4 | V4: =+U4+1 -> 5 | W4: =+V4+1 -> 6 | X4: =+W4+1 -> 7 | Y4: =+X4+1 -> 8 | Z4: =+Y4+1 -> 9 | ... AC4: =+AB4+1 -> 12 | AD4: TOTAL | AF4: 1 | AG4: =+AF4+1 -> 2 | AH4: =+AG4+1 -> 3 | AI4: =+AH4+1 -> 4 | AJ4: =+AI4+1 -> 5 | AK4: =+AJ4+1 -> 6 | AL4: =+AK4+1 -> 7 | AM4: =+AL4+1 -> 8 | AN4: =+AM4+1 -> 9 | ... AQ4: =+AP4+1 -> 12 | AR4: TOTAL | AT4: 1 | AU4: =+AT4+1 -> 2 | AV4: =+AU4+1 -> 3 | AW4: =+AV4+1 -> 4 | AX4: =+AW4+1 -> 5 | AY4: =+AX4+1 -> 6 | AZ4: =+AY4+1 -> 7 | BA4: =+AZ4+1 -> 8 | BB4: =+BA4+1 -> 9 | ... BE4: =+BD4+1 -> 12 | BF4: TOTAL | BH4: 1 | BI4: =+BH4+1 -> 2 | BJ4: =+BI4+1 -> 3 | BK4: =+BJ4+1 -> 4 | BL4: =+BK4+1 -> 5 | BM4: =+BL4+1 -> 6 | BN4: =+BM4+1 -> 7 | BO4: =+BN4+1 -> 8 | BP4: =+BO4+1 -> 9 | ... BS4: =+BR4+1 -> 12 | BT4: TOTAL | BV4: 1 | BW4: =+BV4+1 -> 2 | BX4: =+BW4+1 -> 3 | BY4: =+BX4+1 -> 4 | BZ4: =+BY4+1 -> 5 | CA4: =+BZ4+1 -> 6 | CB4: =+CA4+1 -> 7 | CC4: =+CB4+1 -> 8 | CD4: =+CC4+1 -> 9 | ... CF4: =+CE4+1 -> 11 | CG4: =+CE4+1 -> 11 | CH4: TOTAL
B5: Quarter | D5: Q1 | E5: Q1 | F5: Q1 | G5: Q2 | H5: Q2 | I5: Q2 | J5: Q3 | K5: Q3 | L5: Q3 | M5: Q4 | N5: Q4 | O5: Q4 | R5: Q1 | S5: Q1 | T5: Q1 | U5: Q2 | V5: Q2 | W5: Q2 | X5: Q3 | Y5: Q3 | Z5: Q3 | AA5: Q4 | AB5: Q4 | AC5: Q4 | AF5: Q1 | AG5: Q1 | AH5: Q1 | AI5: Q2 | AJ5: Q2 | AK5: Q2 | AL5: Q3 | AM5: Q3 | AN5: Q3 | AO5: Q4 | AP5: Q4 | AQ5: Q4 | AT5: Q1 | AU5: Q1 | AV5: Q1 | AW5: Q2 | AX5: Q2 | AY5: Q2 | AZ5: Q3 | BA5: Q3 | BB5: Q3 | BC5: Q4 | BD5: Q4 | BE5: Q4 | BH5: Q1 | BI5: Q1 | BJ5: Q1 | BK5: Q2 | BL5: Q2 | BM5: Q2 | BN5: Q3 | BO5: Q3 | BP5: Q3 | BQ5: Q4 | BR5: Q4 | BS5: Q4 | BV5: Q1 | BW5: Q1 | BX5: Q1 | BY5: Q2 | BZ5: Q2 | CA5: Q2 | CB5: Q3 | CC5: Q3 | CD5: Q3 | CE5: Q4 | CF5: Q4 | CG5: Q4
B6: Active Months | D6: =+IF(D4<=MONTH,1,0) -> 1 | E6: =+IF(E4<=MONTH,1,0) -> 1 | F6: =+IF(F4<=MONTH,1,0) -> 1 | G6: =+IF(G4<=MONTH,1,0) -> 1 | H6: =+IF(H4<=MONTH,1,0) -> 1 | I6: =+IF(I4<=MONTH,1,0) -> 1 | J6: =+IF(J4<=MONTH,1,0) -> 1 | K6: =+IF(K4<=MONTH,1,0) -> 1 | ... O6: =+IF(O4<=MONTH,1,0) -> 1 | R6: =+IF(R4<=MONTH,1,0) -> 1 | S6: =+IF(S4<=MONTH,1,0) -> 1 | T6: =+IF(T4<=MONTH,1,0) -> 1 | U6: =+IF(U4<=MONTH,1,0) -> 1 | V6: =+IF(V4<=MONTH,1,0) -> 1 | W6: =+IF(W4<=MONTH,1,0) -> 1 | X6: =+IF(X4<=MONTH,1,0) -> 1 | Y6: =+IF(Y4<=MONTH,1,0) -> 1 | ... AC6: =+IF(AC4<=MONTH,1,0) -> 1 | AF6: =+IF(AF4<=MONTH,1,0) -> 1 | AG6: =+IF(AG4<=MONTH,1,0) -> 1 | AH6: =+IF(AH4<=MONTH,1,0) -> 1 | AI6: =+IF(AI4<=MONTH,1,0) -> 1 | AJ6: =+IF(AJ4<=MONTH,1,0) -> 1 | AK6: =+IF(AK4<=MONTH,1,0) -> 1 | AL6: =+IF(AL4<=MONTH,1,0) -> 1 | AM6: =+IF(AM4<=MONTH,1,0) -> 1 | ... AQ6: =+IF(AQ4<=MONTH,1,0) -> 1 | AT6: =+IF(AT4<=MONTH,1,0) -> 1 | AU6: =+IF(AU4<=MONTH,1,0) -> 1 | AV6: =+IF(AV4<=MONTH,1,0) -> 1 | AW6: =+IF(AW4<=MONTH,1,0) -> 1 | AX6: =+IF(AX4<=MONTH,1,0) -> 1 | AY6: =+IF(AY4<=MONTH,1,0) -> 1 | AZ6: =+IF(AZ4<=MONTH,1,0) -> 1 | BA6: =+IF(BA4<=MONTH,1,0) -> 1 | ... BE6: =+IF(BE4<=MONTH,1,0) -> 1 | BH6: =+IF(BH4<=MONTH,1,0) -> 1 | BI6: =+IF(BI4<=MONTH,1,0) -> 1 | BJ6: =+IF(BJ4<=MONTH,1,0) -> 1 | BK6: =+IF(BK4<=MONTH,1,0) -> 1 | BL6: =+IF(BL4<=MONTH,1,0) -> 1 | BM6: =+IF(BM4<=MONTH,1,0) -> 1 | BN6: =+IF(BN4<=MONTH,1,0) -> 1 | BO6: =+IF(BO4<=MONTH,1,0) -> 1 | ... BS6: =+IF(BS4<=MONTH,1,0) -> 1 | BV6: =+IF(BV4<=MONTH,1,0) -> 1 | BW6: =+IF(BW4<=MONTH,1,0) -> 1 | BX6: =+IF(BX4<=MONTH,1,0) -> 1 | BY6: =+IF(BY4<=MONTH,1,0) -> 1 | BZ6: =+IF(BZ4<=MONTH,1,0) -> 1 | CA6: =+IF(CA4<=MONTH,1,0) -> 1 | CB6: =+IF(CB4<=MONTH,1,0) -> 1 | CC6: =+IF(CC4<=MONTH,1,0) -> 1 | ... CG6: =+IF(CG4<=MONTH,1,0) -> 1
R7: =IND_YEAR_1 -> 0.056 | S7: Inflation | AF7: =IND_YEAR_2 -> 0.051 | AG7: Inflation | AT7: =IND_YEAR_3 -> 0.036 | AU7: Inflation | BH7: =IND_YEAR_4 -> 0.035 | BI7: Inflation | BV7: =IND_YEAR_4 -> 0.035 | BW7: Inflation
B8: =+"Staff "&COMP -> Staff ZHY
D10: =+D2 -> 2025 | E10: =+E2 -> 2025 | F10: =+F2 -> 2025 | G10: =+G2 -> 2025 | H10: =+H2 -> 2025 | I10: =+I2 -> 2025 | J10: =+J2 -> 2025 | K10: =+K2 -> 2025 | ... P10: =+P2 -> 2025 | R10: =+R2 -> 2026 | S10: =+S2 -> 2026 | T10: =+T2 -> 2026 | U10: =+U2 -> 2026 | V10: =+V2 -> 2026 | W10: =+W2 -> 2026 | X10: =+X2 -> 2026 | Y10: =+Y2 -> 2026 | ... AD10: =+AD2 -> 2026 | AF10: =+AF2 -> 2027 | AG10: =+AG2 -> 2027 | AH10: =+AH2 -> 2027 | AI10: =+AI2 -> 2027 | AJ10: =+AJ2 -> 2027 | AK10: =+AK2 -> 2027 | AL10: =+AL2 -> 2027 | AM10: =+AM2 -> 2027 | ... AR10: =+AR2 -> 2027 | AT10: =+AT2 -> 2028 | AU10: =+AU2 -> 2028 | AV10: =+AV2 -> 2028 | AW10: =+AW2 -> 2028 | AX10: =+AX2 -> 2028 | AY10: =+AY2 -> 2028 | AZ10: =+AZ2 -> 2028 | BA10: =+BA2 -> 2028 | ... BF10: =+BF2 -> 2028 | BH10: =+BH2 -> 2029 | BI10: =+BI2 -> 2029 | BJ10: =+BJ2 -> 2029 | BK10: =+BK2 -> 2029 | BL10: =+BL2 -> 2029 | BM10: =+BM2 -> 2029 | BN10: =+BN2 -> 2029 | BO10: =+BO2 -> 2029 | ... BT10: =+BT2 -> 2029 | BV10: =+BV2 -> 2030 | BW10: =+BW2 -> 2030 | BX10: =+BX2 -> 2030 | BY10: =+BY2 -> 2030 | BZ10: =+BZ2 -> 2030 | CA10: =+CA2 -> 2030 | CB10: =+CB2 -> 2030 | CC10: =+CC2 -> 2030 | ... CH10: =+CH2 -> 2030
D11: Jan | E11: Feb | F11: March | G11: April | H11: May | I11: June | J11: July | K11: Aug | L11: Sept | M11: Oct | N11: Nov | O11: Dec | P11: TOTAL | R11: Jan | S11: Feb | T11: March | U11: April | V11: May | W11: June | X11: July | Y11: Aug | Z11: Sept | AA11: Oct | AB11: Nov | AC11: Dec | AD11: TOTAL | AF11: Jan | AG11: Feb | AH11: March | AI11: April | AJ11: May | AK11: June | AL11: July | AM11: Aug | AN11: Sept | AO11: Oct | AP11: Nov | AQ11: Dec | AR11: TOTAL | AT11: Jan | AU11: Feb | AV11: March | AW11: April | AX11: May | AY11: June | AZ11: July | BA11: Aug | BB11: Sept | BC11: Oct | BD11: Nov | BE11: Dec | BF11: TOTAL | BH11: Jan | BI11: Feb | BJ11: March | BK11: April | BL11: May | BM11: June | BN11: July | BO11: Aug | BP11: Sept | BQ11: Oct | BR11: Nov | BS11: Dec | BT11: TOTAL | BV11: Jan | BW11: Feb | BX11: March | BY11: April | BZ11: May | CA11: June | CB11: July | CC11: Aug | CD11: Sept | CE11: Oct | CF11: Nov | CG11: Dec | CH11: TOTAL
B12: Managing Director | C12: P1 | D12: 0 | E12: 0 | F12: 0 | G12: 0 | H12: 0 | I12: 0 | J12: =' Staff'!L16*-1 -> -4922.064 | K12: =' Staff'!M16*-1 -> -4922.064 | L12: =' Staff'!N16*-1 -> -4922.064 | M12: =' Staff'!O16*-1 -> -4922.064 | N12: =' Staff'!P16*-1 -> -7383.096 | O12: =' Staff'!Q16*-1 -> -7383.096 | P12: =SUM(D12:O12) -> -34454.448 | R12: =J12*(1+$R$7) -> -5197.6996 | S12: =R12 -> -5197.6996 | T12: =S12 -> -5197.6996 | U12: =T12 -> -5197.6996 | V12: =U12 -> -5197.6996 | W12: =V12 -> -5197.6996 | X12: =J12*(1+$R$7) -> -5197.6996 | Y12: =K12*(1+$R$7) -> -5197.6996 | Z12: =L12*(1+$R$7) -> -5197.6996 | AA12: =M12*(1+$R$7) -> -5197.6996 | AB12: =N12*(1+$R$7) -> -7796.5494 | AC12: =O12*(1+$R$7) -> -7796.5494 | AD12: =SUM(R12:AC12) -> -67570.095 | AF12: =R12*(1+$AF$7) -> -5462.7823 | AG12: =S12*(1+$AF$7) -> -5462.7823 | AH12: =T12*(1+$AF$7) -> -5462.7823 | AI12: =U12*(1+$AF$7) -> -5462.7823 | AJ12: =V12*(1+$AF$7) -> -5462.7823 | AK12: =W12*(1+$AF$7) -> -5462.7823 | AL12: =X12*(1+$AF$7) -> -5462.7823 | AM12: =Y12*(1+$AF$7) -> -5462.7823 | ... AQ12: =AC12*(1+$AF$7) -> -8194.1734 | AR12: =SUM(AF12:AQ12) -> -71016.169 | AT12: =AF12*(1+$AF$7) -> -5741.3842 | AU12: =AG12*(1+$AF$7) -> -5741.3842 | AV12: =AH12*(1+$AF$7) -> -5741.3842 | AW12: =AI12*(1+$AF$7) -> -5741.3842 | AX12: =AJ12*(1+$AF$7) -> -5741.3842 | AY12: =AK12*(1+$AF$7) -> -5741.3842 | AZ12: =AL12*(1+$AF$7) -> -5741.3842 | BA12: =AM12*(1+$AF$7) -> -5741.3842 | ... BE12: =AQ12*(1+$AF$7) -> -8612.0762 | BF12: =SUM(AT12:BE12) -> -74637.994 | BH12: =AT12*(1+$AF$7) -> -6034.1947 | BI12: =AU12*(1+$AF$7) -> -6034.1947 | BJ12: =AV12*(1+$AF$7) -> -6034.1947 | BK12: =AW12*(1+$AF$7) -> -6034.1947 | BL12: =AX12*(1+$AF$7) -> -6034.1947 | BM12: =AY12*(1+$AF$7) -> -6034.1947 | BN12: =AZ12*(1+$AF$7) -> -6034.1947 | BO12: =BA12*(1+$AF$7) -> -6034.1947 | ... BS12: =BE12*(1+$AF$7) -> -9051.2921 | BT12: =SUM(BH12:BS12) -> -78444.532 | BV12: =BH12*(1+$AF$7) -> -6341.9387 | BW12: =BI12*(1+$AF$7) -> -6341.9387 | BX12: =BJ12*(1+$AF$7) -> -6341.9387 | BY12: =BK12*(1+$AF$7) -> -6341.9387 | BZ12: =BL12*(1+$AF$7) -> -6341.9387 | CA12: =BM12*(1+$AF$7) -> -6341.9387 | CB12: =BN12*(1+$AF$7) -> -6341.9387 | CC12: =BO12*(1+$AF$7) -> -6341.9387 | ... CG12: =BS12*(1+$AF$7) -> -9512.908 | CH12: =SUM(BV12:CG12) -> -82445.203
B13: Office Manager | C13: P2 | D13: 0 | E13: 0 | F13: 0 | G13: 0 | H13: 0 | I13: 0 | J13: =' Staff'!L31*-1 -> -2250.0864 | K13: =' Staff'!M31*-1 -> -2250.0864 | L13: =' Staff'!N31*-1 -> -2250.0864 | M13: =' Staff'!O31*-1 -> -2250.0864 | N13: =' Staff'!P31*-1 -> -3375.1296 | O13: =' Staff'!Q31*-1 -> -3375.1296 | P13: =SUM(D13:O13) -> -15750.605 | R13: =J13*(1+$R$7) -> -2376.0912 | S13: =R13 -> -2376.0912 | T13: =S13 -> -2376.0912 | U13: =T13 -> -2376.0912 | V13: =U13 -> -2376.0912 | W13: =V13 -> -2376.0912 | X13: =J13*(1+$R$7) -> -2376.0912 | Y13: =K13*(1+$R$7) -> -2376.0912 | Z13: =L13*(1+$R$7) -> -2376.0912 | AA13: =M13*(1+$R$7) -> -2376.0912 | AB13: =N13*(1+$R$7) -> -3564.1369 | AC13: =O13*(1+$R$7) -> -3564.1369 | AD13: =SUM(R13:AC13) -> -30889.186 | AF13: =R13*(1+$AF$7) -> -2497.2719 | AG13: =S13*(1+$AF$7) -> -2497.2719 | AH13: =T13*(1+$AF$7) -> -2497.2719 | AI13: =U13*(1+$AF$7) -> -2497.2719 | AJ13: =V13*(1+$AF$7) -> -2497.2719 | AK13: =W13*(1+$AF$7) -> -2497.2719 | AL13: =X13*(1+$AF$7) -> -2497.2719 | AM13: =Y13*(1+$AF$7) -> -2497.2719 | ... AQ13: =AC13*(1+$AF$7) -> -3745.9078 | AR13: =SUM(AF13:AQ13) -> -32464.535 | AT13: =AF13*(1+$AF$7) -> -2624.6328 | AU13: =AG13*(1+$AF$7) -> -2624.6328 | AV13: =AH13*(1+$AF$7) -> -2624.6328 | AW13: =AI13*(1+$AF$7) -> -2624.6328 | AX13: =AJ13*(1+$AF$7) -> -2624.6328 | AY13: =AK13*(1+$AF$7) -> -2624.6328 | AZ13: =AL13*(1+$AF$7) -> -2624.6328 | BA13: =AM13*(1+$AF$7) -> -2624.6328 | ... BE13: =AQ13*(1+$AF$7) -> -3936.9491 | BF13: =SUM(AT13:BE13) -> -34120.226 | BH13: =AT13*(1+$AF$7) -> -2758.489 | BI13: =AU13*(1+$AF$7) -> -2758.489 | BJ13: =AV13*(1+$AF$7) -> -2758.489 | BK13: =AW13*(1+$AF$7) -> -2758.489 | BL13: =AX13*(1+$AF$7) -> -2758.489 | BM13: =AY13*(1+$AF$7) -> -2758.489 | BN13: =AZ13*(1+$AF$7) -> -2758.489 | BO13: =BA13*(1+$AF$7) -> -2758.489 | ... BS13: =BE13*(1+$AF$7) -> -4137.7335 | BT13: =SUM(BH13:BS13) -> -35860.357 | BV13: =BH13*(1+$AF$7) -> -2899.172 | BW13: =BI13*(1+$AF$7) -> -2899.172 | BX13: =BJ13*(1+$AF$7) -> -2899.172 | BY13: =BK13*(1+$AF$7) -> -2899.172 | BZ13: =BL13*(1+$AF$7) -> -2899.172 | CA13: =BM13*(1+$AF$7) -> -2899.172 | CB13: =BN13*(1+$AF$7) -> -2899.172 | CC13: =BO13*(1+$AF$7) -> -2899.172 | ... CG13: =BS13*(1+$AF$7) -> -4348.758 | CH13: =SUM(BV13:CG13) -> -37689.236
B14: IT | C14: P3 | D14: 0 | E14: 0 | F14: 0 | G14: 0 | H14: 0 | I14: 0 | J14: =' Staff'!L46*-1 -> -914.0976 | K14: =' Staff'!M46*-1 -> -914.0976 | L14: =' Staff'!N46*-1 -> -914.0976 | M14: =' Staff'!O46*-1 -> -914.0976 | N14: =' Staff'!P46*-1 -> -1371.1464 | O14: =' Staff'!Q46*-1 -> -1371.1464 | P14: =SUM(D14:O14) -> -6398.6832 | R14: =J14*(1+$R$7) -> -965.28707 | S14: =R14 -> -965.28707 | T14: =S14 -> -965.28707 | U14: =T14 -> -965.28707 | V14: =U14 -> -965.28707 | W14: =V14 -> -965.28707 | X14: =J14*(1+$R$7) -> -965.28707 | Y14: =K14*(1+$R$7) -> -965.28707 | Z14: =L14*(1+$R$7) -> -965.28707 | AA14: =M14*(1+$R$7) -> -965.28707 | AB14: =N14*(1+$R$7) -> -1447.9306 | AC14: =O14*(1+$R$7) -> -1447.9306 | AD14: =SUM(R14:AC14) -> -12548.732 | AF14: =R14*(1+$AF$7) -> -1014.5167 | AG14: =S14*(1+$AF$7) -> -1014.5167 | AH14: =T14*(1+$AF$7) -> -1014.5167 | AI14: =U14*(1+$AF$7) -> -1014.5167 | AJ14: =V14*(1+$AF$7) -> -1014.5167 | AK14: =W14*(1+$AF$7) -> -1014.5167 | AL14: =X14*(1+$AF$7) -> -1014.5167 | AM14: =Y14*(1+$AF$7) -> -1014.5167 | ... AQ14: =AC14*(1+$AF$7) -> -1521.7751 | AR14: =SUM(AF14:AQ14) -> -13188.717 | AT14: =AF14*(1+$AF$7) -> -1066.2571 | AU14: =AG14*(1+$AF$7) -> -1066.2571 | AV14: =AH14*(1+$AF$7) -> -1066.2571 | AW14: =AI14*(1+$AF$7) -> -1066.2571 | AX14: =AJ14*(1+$AF$7) -> -1066.2571 | AY14: =AK14*(1+$AF$7) -> -1066.2571 | AZ14: =AL14*(1+$AF$7) -> -1066.2571 | BA14: =AM14*(1+$AF$7) -> -1066.2571 | ... BE14: =AQ14*(1+$AF$7) -> -1599.3856 | BF14: =SUM(AT14:BE14) -> -13861.342 | BH14: =AT14*(1+$AF$7) -> -1120.6362 | BI14: =AU14*(1+$AF$7) -> -1120.6362 | BJ14: =AV14*(1+$AF$7) -> -1120.6362 | BK14: =AW14*(1+$AF$7) -> -1120.6362 | BL14: =AX14*(1+$AF$7) -> -1120.6362 | BM14: =AY14*(1+$AF$7) -> -1120.6362 | BN14: =AZ14*(1+$AF$7) -> -1120.6362 | BO14: =BA14*(1+$AF$7) -> -1120.6362 | ... BS14: =BE14*(1+$AF$7) -> -1680.9543 | BT14: =SUM(BH14:BS14) -> -14568.27 | BV14: =BH14*(1+$AF$7) -> -1177.7886 | BW14: =BI14*(1+$AF$7) -> -1177.7886 | BX14: =BJ14*(1+$AF$7) -> -1177.7886 | BY14: =BK14*(1+$AF$7) -> -1177.7886 | BZ14: =BL14*(1+$AF$7) -> -1177.7886 | CA14: =BM14*(1+$AF$7) -> -1177.7886 | CB14: =BN14*(1+$AF$7) -> -1177.7886 | CC14: =BO14*(1+$AF$7) -> -1177.7886 | ... CG14: =BS14*(1+$AF$7) -> -1766.6829 | CH14: =SUM(BV14:CG14) -> -15311.252
B16: Production - Packaging | C16: P4 | D16: 0 | E16: 0 | F16: 0 | G16: 0 | H16: 0 | I16: 0 | J16: =' Staff'!L61*-1 -> -815.65632 | K16: =' Staff'!M61*-1 -> -815.65632 | L16: =' Staff'!N61*-1 -> -815.65632 | M16: =' Staff'!O61*-1 -> -815.65632 | N16: =' Staff'!P61*-1 -> -1223.4845 | O16: =' Staff'!Q61*-1 -> -1223.4845 | P16: =SUM(D16:O16) -> -5709.5942 | R16: =J16*(1+$R$7) -> -861.33307 | S16: =R16 -> -861.33307 | T16: =S16 -> -861.33307 | U16: =T16 -> -861.33307 | V16: =U16 -> -861.33307 | W16: =V16 -> -861.33307 | X16: =J16*(1+$R$7) -> -861.33307 | Y16: =K16*(1+$R$7) -> -861.33307 | Z16: =L16*(1+$R$7) -> -861.33307 | AA16: =M16*(1+$R$7) -> -861.33307 | AB16: =N16*(1+$R$7) -> -1291.9996 | AC16: =O16*(1+$R$7) -> -1291.9996 | AD16: =SUM(R16:AC16) -> -11197.33 | AF16: =R16*(1+$AF$7) -> -905.26106 | AG16: =S16*(1+$AF$7) -> -905.26106 | AH16: =T16*(1+$AF$7) -> -905.26106 | AI16: =U16*(1+$AF$7) -> -905.26106 | AJ16: =V16*(1+$AF$7) -> -905.26106 | AK16: =W16*(1+$AF$7) -> -905.26106 | AL16: =X16*(1+$AF$7) -> -905.26106 | AM16: =Y16*(1+$AF$7) -> -905.26106 | ... AQ16: =AC16*(1+$AF$7) -> -1357.8916 | AR16: =SUM(AF16:AQ16) -> -11768.394 | AT16: =AF16*(1+$AF$7) -> -951.42937 | AU16: =AG16*(1+$AF$7) -> -951.42937 | AV16: =AH16*(1+$AF$7) -> -951.42937 | AW16: =AI16*(1+$AF$7) -> -951.42937 | AX16: =AJ16*(1+$AF$7) -> -951.42937 | AY16: =AK16*(1+$AF$7) -> -951.42937 | AZ16: =AL16*(1+$AF$7) -> -951.42937 | BA16: =AM16*(1+$AF$7) -> -951.42937 | ... BE16: =AQ16*(1+$AF$7) -> -1427.1441 | BF16: =SUM(AT16:BE16) -> -12368.582 | BH16: =AT16*(1+$AF$7) -> -999.95227 | BI16: =AU16*(1+$AF$7) -> -999.95227 | BJ16: =AV16*(1+$AF$7) -> -999.95227 | BK16: =AW16*(1+$AF$7) -> -999.95227 | BL16: =AX16*(1+$AF$7) -> -999.95227 | BM16: =AY16*(1+$AF$7) -> -999.95227 | BN16: =AZ16*(1+$AF$7) -> -999.95227 | BO16: =BA16*(1+$AF$7) -> -999.95227 | ... BS16: =BE16*(1+$AF$7) -> -1499.9284 | BT16: =SUM(BH16:BS16) -> -12999.38 | BV16: =BH16*(1+$AF$7) -> -1050.9498 | BW16: =BI16*(1+$AF$7) -> -1050.9498 | BX16: =BJ16*(1+$AF$7) -> -1050.9498 | BY16: =BK16*(1+$AF$7) -> -1050.9498 | BZ16: =BL16*(1+$AF$7) -> -1050.9498 | CA16: =BM16*(1+$AF$7) -> -1050.9498 | CB16: =BN16*(1+$AF$7) -> -1050.9498 | CC16: =BO16*(1+$AF$7) -> -1050.9498 | ... CG16: =BS16*(1+$AF$7) -> -1576.4248 | CH16: =SUM(BV16:CG16) -> -13662.348
B17: Production - Packaging | C17: P4 | D17: 0 | E17: 0 | F17: 0 | G17: 0 | H17: 0 | I17: 0 | J17: =' Staff'!L61*-1 -> -815.65632 | K17: =' Staff'!M61*-1 -> -815.65632 | L17: =' Staff'!N61*-1 -> -815.65632 | M17: =' Staff'!O61*-1 -> -815.65632 | N17: =' Staff'!P61*-1 -> -1223.4845 | O17: =' Staff'!Q61*-1 -> -1223.4845 | P17: =SUM(D17:O17) -> -5709.5942 | R17: =J17*(1+$R$7) -> -861.33307 | S17: =R17 -> -861.33307 | T17: =S17 -> -861.33307 | U17: =T17 -> -861.33307 | V17: =U17 -> -861.33307 | W17: =V17 -> -861.33307 | X17: =J17*(1+$R$7) -> -861.33307 | Y17: =K17*(1+$R$7) -> -861.33307 | Z17: =L17*(1+$R$7) -> -861.33307 | AA17: =M17*(1+$R$7) -> -861.33307 | AB17: =N17*(1+$R$7) -> -1291.9996 | AC17: =O17*(1+$R$7) -> -1291.9996 | AD17: =SUM(R17:AC17) -> -11197.33 | AF17: =R17*(1+$AF$7) -> -905.26106 | AG17: =S17*(1+$AF$7) -> -905.26106 | AH17: =T17*(1+$AF$7) -> -905.26106 | AI17: =U17*(1+$AF$7) -> -905.26106 | AJ17: =V17*(1+$AF$7) -> -905.26106 | AK17: =W17*(1+$AF$7) -> -905.26106 | AL17: =X17*(1+$AF$7) -> -905.26106 | AM17: =Y17*(1+$AF$7) -> -905.26106 | ... AQ17: =AC17*(1+$AF$7) -> -1357.8916 | AR17: =SUM(AF17:AQ17) -> -11768.394 | AT17: =AF17*(1+$AF$7) -> -951.42937 | AU17: =AG17*(1+$AF$7) -> -951.42937 | AV17: =AH17*(1+$AF$7) -> -951.42937 | AW17: =AI17*(1+$AF$7) -> -951.42937 | AX17: =AJ17*(1+$AF$7) -> -951.42937 | AY17: =AK17*(1+$AF$7) -> -951.42937 | AZ17: =AL17*(1+$AF$7) -> -951.42937 | BA17: =AM17*(1+$AF$7) -> -951.42937 | ... BE17: =AQ17*(1+$AF$7) -> -1427.1441 | BF17: =SUM(AT17:BE17) -> -12368.582 | BG17: =SUM(AT17:BE17) -> -12368.582 | BH17: =AT17*(1+$AF$7) -> -999.95227 | BI17: =AU17*(1+$AF$7) -> -999.95227 | BJ17: =AV17*(1+$AF$7) -> -999.95227 | BK17: =AW17*(1+$AF$7) -> -999.95227 | BL17: =AX17*(1+$AF$7) -> -999.95227 | BM17: =AY17*(1+$AF$7) -> -999.95227 | BN17: =AZ17*(1+$AF$7) -> -999.95227 | BO17: =BA17*(1+$AF$7) -> -999.95227 | ... BS17: =BE17*(1+$AF$7) -> -1499.9284 | BT17: =SUM(BH17:BS17) -> -12999.38 | BV17: =BH17*(1+$AF$7) -> -1050.9498 | BW17: =BI17*(1+$AF$7) -> -1050.9498 | BX17: =BJ17*(1+$AF$7) -> -1050.9498 | BY17: =BK17*(1+$AF$7) -> -1050.9498 | BZ17: =BL17*(1+$AF$7) -> -1050.9498 | CA17: =BM17*(1+$AF$7) -> -1050.9498 | CB17: =BN17*(1+$AF$7) -> -1050.9498 | CC17: =BO17*(1+$AF$7) -> -1050.9498 | ... CG17: =BS17*(1+$AF$7) -> -1576.4248 | CH17: =SUM(BV17:CG17) -> -13662.348
B18: Assistant | C18: P5 | D18: 0 | E18: 0 | F18: 0 | G18: 0 | H18: 0 | I18: 0 | J18: =' Staff'!L76*-1 -> -893.00304 | K18: =' Staff'!M76*-1 -> -893.00304 | L18: =' Staff'!N76*-1 -> -893.00304 | M18: =' Staff'!O76*-1 -> -893.00304 | N18: =' Staff'!P76*-1 -> -1339.5046 | O18: =' Staff'!Q76*-1 -> -1339.5046 | P18: =SUM(D18:O18) -> -6251.0213 | R18: =J18*(1+$R$7) -> -943.01121 | S18: =R18 -> -943.01121 | T18: =S18 -> -943.01121 | U18: =T18 -> -943.01121 | V18: =U18 -> -943.01121 | W18: =V18 -> -943.01121 | X18: =J18*(1+$R$7) -> -943.01121 | Y18: =K18*(1+$R$7) -> -943.01121 | Z18: =L18*(1+$R$7) -> -943.01121 | AA18: =M18*(1+$R$7) -> -943.01121 | AB18: =N18*(1+$R$7) -> -1414.5168 | AC18: =O18*(1+$R$7) -> -1414.5168 | AD18: =SUM(R18:AC18) -> -12259.146 | AF18: =R18*(1+$AF$7) -> -991.10478 | AG18: =S18*(1+$AF$7) -> -991.10478 | AH18: =T18*(1+$AF$7) -> -991.10478 | AI18: =U18*(1+$AF$7) -> -991.10478 | AJ18: =V18*(1+$AF$7) -> -991.10478 | AK18: =W18*(1+$AF$7) -> -991.10478 | AL18: =X18*(1+$AF$7) -> -991.10478 | AM18: =Y18*(1+$AF$7) -> -991.10478 | ... AQ18: =AC18*(1+$AF$7) -> -1486.6572 | AR18: =SUM(AF18:AQ18) -> -12884.362 | AT18: =AF18*(1+$AF$7) -> -1041.6511 | AU18: =AG18*(1+$AF$7) -> -1041.6511 | AV18: =AH18*(1+$AF$7) -> -1041.6511 | AW18: =AI18*(1+$AF$7) -> -1041.6511 | AX18: =AJ18*(1+$AF$7) -> -1041.6511 | AY18: =AK18*(1+$AF$7) -> -1041.6511 | AZ18: =AL18*(1+$AF$7) -> -1041.6511 | BA18: =AM18*(1+$AF$7) -> -1041.6511 | ... BE18: =AQ18*(1+$AF$7) -> -1562.4767 | BF18: =SUM(AT18:BE18) -> -13541.465 | BG18: =SUM(AT18:BE18) -> -13541.465 | BH18: =AT18*(1+$AF$7) -> -1094.7753 | BI18: =AU18*(1+$AF$7) -> -1094.7753 | BJ18: =AV18*(1+$AF$7) -> -1094.7753 | BK18: =AW18*(1+$AF$7) -> -1094.7753 | BL18: =AX18*(1+$AF$7) -> -1094.7753 | BM18: =AY18*(1+$AF$7) -> -1094.7753 | BN18: =AZ18*(1+$AF$7) -> -1094.7753 | BO18: =BA18*(1+$AF$7) -> -1094.7753 | ... BS18: =BE18*(1+$AF$7) -> -1642.163 | BT18: =SUM(BH18:BS18) -> -14232.079 | BV18: =BH18*(1+$AF$7) -> -1150.6089 | BW18: =BI18*(1+$AF$7) -> -1150.6089 | BX18: =BJ18*(1+$AF$7) -> -1150.6089 | BY18: =BK18*(1+$AF$7) -> -1150.6089 | BZ18: =BL18*(1+$AF$7) -> -1150.6089 | CA18: =BM18*(1+$AF$7) -> -1150.6089 | CB18: =BN18*(1+$AF$7) -> -1150.6089 | CC18: =BO18*(1+$AF$7) -> -1150.6089 | ... CG18: =BS18*(1+$AF$7) -> -1725.9133 | CH18: =SUM(BV18:CG18) -> -14957.915
B19: =' Staff'!C78 -> Order - Distribution | C19: =' Staff'!B78 -> P6 | D19: 0 | E19: 0 | F19: 0 | G19: 0 | H19: 0 | I19: 0 | J19: 0 | K19: =' Staff'!M91*-1 -> -893.00304 | L19: =' Staff'!N91*-1 -> -893.00304 | M19: =' Staff'!O91*-1 -> -893.00304 | N19: =' Staff'!P91*-1 -> -1339.5046 | O19: =' Staff'!Q91*-1 -> -1339.5046 | P19: =SUM(D19:O19) -> -5358.0182 | AD19: =SUM(R19:AC19) -> 0
B20: =' Staff'!C93 -> Security | C20: P7 | D20: 0 | E20: 0 | F20: 0 | G20: 0 | H20: 0 | I20: 0 | J20: 0 | K20: 0 | L20: =' Staff'!N106*-1 -> -893.00304 | M20: =' Staff'!O106*-1 -> -893.00304 | N20: =' Staff'!P106*-1 -> -1339.5046 | O20: =' Staff'!Q106*-1 -> -1339.5046 | P20: =SUM(D20:O20) -> -4465.0152 | R20: =' Staff'!F106*-1 -> -893.00304 | S20: =' Staff'!G106*-1 -> -893.00304 | T20: =' Staff'!H106*-1 -> -893.00304 | U20: =' Staff'!I106*-1 -> -893.00304 | V20: =' Staff'!J106*-1 -> -893.00304 | W20: =' Staff'!K106*-1 -> -893.00304 | X20: =' Staff'!L106*-1 -> -893.00304 | Y20: =' Staff'!M106*-1 -> -893.00304 | ... AC20: =' Staff'!Q106*-1 -> -1339.5046 | AD20: =SUM(R20:AC20) -> -11609.04
B21: Production - Packaging | C21: P4 | D21: 0 | E21: 0 | F21: 0 | G21: 0 | H21: 0 | I21: 0 | J21: 0 | K21: 0 | L21: 0 | M21: 0 | N21: 0 | O21: 0 | R21: 0 | S21: 0 | T21: 0 | U21: 0 | V21: 0 | W21: 0 | X21: =X16 -> -861.33307 | Y21: =Y16 -> -861.33307 | Z21: =Z16 -> -861.33307 | AA21: =AA16 -> -861.33307 | AB21: =AB16 -> -1291.9996 | AC21: =AC16 -> -1291.9996 | AD21: =SUM(R21:AC21) -> -6029.3315
B22: Production - Packaging | C22: P4 | X22: =X21 -> -861.33307 | Y22: =Y21 -> -861.33307 | Z22: =Z21 -> -861.33307 | AA22: =AA21 -> -861.33307 | AB22: =AB21 -> -1291.9996 | AC22: =AC21 -> -1291.9996 | AD22: =SUM(R22:AC22) -> -6029.3315
B23: Assistant | C23: P5 | AF23: =' Staff'!F76*-1 -> -893.00304 | AG23: =' Staff'!G76*-1 -> -893.00304 | AH23: =' Staff'!H76*-1 -> -893.00304 | AI23: =' Staff'!I76*-1 -> -893.00304 | AJ23: =' Staff'!J76*-1 -> -893.00304 | AK23: =' Staff'!K76*-1 -> -893.00304 | AL23: =' Staff'!L76*-1 -> -893.00304 | AM23: =' Staff'!M76*-1 -> -893.00304 | ... AQ23: =' Staff'!Q76*-1 -> -1339.5046

Sheet  Staff
B3: P1 | C3: Managing Director | E3: per months | F3: Jan | G3: Feb | H3: March | I3: April | J3: May | K3: June | L3: July | M3: August | N3: Sept | O3: Oct | P3: Nov | Q3: Dec
C4: monthly payment | E4: 3500 | F4: =$E$4 -> 3500 | G4: =$E$4 -> 3500 | H4: =$E$4 -> 3500 | I4: =$E$4 -> 3500 | J4: =$E$4 -> 3500 | K4: =$E$4 -> 3500 | L4: =$E$4 -> 3500 | M4: =$E$4 -> 3500 | ... Q4: =$E$4 -> 3500
C5: 13th months | E5: =E4 -> 3500 | P5: =E5*0.5 -> 1750 | Q5: =E5*0.5 -> 1750
C6: Vacation Bonus | D6: 0.028 | F6: =(F4+F5)*$D$6 -> 98 | G6: =(G4+G5)*$D$6 -> 98 | H6: =(H4+H5)*$D$6 -> 98 | I6: =(I4+I5)*$D$6 -> 98 | J6: =(J4+J5)*$D$6 -> 98 | K6: =(K4+K5)*$D$6 -> 98 | L6: =(L4+L5)*$D$6 -> 98 | M6: =(M4+M5)*$D$6 -> 98 | ... Q6: =(Q4+Q5)*$D$6 -> 147
C7: total Brutto Income | F7: =SUM(F4:F6) -> 3598 | G7: =SUM(G4:G6) -> 3598 | H7: =SUM(H4:H6) -> 3598 | I7: =SUM(I4:I6) -> 3598 | J7: =SUM(J4:J6) -> 3598 | K7: =SUM(K4:K6) -> 3598 | L7: =SUM(L4:L6) -> 3598 | M7: =SUM(M4:M6) -> 3598 | ... Q7: =SUM(Q4:Q6) -> 5397
C9: additional payment
C10: Public Pension Fund (INSS) | D10: 0.2 | F10: =F7*$D$10 -> 719.6 | G10: =G7*$D$10 -> 719.6 | H10: =H7*$D$10 -> 719.6 | I10: =I7*$D$10 -> 719.6 | J10: =J7*$D$10 -> 719.6 | K10: =K7*$D$10 -> 719.6 | L10: =L7*$D$10 -> 719.6 | M10: =M7*$D$10 -> 719.6 | ... Q10: =Q7*$D$10 -> 1079.4
C11: Severance Fund (FGTS) | D11: 0.08 | F11: =F7*$D$11 -> 287.84 | G11: =G7*$D$11 -> 287.84 | H11: =H7*$D$11 -> 287.84 | I11: =I7*$D$11 -> 287.84 | J11: =J7*$D$11 -> 287.84 | K11: =K7*$D$11 -> 287.84 | L11: =L7*$D$11 -> 287.84 | M11: =M7*$D$11 -> 287.84 | ... Q11: =Q7*$D$11 -> 431.76
C12: Education contribution, INCRA, SENAI, SESI and SEBRAE contributions | D12: 0.058 | F12: =F7*$D$12 -> 208.684 | G12: =G7*$D$12 -> 208.684 | H12: =H7*$D$12 -> 208.684 | I12: =I7*$D$12 -> 208.684 | J12: =J7*$D$12 -> 208.684 | K12: =K7*$D$12 -> 208.684 | L12: =L7*$D$12 -> 208.684 | M12: =M7*$D$12 -> 208.684 | ... Q12: =Q7*$D$12 -> 313.026
C13: Accident Insurance | D13: 0.03 | F13: =F7*$D$13 -> 107.94 | G13: =G7*$D$13 -> 107.94 | H13: =H7*$D$13 -> 107.94 | I13: =I7*$D$13 -> 107.94 | J13: =J7*$D$13 -> 107.94 | K13: =K7*$D$13 -> 107.94 | L13: =L7*$D$13 -> 107.94 | M13: =M7*$D$13 -> 107.94 | ... Q13: =Q7*$D$13 -> 161.91
D14: =SUM(D10:D13) -> 0.368 | F14: =SUM(F10:F13) -> 1324.064 | G14: =SUM(G10:G13) -> 1324.064 | H14: =SUM(H10:H13) -> 1324.064 | I14: =SUM(I10:I13) -> 1324.064 | J14: =SUM(J10:J13) -> 1324.064 | K14: =SUM(K10:K13) -> 1324.064 | L14: =SUM(L10:L13) -> 1324.064 | M14: =SUM(M10:M13) -> 1324.064 | ... Q14: =SUM(Q10:Q13) -> 1986.096
C16: total costs for employer | F16: =F7+F14 -> 4922.064 | G16: =G7+G14 -> 4922.064 | H16: =H7+H14 -> 4922.064 | I16: =I7+I14 -> 4922.064 | J16: =J7+J14 -> 4922.064 | K16: =K7+K14 -> 4922.064 | L16: =L7+L14 -> 4922.064 | M16: =M7+M14 -> 4922.064 | ... Q16: =Q7+Q14 -> 7383.096
B18: P2 | C18: Office Manager | E18: per months | F18: Jan | G18: Feb | H18: March | I18: April | J18: May | K18: June | L18: July | M18: August | N18: Sept | O18: Oct | P18: Nov | Q18: Dec
C19: monthly payment | E19: 1600 | F19: =$E$19 -> 1600 | G19: =$E$19 -> 1600 | H19: =$E$19 -> 1600 | I19: =$E$19 -> 1600 | J19: =$E$19 -> 1600 | K19: =$E$19 -> 1600 | L19: =$E$19 -> 1600 | M19: =$E$19 -> 1600 | ... Q19: =$E$19 -> 1600
C20: 13th months | E20: 1600 | P20: =E20*0.5 -> 800 | Q20: =E20*0.5 -> 800
C21: Vacation Bonus | D21: 0.028 | F21: =(F19+F20)*$D$21 -> 44.8 | G21: =(G19+G20)*$D$21 -> 44.8 | H21: =(H19+H20)*$D$21 -> 44.8 | I21: =(I19+I20)*$D$21 -> 44.8 | J21: =(J19+J20)*$D$21 -> 44.8 | K21: =(K19+K20)*$D$21 -> 44.8 | L21: =(L19+L20)*$D$21 -> 44.8 | M21: =(M19+M20)*$D$21 -> 44.8 | ... Q21: =(Q19+Q20)*$D$21 -> 67.2
C22: total Brutto Income | F22: =SUM(F19:F21) -> 1644.8 | G22: =SUM(G19:G21) -> 1644.8 | H22: =SUM(H19:H21) -> 1644.8 | I22: =SUM(I19:I21) -> 1644.8 | J22: =SUM(J19:J21) -> 1644.8 | K22: =SUM(K19:K21) -> 1644.8 | L22: =SUM(L19:L21) -> 1644.8 | M22: =SUM(M19:M21) -> 1644.8 | ... Q22: =SUM(Q19:Q21) -> 2467.2
C24: additional payment
C25: Public Pension Fund (INSS) | D25: 0.2 | F25: =F22*$D$25 -> 328.96 | G25: =G22*$D$25 -> 328.96 | H25: =H22*$D$25 -> 328.96 | I25: =I22*$D$25 -> 328.96 | J25: =J22*$D$25 -> 328.96 | K25: =K22*$D$25 -> 328.96 | L25: =L22*$D$25 -> 328.96 | M25: =M22*$D$25 -> 328.96 | ... Q25: =Q22*$D$25 -> 493.44
C26: Severance Fund (FGTS) | D26: 0.08 | F26: =F22*$D$26 -> 131.584 | G26: =G22*$D$26 -> 131.584 | H26: =H22*$D$26 -> 131.584 | I26: =I22*$D$26 -> 131.584 | J26: =J22*$D$26 -> 131.584 | K26: =K22*$D$26 -> 131.584 | L26: =L22*$D$26 -> 131.584 | M26: =M22*$D$26 -> 131.584 | ... Q26: =Q22*$D$26 -> 197.376
C27: Education contribution, INCRA, SENAI, SESI and SEBRAE contributions | D27: 0.058 | F27: =F22*$D$27 -> 95.3984 | G27: =G22*$D$27 -> 95.3984 | H27: =H22*$D$27 -> 95.3984 | I27: =I22*$D$27 -> 95.3984 | J27: =J22*$D$27 -> 95.3984 | K27: =K22*$D$27 -> 95.3984 | L27: =L22*$D$27 -> 95.3984 | M27: =M22*$D$27 -> 95.3984 | ... Q27: =Q22*$D$27 -> 143.0976
C28: Accident Insurance | D28: 0.03 | F28: =F22*$D$28 -> 49.344 | G28: =G22*$D$28 -> 49.344 | H28: =H22*$D$28 -> 49.344 | I28: =I22*$D$28 -> 49.344 | J28: =J22*$D$28 -> 49.344 | K28: =K22*$D$28 -> 49.344 | L28: =L22*$D$28 -> 49.344 | M28: =M22*$D$28 -> 49.344 | ... Q28: =Q22*$D$28 -> 74.016
D29: =SUM(D25:D28) -> 0.368 | F29: =SUM(F25:F28) -> 605.2864 | G29: =SUM(G25:G28) -> 605.2864 | H29: =SUM(H25:H28) -> 605.2864 | I29: =SUM(I25:I28) -> 605.2864 | J29: =SUM(J25:J28) -> 605.2864 | K29: =SUM(K25:K28) -> 605.2864 | L29: =SUM(L25:L28) -> 605.2864 | M29: =SUM(M25:M28) -> 605.2864 | ... Q29: =SUM(Q25:Q28) -> 907.9296
C31: total costs for employer | F31: =F22+F29 -> 2250.0864 | G31: =G22+G29 -> 2250.0864 | H31: =H22+H29 -> 2250.0864 | I31: =I22+I29 -> 2250.0864 | J31: =J22+J29 -> 2250.0864 | K31: =K22+K29 -> 2250.0864 | L31: =L22+L29 -> 2250.0864 | M31: =M22+M29 -> 2250.0864 | ... Q31: =Q22+Q29 -> 3375.1296
B33: P3 | C33: IT | E33: per months | F33: Jan | G33: Feb | H33: March | I33: April | J33: May | K33: June | L33: July | M33: August | N33: Sept | O33: Oct | P33: Nov | Q33: Dec
C34: monthly payment | E34: 650 | F34: =$E$34 -> 650 | G34: =$E$34 -> 650 | H34: =$E$34 -> 650 | I34: =$E$34 -> 650 | J34: =$E$34 -> 650 | K34: =$E$34 -> 650 | L34: =$E$34 -> 650 | M34: =$E$34 -> 650 | ... Q34: =$E$34 -> 650
C35: 13th months | E35: 650 | P35: =E35*0.5 -> 325 | Q35: =E35*0.5 -> 325
C36: Vacation Bonus | D36: 0.028 | F36: =(F34+F35)*$D$36 -> 18.2 | G36: =(G34+G35)*$D$36 -> 18.2 | H36: =(H34+H35)*$D$36 -> 18.2 | I36: =(I34+I35)*$D$36 -> 18.2 | J36: =(J34+J35)*$D$36 -> 18.2 | K36: =(K34+K35)*$D$36 -> 18.2 | L36: =(L34+L35)*$D$36 -> 18.2 | M36: =(M34+M35)*$D$36 -> 18.2 | ... Q36: =(Q34+Q35)*$D$36 -> 27.3
C37: total Brutto Income | F37: =SUM(F34:F36) -> 668.2 | G37: =SUM(G34:G36) -> 668.2 | H37: =SUM(H34:H36) -> 668.2 | I37: =SUM(I34:I36) -> 668.2 | J37: =SUM(J34:J36) -> 668.2 | K37: =SUM(K34:K36) -> 668.2 | L37: =SUM(L34:L36) -> 668.2 | M37: =SUM(M34:M36) -> 668.2 | ... Q37: =SUM(Q34:Q36) -> 1002.3
C39: additional payment
C40: Public Pension Fund (INSS) | D40: 0.2 | F40: =F37*$D$40 -> 133.64 | G40: =G37*$D$40 -> 133.64 | H40: =H37*$D$40 -> 133.64 | I40: =I37*$D$40 -> 133.64 | J40: =J37*$D$40 -> 133.64 | K40: =K37*$D$40 -> 133.64 | L40: =L37*$D$40 -> 133.64 | M40: =M37*$D$40 -> 133.64 | ... Q40: =Q37*$D$40 -> 200.46
C41: Severance Fund (FGTS) | D41: 0.08 | F41: =F37*$D$41 -> 53.456 | G41: =G37*$D$41 -> 53.456 | H41: =H37*$D$41 -> 53.456 | I41: =I37*$D$41 -> 53.456 | J41: =J37*$D$41 -> 53.456 | K41: =K37*$D$41 -> 53.456 | L41: =L37*$D$41 -> 53.456 | M41: =M37*$D$41 -> 53.456 | ... Q41: =Q37*$D$41 -> 80.184
C42: Education contribution, INCRA, SENAI, SESI and SEBRAE contributions | D42: 0.058 | F42: =F37*$D$42 -> 38.7556 | G42: =G37*$D$42 -> 38.7556 | H42: =H37*$D$42 -> 38.7556 | I42: =I37*$D$42 -> 38.7556 | J42: =J37*$D$42 -> 38.7556 | K42: =K37*$D$42 -> 38.7556 | L42: =L37*$D$42 -> 38.7556 | M42: =M37*$D$42 -> 38.7556 | ... Q42: =Q37*$D$42 -> 58.1334
C43: Accident Insurance | D43: 0.03 | F43: =F37*$D$43 -> 20.046 | G43: =G37*$D$43 -> 20.046 | H43: =H37*$D$43 -> 20.046 | I43: =I37*$D$43 -> 20.046 | J43: =J37*$D$43 -> 20.046 | K43: =K37*$D$43 -> 20.046 | L43: =L37*$D$43 -> 20.046 | M43: =M37*$D$43 -> 20.046 | ... Q43: =Q37*$D$43 -> 30.069
D44: =SUM(D40:D43) -> 0.368 | F44: =SUM(F40:F43) -> 245.8976 | G44: =SUM(G40:G43) -> 245.8976 | H44: =SUM(H40:H43) -> 245.8976 | I44: =SUM(I40:I43) -> 245.8976 | J44: =SUM(J40:J43) -> 245.8976 | K44: =SUM(K40:K43) -> 245.8976 | L44: =SUM(L40:L43) -> 245.8976 | M44: =SUM(M40:M43) -> 245.8976 | ... Q44: =SUM(Q40:Q43) -> 368.8464
C46: total costs for employer | F46: =F37+F44 -> 914.0976 | G46: =G37+G44 -> 914.0976 | H46: =H37+H44 -> 914.0976 | I46: =I37+I44 -> 914.0976 | J46: =J37+J44 -> 914.0976 | K46: =K37+K44 -> 914.0976 | L46: =L37+L44 -> 914.0976 | M46: =M37+M44 -> 914.0976 | ... Q46: =Q37+Q44 -> 1371.1464
B48: P4 | C48: Production - packaging | E48: per months | F48: Jan | G48: Feb | H48: March | I48: April | J48: May | K48: June | L48: July | M48: August | N48: Sept | O48: Oct | P48: Nov | Q48: Dec
C49: monthly payment | E49: 580 | F49: =$E$49 -> 580 | G49: =$E$49 -> 580 | H49: =$E$49 -> 580 | I49: =$E$49 -> 580 | J49: =$E$49 -> 580 | K49: =$E$49 -> 580 | L49: =$E$49 -> 580 | M49: =$E$49 -> 580 | ... Q49: =$E$49 -> 580
C50: 13th months | E50: 580 | P50: =E50*0.5 -> 290 | Q50: =E50*0.5 -> 290
C51: Vacation Bonus | D51: 0.028 | F51: =(F49+F50)*$D$51 -> 16.24 | G51: =(G49+G50)*$D$51 -> 16.24 | H51: =(H49+H50)*$D$51 -> 16.24 | I51: =(I49+I50)*$D$51 -> 16.24 | J51: =(J49+J50)*$D$51 -> 16.24 | K51: =(K49+K50)*$D$51 -> 16.24 | L51: =(L49+L50)*$D$51 -> 16.24 | M51: =(M49+M50)*$D$51 -> 16.24 | ... Q51: =(Q49+Q50)*$D$51 -> 24.36
C52: total Brutto Income | F52: =SUM(F49:F51) -> 596.24 | G52: =SUM(G49:G51) -> 596.24 | H52: =SUM(H49:H51) -> 596.24 | I52: =SUM(I49:I51) -> 596.24 | J52: =SUM(J49:J51) -> 596.24 | K52: =SUM(K49:K51) -> 596.24 | L52: =SUM(L49:L51) -> 596.24 | M52: =SUM(M49:M51) -> 596.24 | ... Q52: =SUM(Q49:Q51) -> 894.36
C54: additional payment
C55: Public Pension Fund (INSS) | D55: 0.2 | F55: =F52*$D$55 -> 119.248 | G55: =G52*$D$55 -> 119.248 | H55: =H52*$D$55 -> 119.248 | I55: =I52*$D$55 -> 119.248 | J55: =J52*$D$55 -> 119.248 | K55: =K52*$D$55 -> 119.248 | L55: =L52*$D$55 -> 119.248 | M55: =M52*$D$55 -> 119.248 | ... Q55: =Q52*$D$55 -> 178.872
C56: Severance Fund (FGTS) | D56: 0.08 | F56: =F52*$D$56 -> 47.6992 | G56: =G52*$D$56 -> 47.6992 | H56: =H52*$D$56 -> 47.6992 | I56: =I52*$D$56 -> 47.6992 | J56: =J52*$D$56 -> 47.6992 | K56: =K52*$D$56 -> 47.6992 | L56: =L52*$D$56 -> 47.6992 | M56: =M52*$D$56 -> 47.6992 | ... Q56: =Q52*$D$56 -> 71.5488
C57: Education contribution, INCRA, SENAI, SESI and SEBRAE contributions | D57: 0.058 | F57: =F52*$D$57 -> 34.58192 | G57: =G52*$D$57 -> 34.58192 | H57: =H52*$D$57 -> 34.58192 | I57: =I52*$D$57 -> 34.58192 | J57: =J52*$D$57 -> 34.58192 | K57: =K52*$D$57 -> 34.58192 | L57: =L52*$D$57 -> 34.58192 | M57: =M52*$D$57 -> 34.58192 | ... Q57: =Q52*$D$57 -> 51.87288
C58: Accident Insurance | D58: 0.03 | F58: =F52*$D$58 -> 17.8872 | G58: =G52*$D$58 -> 17.8872 | H58: =H52*$D$58 -> 17.8872 | I58: =I52*$D$58 -> 17.8872 | J58: =J52*$D$58 -> 17.8872 | K58: =K52*$D$58 -> 17.8872 | L58: =L52*$D$58 -> 17.8872 | M58: =M52*$D$58 -> 17.8872 | ... Q58: =Q52*$D$58 -> 26.8308
D59: =SUM(D55:D58) -> 0.368 | F59: =SUM(F55:F58) -> 219.41632 | G59: =SUM(G55:G58) -> 219.41632 | H59: =SUM(H55:H58) -> 219.41632 | I59: =SUM(I55:I58) -> 219.41632 | J59: =SUM(J55:J58) -> 219.41632 | K59: =SUM(K55:K58) -> 219.41632 | L59: =SUM(L55:L58) -> 219.41632 | M59: =SUM(M55:M58) -> 219.41632 | ... Q59: =SUM(Q55:Q58) -> 329.12448
C61: total costs for employer | F61: =F52+F59 -> 815.65632 | G61: =G52+G59 -> 815.65632 | H61: =H52+H59 -> 815.65632 | I61: =I52+I59 -> 815.65632 | J61: =J52+J59 -> 815.65632 | K61: =K52+K59 -> 815.65632 | L61: =L52+L59 -> 815.65632 | M61: =M52+M59 -> 815.65632 | ... Q61: =Q52+Q59 -> 1223.4845
B63: P5 | C63: Assistant | E63: per months | F63: Jan | G63: Feb | H63: March | I63: April | J63: May | K63: June | L63: July | M63: August | N63: Sept | O63: Oct | P63: Nov | Q63: Dec
C64: monthly payment | E64: 635 | F64: =$E$64 -> 635 | G64: =$E$64 -> 635 | H64: =$E$64 -> 635 | I64: =$E$64 -> 635 | J64: =$E$64 -> 635 | K64: =$E$64 -> 635 | L64: =$E$64 -> 635 | M64: =$E$64 -> 635 | ... Q64: =$E$64 -> 635
C65: 13th months | E65: 635 | P65: =E65*0.5 -> 317.5 | Q65: =E65*0.5 -> 317.5
C66: Vacation Bonus | D66: 0.028 | F66: =(F64+F65)*$D$66 -> 17.78 | G66: =(G64+G65)*$D$66 -> 17.78 | H66: =(H64+H65)*$D$66 -> 17.78 | I66: =(I64+I65)*$D$66 -> 17.78 | J66: =(J64+J65)*$D$66 -> 17.78 | K66: =(K64+K65)*$D$66 -> 17.78 | L66: =(L64+L65)*$D$66 -> 17.78 | M66: =(M64+M65)*$D$66 -> 17.78 | ... Q66: =(Q64+Q65)*$D$66 -> 26.67
C67: total Brutto Income | F67: =SUM(F64:F66) -> 652.78 | G67: =SUM(G64:G66) -> 652.78 | H67: =SUM(H64:H66) -> 652.78 | I67: =SUM(I64:I66) -> 652.78 | J67: =SUM(J64:J66) -> 652.78 | K67: =SUM(K64:K66) -> 652.78 | L67: =SUM(L64:L66) -> 652.78 | M67: =SUM(M64:M66) -> 652.78 | ... Q67: =SUM(Q64:Q66) -> 979.17
C69: additional payment
C70: Public Pension Fund (INSS) | D70: 0.2 | F70: =F67*$D$70 -> 130.556 | G70: =G67*$D$70 -> 130.556 | H70: =H67*$D$70 -> 130.556 | I70: =I67*$D$70 -> 130.556 | J70: =J67*$D$70 -> 130.556 | K70: =K67*$D$70 -> 130.556 | L70: =L67*$D$70 -> 130.556 | M70: =M67*$D$70 -> 130.556 | ... Q70: =Q67*$D$70 -> 195.834
C71: Severance Fund (FGTS) | D71: 0.08 | F71: =F67*$D$71 -> 52.2224 | G71: =G67*$D$71 -> 52.2224 | H71: =H67*$D$71 -> 52.2224 | I71: =I67*$D$71 -> 52.2224 | J71: =J67*$D$71 -> 52.2224 | K71: =K67*$D$71 -> 52.2224 | L71: =L67*$D$71 -> 52.2224 | M71: =M67*$D$71 -> 52.2224 | ... Q71: =Q67*$D$71 -> 78.3336
C72: Education contribution, INCRA, SENAI, SESI and SEBRAE contributions | D72: 0.058 | F72: =F67*$D$72 -> 37.86124 | G72: =G67*$D$72 -> 37.86124 | H72: =H67*$D$72 -> 37.86124 | I72: =I67*$D$72 -> 37.86124 | J72: =J67*$D$72 -> 37.86124 | K72: =K67*$D$72 -> 37.86124 | L72: =L67*$D$72 -> 37.86124 | M72: =M67*$D$72 -> 37.86124 | ... Q72: =Q67*$D$72 -> 56.79186
C73: Accident Insurance | D73: 0.03 | F73: =F67*$D$73 -> 19.5834 | G73: =G67*$D$73 -> 19.5834 | H73: =H67*$D$73 -> 19.5834 | I73: =I67*$D$73 -> 19.5834 | J73: =J67*$D$73 -> 19.5834 | K73: =K67*$D$73 -> 19.5834 | L73: =L67*$D$73 -> 19.5834 | M73: =M67*$D$73 -> 19.5834 | ... Q73: =Q67*$D$73 -> 29.3751
D74: =SUM(D70:D73) -> 0.368 | F74: =SUM(F70:F73) -> 240.22304 | G74: =SUM(G70:G73) -> 240.22304 | H74: =SUM(H70:H73) -> 240.22304 | I74: =SUM(I70:I73) -> 240.22304 | J74: =SUM(J70:J73) -> 240.22304 | K74: =SUM(K70:K73) -> 240.22304 | L74: =SUM(L70:L73) -> 240.22304 | M74: =SUM(M70:M73) -> 240.22304 | ... Q74: =SUM(Q70:Q73) -> 360.33456
C76: total costs for employer | F76: =F67+F74 -> 893.00304 | G76: =G67+G74 -> 893.00304 | H76: =H67+H74 -> 893.00304 | I76: =I67+I74 -> 893.00304 | J76: =J67+J74 -> 893.00304 | K76: =K67+K74 -> 893.00304 | L76: =L67+L74 -> 893.00304 | M76: =M67+M74 -> 893.00304 | ... Q76: =Q67+Q74 -> 1339.5046
B78: P6 | C78: Order - Distribution | E78: per months | F78: Jan | G78: Feb | H78: March | I78: April | J78: May | K78: June | L78: July | M78: August | N78: Sept | O78: Oct | P78: Nov | Q78: Dec
C79: monthly payment | E79: 635 | F79: =E79 -> 635 | G79: =F79 -> 635 | H79: =G79 -> 635 | I79: =H79 -> 635 | J79: =I79 -> 635 | K79: =J79 -> 635 | L79: =K79 -> 635 | M79: =L79 -> 635 | ... Q79: =P79 -> 635
C80: 13th months | E80: 635 | P80: =E80*0.5 -> 317.5 | Q80: =E80*0.5 -> 317.5
C81: Vacation Bonus | D81: 0.028 | F81: =(F79+F80)*$D$66 -> 17.78 | G81: =(G79+G80)*$D$66 -> 17.78 | H81: =(H79+H80)*$D$66 -> 17.78 | I81: =(I79+I80)*$D$66 -> 17.78 | J81: =(J79+J80)*$D$66 -> 17.78 | K81: =(K79+K80)*$D$66 -> 17.78 | L81: =(L79+L80)*$D$66 -> 17.78 | M81: =(M79+M80)*$D$66 -> 17.78 | ... Q81: =(Q79+Q80)*$D$66 -> 26.67
C82: total Brutto Income | F82: =SUM(F79:F81) -> 652.78 | G82: =SUM(G79:G81) -> 652.78 | H82: =SUM(H79:H81) -> 652.78 | I82: =SUM(I79:I81) -> 652.78 | J82: =SUM(J79:J81) -> 652.78 | K82: =SUM(K79:K81) -> 652.78 | L82: =SUM(L79:L81) -> 652.78 | M82: =SUM(M79:M81) -> 652.78 | ... Q82: =SUM(Q79:Q81) -> 979.17
C84: additional payment
C85: Public Pension Fund (INSS) | D85: 0.2 | F85: =F82*$D$70 -> 130.556 | G85: =G82*$D$70 -> 130.556 | H85: =H82*$D$70 -> 130.556 | I85: =I82*$D$70 -> 130.556 | J85: =J82*$D$70 -> 130.556 | K85: =K82*$D$70 -> 130.556 | L85: =L82*$D$70 -> 130.556 | M85: =M82*$D$70 -> 130.556 | ... Q85: =Q82*$D$70 -> 195.834
C86: Severance Fund (FGTS) | D86: 0.08 | F86: =F82*$D$71 -> 52.2224 | G86: =G82*$D$71 -> 52.2224 | H86: =H82*$D$71 -> 52.2224 | I86: =I82*$D$71 -> 52.2224 | J86: =J82*$D$71 -> 52.2224 | K86: =K82*$D$71 -> 52.2224 | L86: =L82*$D$71 -> 52.2224 | M86: =M82*$D$71 -> 52.2224 | ... Q86: =Q82*$D$71 -> 78.3336
C87: Education contribution, INCRA, SENAI, SESI and SEBRAE contributions | D87: 0.058 | F87: =F82*$D$72 -> 37.86124 | G87: =G82*$D$72 -> 37.86124 | H87: =H82*$D$72 -> 37.86124 | I87: =I82*$D$72 -> 37.86124 | J87: =J82*$D$72 -> 37.86124 | K87: =K82*$D$72 -> 37.86124 | L87: =L82*$D$72 -> 37.86124 | M87: =M82*$D$72 -> 37.86124 | ... Q87: =Q82*$D$72 -> 56.79186
C88: Accident Insurance | D88: 0.03 | F88: =F82*$D$73 -> 19.5834 | G88: =G82*$D$73 -> 19.5834 | H88: =H82*$D$73 -> 19.5834 | I88: =I82*$D$73 -> 19.5834 | J88: =J82*$D$73 -> 19.5834 | K88: =K82*$D$73 -> 19.5834 | L88: =L82*$D$73 -> 19.5834 | M88: =M82*$D$73 -> 19.5834 | ... Q88: =Q82*$D$73 -> 29.3751
D89: =SUM(D85:D88) -> 0.368 | F89: =SUM(F85:F88) -> 240.22304 | G89: =SUM(G85:G88) -> 240.22304 | H89: =SUM(H85:H88) -> 240.22304 | I89: =SUM(I85:I88) -> 240.22304 | J89: =SUM(J85:J88) -> 240.22304 | K89: =SUM(K85:K88) -> 240.22304 | L89: =SUM(L85:L88) -> 240.22304 | M89: =SUM(M85:M88) -> 240.22304 | ... Q89: =SUM(Q85:Q88) -> 360.33456
C91: total costs for employer | F91: =F82+F89 -> 893.00304 | G91: =G82+G89 -> 893.00304 | H91: =H82+H89 -> 893.00304 | I91: =I82+I89 -> 893.00304 | J91: =J82+J89 -> 893.00304 | K91: =K82+K89 -> 893.00304 | L91: =L82+L89 -> 893.00304 | M91: =M82+M89 -> 893.00304 | ... Q91: =Q82+Q89 -> 1339.5046
B93: P7 | C93: Security | E93: per months | F93: Jan | G93: Feb | H93: March | I93: April | J93: May | K93: June | L93: July | M93: August | N93: Sept | O93: Oct | P93: Nov | Q93: Dec
C94: monthly payment | E94: 635 | F94: =E94 -> 635 | G94: =F94 -> 635 | H94: =G94 -> 635 | I94: =H94 -> 635 | J94: =I94 -> 635 | K94: =J94 -> 635 | L94: =K94 -> 635 | M94: =L94 -> 635 | ... Q94: =P94 -> 635
C95: 13th months | E95: 635 | P95: =E95*0.5 -> 317.5 | Q95: =E95*0.5 -> 317.5
C96: Vacation Bonus | D96: 0.028 | F96: =(F94+F95)*$D$66 -> 17.78 | G96: =(G94+G95)*$D$66 -> 17.78 | H96: =(H94+H95)*$D$66 -> 17.78 | I96: =(I94+I95)*$D$66 -> 17.78 | J96: =(J94+J95)*$D$66 -> 17.78 | K96: =(K94+K95)*$D$66 -> 17.78 | L96: =(L94+L95)*$D$66 -> 17.78 | M96: =(M94+M95)*$D$66 -> 17.78 | ... Q96: =(Q94+Q95)*$D$66 -> 26.67
C97: total Brutto Income | F97: =SUM(F94:F96) -> 652.78 | G97: =SUM(G94:G96) -> 652.78 | H97: =SUM(H94:H96) -> 652.78 | I97: =SUM(I94:I96) -> 652.78 | J97: =SUM(J94:J96) -> 652.78 | K97: =SUM(K94:K96) -> 652.78 | L97: =SUM(L94:L96) -> 652.78 | M97: =SUM(M94:M96) -> 652.78 | ... Q97: =SUM(Q94:Q96) -> 979.17
C99: additional payment
C100: Public Pension Fund (INSS) | D100: 0.2 | F100: =F97*$D$70 -> 130.556 | G100: =G97*$D$70 -> 130.556 | H100: =H97*$D$70 -> 130.556 | I100: =I97*$D$70 -> 130.556 | J100: =J97*$D$70 -> 130.556 | K100: =K97*$D$70 -> 130.556 | L100: =L97*$D$70 -> 130.556 | M100: =M97*$D$70 -> 130.556 | ... Q100: =Q97*$D$70 -> 195.834
C101: Severance Fund (FGTS) | D101: 0.08 | F101: =F97*$D$71 -> 52.2224 | G101: =G97*$D$71 -> 52.2224 | H101: =H97*$D$71 -> 52.2224 | I101: =I97*$D$71 -> 52.2224 | J101: =J97*$D$71 -> 52.2224 | K101: =K97*$D$71 -> 52.2224 | L101: =L97*$D$71 -> 52.2224 | M101: =M97*$D$71 -> 52.2224 | ... Q101: =Q97*$D$71 -> 78.3336
C102: Education contribution, INCRA, SENAI, SESI and SEBRAE contributions | D102: 0.058 | F102: =F97*$D$72 -> 37.86124 | G102: =G97*$D$72 -> 37.86124 | H102: =H97*$D$72 -> 37.86124 | I102: =I97*$D$72 -> 37.86124 | J102: =J97*$D$72 -> 37.86124 | K102: =K97*$D$72 -> 37.86124 | L102: =L97*$D$72 -> 37.86124 | M102: =M97*$D$72 -> 37.86124 | ... Q102: =Q97*$D$72 -> 56.79186
C103: Accident Insurance | D103: 0.03 | F103: =F97*$D$73 -> 19.5834 | G103: =G97*$D$73 -> 19.5834 | H103: =H97*$D$73 -> 19.5834 | I103: =I97*$D$73 -> 19.5834 | J103: =J97*$D$73 -> 19.5834 | K103: =K97*$D$73 -> 19.5834 | L103: =L97*$D$73 -> 19.5834 | M103: =M97*$D$73 -> 19.5834 | ... Q103: =Q97*$D$73 -> 29.3751
D104: =SUM(D100:D103) -> 0.368 | F104: =SUM(F100:F103) -> 240.22304 | G104: =SUM(G100:G103) -> 240.22304 | H104: =SUM(H100:H103) -> 240.22304 | I104: =SUM(I100:I103) -> 240.22304 | J104: =SUM(J100:J103) -> 240.22304 | K104: =SUM(K100:K103) -> 240.22304 | L104: =SUM(L100:L103) -> 240.22304 | M104: =SUM(M100:M103) -> 240.22304 | ... Q104: =SUM(Q100:Q103) -> 360.33456
